Workbook

Sheet 00_Bìa
A1: FPTPost – Bộ đặc tả yêu cầu và thiết kế hệ thống
A2: Nền tảng giao hàng cowork ngang hàng (P2P) • Tài liệu đặc tả nghiệp vụ • Ngôn ngữ: tiếng Việt • Phiên bản 1.0
A4: 1. Thông tin tài liệu
A5: Dự án | B5: FPTPost
A6: Môn học | B6: SBA301 – Tích hợp ứng dụng trang đơn với Spring Boot
A7: Nhóm | B7: 6 thành viên (Lead: Lư Hữu Luân), 5 tuần, 5 sprint (10/10/2026 – 14/11/2026)
A8: Ngày lập | B8: 08/10/2026
A9: Trạng thái | B9: Dự thảo v1.0 – chờ nhóm rà soát
A10: Tài liệu đi kèm | B10: FPTPost – Tài liệu thiết kế hệ thống (SPEC): tài liệu Claude Docs, xuất được sang Word/PDF; thiết kế kỹ thuật cho nhóm phát triển, không lặp lại nội dung của bảng tính này
A12: 2. Lịch sử phiên bản
A13: Phiên bản | B13: Nội dung thay đổi | C13: Ngày | D13: Người lập
A14: 1.0 | B14: Khởi tạo bộ đặc tả: BR, UC, tham số, dữ liệu, API, màn hình, đánh giá VNPay, kế hoạch | C14: 08/10/2026 | D14: Nhóm FPTPost
A16: 3. Số liệu tổng hợp (tính tự động từ các sheet)
A17: Chỉ tiêu | B17: Diễn giải | C17: Giá trị
A18: Tổng số BR | B18: Mọi loại yêu cầu nghiệp vụ | C18: =COUNTIF('03_BR'!A:A,"BR-*") -> 286
A19: Functional BR | B19: Yêu cầu chức năng | C19: =COUNTIF('03_BR'!B:B,"Functional BR") -> 124
A20: Non-functional BR | B20: Yêu cầu phi chức năng | C20: =COUNTIF('03_BR'!B:B,"Non-functional BR") -> 41
A21: Business Rule | B21: Quy tắc nghiệp vụ | C21: =COUNTIF('03_BR'!B:B,"Business Rule") -> 85
A22: Business Constraint | B22: Ràng buộc | C22: =COUNTIF('03_BR'!B:B,"Business Constraint") -> 22
A23: Business Goal | B23: Mục tiêu kinh doanh | C23: =COUNTIF('03_BR'!B:B,"Business Goal") -> 14
A24: BR mức Must / Should / Could | B24: Theo MoSCoW | C24: =COUNTIF('03_BR'!H:H,"Must")&" / "&COUNTIF('03_BR'!H:H,"Should")&" / "&COUNTIF('03_BR'!H:H,"Could") -> 213 / 50 / 23
A25: Tổng số Use Case | B25: UC mô tả ở sheet 04 | C25: =COUNTIF('04_UC'!A:A,"UC-*") -> 63
A26: UC mức Must / Should / Could | B26: Theo MoSCoW | C26: =COUNTIF('04_UC'!F:F,"Must")&" / "&COUNTIF('04_UC'!F:F,"Should")&" / "&COUNTIF('04_UC'!F:F,"Could") -> 50 / 6 / 7
A27: Tổng giờ ước lượng UC (BE+FE) | B27: Gồm cả Could | C27: =SUM('04_UC'!Q:Q) -> 474
A28: Giờ ước lượng UC Must + Should | B28: Không gồm Could | C28: =SUMIFS('04_UC'!Q:Q,'04_UC'!F:F,"<>Could") -> 420
A29: Tham số nghiệp vụ | B29: Sheet 06 | C29: =COUNTIF('06_Tham_số'!A:A,"PRM-*") -> 109
A30: Thực thể dữ liệu | B30: Sheet 09 | C30: =COUNTIF('09_Dữ_liệu'!A:A,"DB-*") -> 55
A31: Endpoint API | B31: Sheet 10 | C31: =COUNTIF('10_API'!A:A,"API-*") -> 167
A32: Màn hình | B32: Sheet 11 | C32: =COUNTIF('11_Màn_hình'!A:A,"SCR-*") -> 64
A33: Rủi ro đã nhận diện | B33: Sheet 16 | C33: =COUNTIF('16_Rủi_ro'!A:A,"R-*") -> 24
A34: UC chưa có BR chức năng/quy tắc | B34: Kiểm tra độ phủ, mong đợi = 0 | C34: =SUMPRODUCT(--(('05_Truy_vết'!E5:E67+'05_Truy_vết'!G5:G67)=0)) -> 0
A35: Mức sử dụng công suất toàn đội | B35: Từ sheet 13 (UC + việc chung + họp) | C35: ='13_Kế_hoạch_Nhân_sự'!G21 -> 0.97777778
A37: 4. Danh mục sheet
A38: Sheet | B38: Nội dung
A39: 01_Tổng_quan | B39: Tầm nhìn, phạm vi, giá trị khác biệt, bên liên quan, giả định
A40: 02_Tác_nhân_Phân_quyền | B40: Tác nhân và ma trận phân quyền theo vai trò
A41: 03_BR | B41: Toàn bộ BR (Functional, Non-functional, Business Rule, Constraint, Goal) kèm tiêu chí nghiệm thu
A42: 04_UC | B42: 63 Use Case: luồng chính, ngoại lệ, người phụ trách, ước lượng giờ, sprint
A43: 05_Truy_vết | B43: Ma trận truy vết UC ↔ BR ↔ màn hình ↔ API và số liệu độ phủ
A44: 06_Tham_số | B44: Tham số nghiệp vụ có thể cấu hình (mọi con số trong BR lấy từ đây)
A45: 07_Biểu_phí_Mô_phỏng | B45: Công cụ mô phỏng giá, hoa hồng và 20 ca kiểm thử công thức
A46: 08_Trạng_thái | B46: Danh mục trạng thái và bảng chuyển trạng thái
A47: 09_Dữ_liệu | B47: Từ điển dữ liệu mức thực thể (SQL Server và MongoDB)
A48: 10_API | B48: Danh mục endpoint REST và kênh WebSocket
A49: 11_Màn_hình | B49: Danh mục màn hình frontend
... A55: 17_Thuật_ngữ | B55: Thuật ngữ và viết tắt kỹ thuật/nghiệp vụ
A56: 5. Quy ước
A57: Mã BR | B57: BR-F-xxx (Functional), BR-N-xxx (Non-functional), BR-R-xxx (Business Rule), BR-C-xxx (Constraint), BR-G-xxx (Goal)
A58: Mã UC / SCR / API / DB / PRM | B58: UC-xx, SCR-xx, API-xxx, DB-xxx, PRM-xxx; mã tham số được trích dẫn trong ngoặc vuông [PRM-xxx] ở phần mô tả BR
A59: MoSCoW và Pha | B59: Must = Pha 1 (MVP); Should = Pha 2; Could = Pha 3 (làm khi còn công suất)
A60: Ô nhập liệu | B60: Chữ xanh dương trên nền vàng nhạt là ô nhập; công thức màu đen tính tự động
A61: Tiền tệ | B61: VND, số nguyên; ký hiệu đ
A63: 6. Mã phân hệ
A64: Mã | B64: Tên phân hệ | C64: Số BR | D64: Số UC
A65: AUTH | B65: Tài khoản & Xác thực | C65: =COUNTIFS('03_BR'!C:C,A65,'03_BR'!A:A,"BR-*") -> 18 | D65: =COUNTIFS('04_UC'!C:C,A65,'04_UC'!A:A,"UC-*") -> 6
A66: KYC | B66: Xác minh & Hồ sơ | C66: =COUNTIFS('03_BR'!C:C,A66,'03_BR'!A:A,"BR-*") -> 16 | D66: =COUNTIFS('04_UC'!C:C,A66,'04_UC'!A:A,"UC-*") -> 4
A67: ORD | B67: Đơn hàng | C67: =COUNTIFS('03_BR'!C:C,A67,'03_BR'!A:A,"BR-*") -> 25 | D67: =COUNTIFS('04_UC'!C:C,A67,'04_UC'!A:A,"UC-*") -> 5
A68: MKT | B68: Sàn đơn & Ghép đơn | C68: =COUNTIFS('03_BR'!C:C,A68,'03_BR'!A:A,"BR-*") -> 20 | D68: =COUNTIFS('04_UC'!C:C,A68,'04_UC'!A:A,"UC-*") -> 6
A69: TRP | B69: Chuyến đi | C69: =COUNTIFS('03_BR'!C:C,A69,'03_BR'!A:A,"BR-*") -> 8 | D69: =COUNTIFS('04_UC'!C:C,A69,'04_UC'!A:A,"UC-*") -> 2
A70: NEG | B70: Thương lượng & Chat | C70: =COUNTIFS('03_BR'!C:C,A70,'03_BR'!A:A,"BR-*") -> 8 | D70: =COUNTIFS('04_UC'!C:C,A70,'04_UC'!A:A,"UC-*") -> 1
A71: TRK | B71: Theo dõi & Giao nhận | C71: =COUNTIFS('03_BR'!C:C,A71,'03_BR'!A:A,"BR-*") -> 23 | D71: =COUNTIFS('04_UC'!C:C,A71,'04_UC'!A:A,"UC-*") -> 6
A72: REL | B72: Giao tiếp sức & Gộp đơn | C72: =COUNTIFS('03_BR'!C:C,A72,'03_BR'!A:A,"BR-*") -> 9 | D72: =COUNTIFS('04_UC'!C:C,A72,'04_UC'!A:A,"UC-*") -> 3
A73: PAY | B73: Ví & Thanh toán | C73: =COUNTIFS('03_BR'!C:C,A73,'03_BR'!A:A,"BR-*") -> 51 | D73: =COUNTIFS('04_UC'!C:C,A73,'04_UC'!A:A,"UC-*") -> 10
A74: FEE | B74: Giá, Phí & Khuyến mãi | C74: =COUNTIFS('03_BR'!C:C,A74,'03_BR'!A:A,"BR-*") -> 11 | D74: =COUNTIFS('04_UC'!C:C,A74,'04_UC'!A:A,"UC-*") -> 2
A75: REP | B75: Uy tín & Đánh giá | C75: =COUNTIFS('03_BR'!C:C,A75,'03_BR'!A:A,"BR-*") -> 12 | D75: =COUNTIFS('04_UC'!C:C,A75,'04_UC'!A:A,"UC-*") -> 3
A76: DSP | B76: Khiếu nại & Bảo đảm | C76: =COUNTIFS('03_BR'!C:C,A76,'03_BR'!A:A,"BR-*") -> 11 | D76: =COUNTIFS('04_UC'!C:C,A76,'04_UC'!A:A,"UC-*") -> 3
... A81: SYS | B81: Hệ thống chung | C81: =COUNTIFS('03_BR'!C:C,A81,'03_BR'!A:A,"BR-*") -> 43 | D81: =COUNTIFS('04_UC'!C:C,A81,'04_UC'!A:A,"UC-*") -> 0

Sheet 01_Tổng_quan
A1: Tổng quan dự án
A2: Tầm nhìn, phạm vi, giá trị khác biệt, bên liên quan, giả định
A4: 1. Thông tin dự án
A5: Tên dự án | B5: FPTPost – nền tảng giao hàng cowork ngang hàng (P2P)
A6: Mã dự án | B6: FPTPOST
A7: Mô tả ngắn | B7: Nền tảng kết nối người có hàng cần gửi với người sẵn sàng giao hàng tiện đường, không qua nhà phân phối; nền tảng chịu trách nhiệm xác minh, ký quỹ, theo dõi và thanh toán với phí hoa hồng thấp.
A8: Môn học | B8: SBA301 – Tích hợp ứng dụng trang đơn với Spring Boot (đồ án nhóm chiếm 25% điểm; phải bao phủ toàn bộ CLO)
A9: Thời gian | B9: 5 tuần (10/10/2026 – 14/11/2026), chia 5 sprint, mỗi sprint 1 tuần
A10: Quy mô nhóm | B10: 6 thành viên (Lead: Lư Hữu Luân), phụ trách theo lát cắt dọc (backend + frontend)
A11: Công nghệ chính | B11: Java 21, Spring Boot 3, Spring Security (JWT), Spring Data JPA/Hibernate với SQL Server, Spring Data MongoDB, ReactJS (Node 21) + React-Bootstrap, WebSocket, Docker
A12: Thanh toán | B12: VNPay (sandbox) cho thu tiền và hoàn tiền; rút tiền qua PayoutProvider (xem sheet 12_VNPay)
A13: Phiên bản tài liệu | B13: 1.0 – khởi tạo (08/10/2026)
A14: Phạm vi địa lý khởi điểm (giả định) | B14: Cộng đồng FPT (sinh viên, giảng viên, nhân viên) và khu vực lân cận campus; kiến trúc cho phép mở rộng toàn thành phố
A16: 2. Tầm nhìn và vấn đề
A17: Tầm nhìn | B17: Biến mỗi chuyến đi hằng ngày thành một cơ hội giao hàng: người có hàng gửi nhanh và rẻ hơn, người đi đường có thêm thu nhập, và mọi giao dịch đều minh bạch, được bảo chứng bởi nền tảng.
A18: Vấn đề cần giải quyết | B18: Chi phí và thời gian giao hàng qua đơn vị vận chuyển truyền thống cao; nhiều người có sẵn chuyến đi nhưng thiếu kênh an toàn để nhận giao hàng; giao dịch tự phát trên mạng xã hội thiếu niềm tin, không theo dõi được và dễ lừa đảo.
A20: 3. Giá trị khác biệt của FPTPost
A21: Điểm khác biệt | B21: Mô tả | C21: UC chính | D21: BR tham chiếu
A22: Giao tiện đường (trip-based matching) | B22: Người giao đăng chuyến đi; hệ thống gợi ý đơn nằm dọc tuyến, giảm chi phí cho cả hai bên. | C22: UC-21, UC-22, UC-23 | D22: BR-F ghép đơn; BR-R điều kiện ghép đơn–chuyến
A23: Ký quỹ và xác nhận bằng OTP/QR | B23: Tiền được giữ cho đến khi người nhận xác nhận, giải quyết bài toán niềm tin giữa người lạ. | C23: UC-35, UC-36, UC-25, UC-28 | D23: BR-R điều kiện ký quỹ và giải ngân
A24: Điểm uy tín và hạng thành viên | B24: Hạng quyết định hoa hồng, hạn mức đơn và quyền nhận hàng giá trị cao. | C24: UC-49, UC-48 | D24: BR-R công thức điểm uy tín, hạng
A25: Hoa hồng thấp, minh bạch | B25: Hoa hồng 4–8% phí giao, chỉ thu từ người giao; người gửi không trả phí nền tảng. | C25: UC-36, UC-46 | D25: BR-R hoa hồng theo hạng
A26: Thương lượng giá có biên | B26: Người giao chào giá trong biên quanh giá gợi ý, tránh chặt chém và tránh giá phi thực tế. | C26: UC-18, UC-19 | D26: BR-R biên giá chào
A27: Giao tiếp sức (relay) | B27: Chia đơn đường dài thành nhiều chặng, mỗi người giao một đoạn tiện đường (giai đoạn mở rộng). | C27: UC-32, UC-33 | D27: BR-R quy tắc đơn tiếp sức
A28: Bằng chứng giao nhận và Quỹ bảo đảm | B28: Ảnh, mã xác nhận, vị trí làm chứng cứ; quỹ bảo đảm bồi thường cho đơn có bảo hiểm. | C28: UC-25, UC-28, UC-52 | D28: BR-R điều kiện bồi thường
A29: Cộng đồng tin cậy FPT | B29: Huy hiệu Cộng đồng FPT, điểm hẹn bàn giao an toàn quanh campus. | C29: UC-07, UC-33 | D29: BR-R huy hiệu cộng đồng FPT
A31: 4. Mô hình doanh thu và chi phí (trích từ tham số)
A32: Nguồn thu chính | B32: Hoa hồng thu từ người giao, tính trên phí giao: Tân binh 8% [PRM-042], Đồng 7% [PRM-043], Bạc 6% [PRM-044], Vàng 5% [PRM-045], Kim cương 4% [PRM-046].
A33: Người gửi | B33: Không trả phí nền tảng; chỉ trả phí giao và bảo hiểm tùy chọn (1% [PRM-047] giá trị khai báo).
A34: Phí rút tiền | B34: Miễn phí 4 lần [PRM-062]; từ lần kế tiếp 5.000đ [PRM-063]/lần.
A35: Quỹ bảo đảm | B35: Trích 10% [PRM-049] hoa hồng và toàn bộ phí bảo hiểm để bồi thường đơn có bảo hiểm.
A36: Khuyến mãi | B36: Chi phí do nền tảng chịu, không làm giảm thu nhập người giao.
A37: Mô phỏng | B37: Xem sheet 07 để thử các kịch bản giá, hoa hồng và dòng tiền.
A39: 5. Phạm vi
A40: Giai đoạn / loại | B40: Nội dung
A41: Giai đoạn 1 (MVP – Must) | B41: Tài khoản, KYC, tạo đơn, sàn đơn, nhận đơn/chào giá, chat, ký quỹ qua ví và VNPay, lấy/giao bằng QR/OTP, theo dõi, giải ngân, hoàn tiền, rút tiền, khiếu nại, kiểm duyệt, quản trị cơ bản.
A42: Giai đoạn 2 (Should) | B42: Chuyến đi và gợi ý ghép đơn–chuyến, hoàn tiền về nguồn VNPay, đối soát, thu nhập và thống kê, nhật ký kiểm toán, SOS.
A43: Giai đoạn 3 (Could – làm khi còn công suất) | B43: Mời trực tiếp, khuyến mãi, huy hiệu/giới thiệu bạn bè, gộp đơn, giao tiếp sức, Web Push.
A44: Ngoài phạm vi | B44: Ứng dụng di động native (chỉ web responsive/PWA nếu còn thời gian).
B45: Thu hộ tiền hàng (COD) và thanh toán tiền mặt cho phí giao.
B46: Vận chuyển quốc tế, hàng quá khổ/quá tải, hàng cần bảo quản lạnh hoặc hàng nguy hiểm.
B47: Tích hợp với hãng vận chuyển thương mại hoặc kho bãi.
B48: Xác minh danh tính tự động bằng AI (eKYC máy); giai đoạn này duyệt thủ công.
B49: Chi trả tiền thật qua nhà cung cấp chi hộ (bản đồ án dùng Mock/thủ công).
B50: Hóa đơn điện tử và kê khai thuế tự động (chỉ hỗ trợ dữ liệu doanh thu theo người giao).
A52: 6. Các bên liên quan
A53: Bên liên quan | B53: Vai trò và kỳ vọng | C53: Mức ảnh hưởng
A54: Nhóm phát triển (Product Owner & Team) | B54: Quyết định phạm vi, thiết kế và phát triển; chịu trách nhiệm chất lượng. | C54: Cao
A55: Giảng viên / hội đồng đánh giá | B55: Đánh giá mức độ đạt CLO, chất lượng sản phẩm và tài liệu. | C55: Cao
A56: Người gửi | B56: Người dùng trả phí giao; yêu cầu an toàn, rẻ, dễ dùng. | C56: Cao
A57: Người giao | B57: Người dùng tạo giá trị cung ứng; yêu cầu thu nhập rõ ràng, rút tiền nhanh. | C57: Cao
A58: Người nhận | B58: Nhận hàng; yêu cầu thông tin theo dõi chính xác, không phải đăng ký. | C58: Trung bình
A59: Vận hành (Admin, Kiểm duyệt) | B59: Giữ nền tảng an toàn, xử lý tranh chấp và rút tiền. | C59: Cao
A60: VNPay | B60: Đối tác thanh toán; ràng buộc quy trình tích hợp và kiểm thử. | C60: Trung bình
A61: Cơ quan quản lý (Ngân hàng Nhà nước, cơ quan thuế, cơ quan bảo vệ dữ liệu) | B61: Quy định ví/trung gian thanh toán, thuế, dữ liệu cá nhân; ảnh hưởng điều kiện thương mại hóa. | C61: Cao (khi thương mại hóa)
A63: 7. Giả định và phụ thuộc
A64: Loại | B64: Nội dung
A65: Giả định | B65: Mỗi thành viên dành khoảng 24 giờ/tuần cho dự án trong lộ trình 5 tuần (tổng công suất 120 giờ/người, 720 giờ toàn đội); ước lượng giờ ở sheet 04_UC dựa trên giả định này và được điều chỉnh cân bằng ở sheet 13.
A66: Giả định | B66: Người dùng pilot chủ yếu là sinh viên/nhân viên cộng đồng FPT, quen dùng ứng dụng web trên điện thoại.
A67: Giả định | B67: VNPay sandbox khả dụng suốt thời gian phát triển; IPN nhận được thông qua tunnel công khai khi phát triển.
A68: Giả định | B68: Dịch vụ OpenStreetMap/định tuyến miễn phí đủ cho lưu lượng pilot; có phương án dự phòng.
A69: Giả định | B69: Trong bản đồ án, tiền là tiền thử nghiệm (sandbox); không có giao dịch tiền thật.
A70: Phụ thuộc | B70: Hoàn thành đăng ký tài khoản sandbox VNPay trong sprint 1.
A71: Phụ thuộc | B71: Quy trình duyệt KYC thủ công cần ít nhất 2 người đóng vai Kiểm duyệt khi demo.
A72: Phụ thuộc | B72: Hai Admin khác nhau để thực hiện luồng duyệt rút tiền hai cấp.
A73: Phụ thuộc | B73: Thẩm định pháp lý trước khi thương mại hóa (ví/ký quỹ, bưu chính, thuế, dữ liệu cá nhân).

Sheet 02_Tác_nhân_Phân_quyền
A1: Tác nhân và phân quyền
A2: Danh sách tác nhân; ma trận phân quyền theo vai trò (RBAC)
A4: 1. Danh sách tác nhân
A5: Mã | B5: Tác nhân | C5: Loại | D5: Mô tả | F5: Mục tiêu chính | H5: UC tham gia
A6: A01 | B6: Khách vãng lai (Guest) | C6: Người dùng | D6: Người chưa đăng nhập, truy cập trang công khai và ước tính giá. | F6: Tìm hiểu dịch vụ, ước tính giá, đăng ký. | H6: UC-01
A7: A02 | B7: Người gửi (Sender) | C7: Người dùng | D7: Cá nhân có hàng cần gửi; tạo đơn, chọn người giao, ký quỹ và theo dõi. | F7: Gửi hàng nhanh, rẻ, an toàn và minh bạch. | H7: UC-11, UC-12, UC-14, UC-15, UC-17, UC-18, UC-19, UC-20, UC-21, UC-25, UC-27, UC-29, UC-30, UC-32, UC-35, UC-37, UC-44, UC-51
A8: A03 | B8: Người giao (Courier / Cowork) | C8: Người dùng | D8: Cá nhân đã xác minh, nhận giao hàng tiện đường hoặc theo đơn để có thêm thu nhập. | F8: Có đơn phù hợp tuyến, thu nhập rõ ràng, rút tiền dễ. | H8: UC-15, UC-16, UC-17, UC-18, UC-19, UC-20, UC-21, UC-22, UC-23, UC-25, UC-26, UC-28, UC-29, UC-30, UC-31, UC-32, UC-33, UC-36, UC-39, UC-40, UC-51, UC-61
A9: A04 | B9: Người nhận (Recipient) | C9: Người dùng ngoài hệ thống | D9: Người nhận hàng; không cần tài khoản, tương tác qua liên kết theo dõi và OTP/QR. | F9: Biết hàng đang ở đâu và nhận đúng hàng. | H9: UC-27, UC-28
A10: A05 | B10: Kiểm duyệt viên (Moderator) | C10: Nhân sự nội bộ | D10: Duyệt KYC, kiểm duyệt đơn, xử lý khiếu nại và báo cáo vi phạm. | F10: Giữ nền tảng an toàn, xử lý tranh chấp công bằng. | H10: UC-09, UC-29, UC-51, UC-54, UC-55
A11: A06 | B11: Quản trị viên (Admin) | C11: Nhân sự nội bộ | D11: Cấu hình hệ thống, duyệt rút tiền, đối soát, quản lý người dùng và báo cáo. | F11: Vận hành ổn định, kiểm soát rủi ro tài chính. | H11: UC-41, UC-43, UC-45, UC-46, UC-52, UC-56, UC-57, UC-58, UC-59, UC-60, UC-63
A12: A07 | B12: Hệ thống (Scheduler/System) | C12: Hệ thống | D12: Tác nhân tự động theo thời gian hoặc sự kiện: hết hạn, giải ngân, đối soát, tính điểm. | F12: Thực thi quy tắc nghiệp vụ chính xác, đúng hạn. | H12: UC-21, UC-36, UC-37, UC-42, UC-43, UC-49, UC-54, UC-63
A13: A08 | B13: Cổng thanh toán VNPay | C13: Hệ thống ngoài | D13: Cung cấp thanh toán trực tuyến, IPN, truy vấn và hoàn tiền. | F13: Thu tiền và hoàn tiền an toàn. | H13: UC-34, UC-35, UC-37, UC-42
A14: A09 | B14: Dịch vụ bản đồ và định tuyến | C14: Hệ thống ngoài | D14: OpenStreetMap/Leaflet cho hiển thị, dịch vụ định tuyến và geocoding. | F14: Tính quãng đường và hiển thị bản đồ. | H14: UC-11, UC-12, UC-22
A15: A10 | B15: Dịch vụ Email/SMS | C15: Hệ thống ngoài | D15: Gửi OTP và thông báo qua email/SMS (SMTP, SMS giả lập khi phát triển). | F15: Gửi thông báo tin cậy. | H15: UC-01, UC-02, UC-05, UC-53
A16: A11 | B16: Dịch vụ chi trả (PayoutProvider) | C16: Hệ thống ngoài/nội bộ | D16: Mock, thủ công hoặc nhà cung cấp chi hộ thật dùng để chuyển tiền rút về ngân hàng. | F16: Chuyển tiền rút cho người giao. | H16: UC-41
A18: 2. Ma trận phân quyền (RBAC)
A19: STT | B19: Chức năng | C19: UC | D19: Khách | E19: Người gửi | F19: Người giao | G19: Người nhận | H19: Kiểm duyệt | I19: Admin
A20: 1 | B20: Xem trang giới thiệu, điều khoản, FAQ | C20: — | D20: ✔ | E20: ✔ | F20: ✔ | G20: ✔ | H20: ✔ | I20: ✔
A21: 2 | B21: Ước tính giá giao hàng | C21: UC-11 | D21: ✔ | E21: ✔ | F21: ✔ | G21: — | H21: — | I21: ✔
A22: 3 | B22: Đăng ký tài khoản, xác thực OTP | C22: UC-01, UC-02 | D22: ✔ | E22: — | F22: — | G22: — | H22: — | I22: —
A23: 4 | B23: Đăng nhập, đăng xuất, quên/đổi mật khẩu | C23: UC-03..06 | D23: ✔ | E23: ✔ | F23: ✔ | G23: — | H23: ✔ | I23: ✔
A24: 5 | B24: Quản lý hồ sơ cá nhân, sổ địa chỉ | C24: UC-07 | D24: — | E24: Của mình | F24: Của mình | G24: — | H24: Của mình | I24: Của mình
A25: 6 | B25: Gửi hồ sơ xác minh KYC | C25: UC-08 | D25: — | E25: ✔ | F25: ✔ | G25: — | H25: — | I25: —
A26: 7 | B26: Duyệt hồ sơ KYC | C26: UC-09 | D26: — | E26: — | F26: — | G26: — | H26: ✔ | I26: ✔
A27: 8 | B27: Đăng ký làm Người giao | C27: UC-10 | D27: — | E27: ✔ | F27: — | G27: — | H27: — | I27: —
A28: 9 | B28: Tạo, sửa đơn | C28: UC-12, UC-14 | D28: — | E28: Của mình | F28: — | G28: — | H28: — | I28: —
A29: 10 | B29: Hủy đơn | C29: UC-15 | D29: — | E29: Của mình | F29: Của mình | G29: — | H29: — | I29: ✔
A30: 11 | B30: Xem danh sách và chi tiết đơn | C30: UC-13 | D30: — | E30: Của mình | F30: Của mình | G30: — | H30: ✔ | I30: ✔
A31: 12 | B31: Duyệt sàn đơn | C31: UC-16 | D31: — | E31: — | F31: ✔ | G31: — | H31: — | I31: ✔
... A64: 45 | B64: Xem trạng thái tác vụ định kỳ | C64: UC-63 | D64: — | E64: — | F64: — | G64: — | H64: — | I64: ✔
B66: Chú giải: ✔ = được thực hiện; Của mình = chỉ dữ liệu thuộc quyền; Một phần = chỉ một số thao tác hoặc dữ liệu; Đề xuất = chỉ được đề xuất, Admin quyết định; — = không có quyền.

Sheet 03_BR
A1: Danh mục BR – Business Requirements
A2: Functional • Non-functional • Business Rule • Business Constraint • Business Goal | Mọi giá trị số lấy từ sheet 06_Tham_số (mã trong [PRM-xxx])
A4: Mã BR | B4: Loại BR | C4: Phân hệ | D4: Tiêu đề | E4: Mô tả yêu cầu | F4: Tác nhân / Chủ thể | G4: UC liên quan | H4: Ưu tiên | I4: Pha | J4: Tiêu chí nghiệm thu / đo lường | K4: Tham số liên quan | L4: Căn cứ | M4: Trạng thái
A5: BR-F-001 | B5: Functional BR | C5: AUTH | D5: Đăng ký tài khoản | E5: Hệ thống cho phép khách đăng ký tài khoản bằng họ tên, email, số điện thoại và mật khẩu sau khi đồng ý Điều khoản sử dụng và Chính sách dữ liệu cá nhân (có ghi nhận phiên bản và thời điểm đồng ý). | F5: Khách | G5: UC-01 | H5: Must | I5: Pha 1 | J5: Đăng ký hợp lệ tạo tài khoản trạng thái Chờ xác thực và lưu bản ghi đồng ý chính sách. | L5: Nhu cầu người dùng | M5: Dự thảo
A6: BR-F-002 | B6: Functional BR | C6: AUTH | D6: Xác thực OTP | E6: Hệ thống gửi OTP đến email hoặc số điện thoại và cho phép người dùng xác thực để kích hoạt tài khoản. | F6: Người dùng | G6: UC-02 | H6: Must | I6: Pha 1 | J6: Nhập đúng OTP: tài khoản chuyển Hoạt động; sai/hết hạn: báo lỗi đúng mã. | L6: Nhu cầu người dùng | M6: Dự thảo
A7: BR-F-003 | B7: Functional BR | C7: AUTH | D7: Đăng nhập và cấp token | E7: Hệ thống cho phép đăng nhập bằng email hoặc số điện thoại và mật khẩu, trả về Access Token và Refresh Token theo cơ chế JWT. | F7: Người dùng | G7: UC-03 | H7: Must | I7: Pha 1 | J7: Đăng nhập đúng trả token hợp lệ; sai trả 401 không tiết lộ trường nào sai. | L7: Nhu cầu người dùng | M7: Dự thảo
A8: BR-F-004 | B8: Functional BR | C8: AUTH | D8: Đăng nhập nhanh bằng Google | E8: Hệ thống cho phép đăng nhập hoặc đăng ký nhanh bằng tài khoản Google (OAuth2), tự động nhận diện email thuộc tên miền FPT để cấp huy hiệu cộng đồng. | F8: Người dùng | G8: UC-03, UC-07 | H8: Could | I8: Pha 3 | J8: Đăng nhập Google tạo/liên kết tài khoản đúng email; email @fpt.edu.vn nhận huy hiệu. | L8: Nhu cầu người dùng | M8: Dự thảo
A9: BR-F-005 | B9: Functional BR | C9: AUTH | D9: Đăng xuất và quản lý thiết bị | E9: Hệ thống cho phép đăng xuất, xem danh sách thiết bị/phiên đang đăng nhập và thu hồi từng phiên từ xa. | F9: Người dùng | G9: UC-04 | H9: Must | I9: Pha 1 | J9: Thu hồi phiên: token của phiên đó bị vô hiệu ngay. | L9: Nhu cầu người dùng | M9: Dự thảo
A10: BR-F-006 | B10: Functional BR | C10: AUTH | D10: Quên và đặt lại mật khẩu | E10: Hệ thống cho phép đặt lại mật khẩu bằng OTP gửi tới email hoặc số điện thoại đã đăng ký; sau khi đặt lại, mọi phiên cũ bị thu hồi. | F10: Người dùng | G10: UC-05 | H10: Must | I10: Pha 1 | J10: Đặt lại thành công: đăng nhập được bằng mật khẩu mới, phiên cũ mất hiệu lực. | L10: Nhu cầu người dùng | M10: Dự thảo
A11: BR-F-007 | B11: Functional BR | C11: AUTH | D11: Đổi mật khẩu | E11: Hệ thống cho phép người dùng đang đăng nhập đổi mật khẩu sau khi nhập đúng mật khẩu hiện tại. | F11: Người dùng | G11: UC-06 | H11: Must | I11: Pha 1 | J11: Đổi thành công gửi thông báo bảo mật; sai mật khẩu cũ bị từ chối. | L11: Nhu cầu người dùng | M11: Dự thảo
A12: BR-F-008 | B12: Functional BR | C12: KYC | D12: Quản lý hồ sơ cá nhân | E12: Hệ thống cho phép người dùng xem và cập nhật hồ sơ cá nhân gồm họ tên, ảnh đại diện, ngày sinh, giới thiệu ngắn và thông tin liên hệ; việc đổi email/số điện thoại phải xác thực lại bằng OTP. | F12: Người dùng | G12: UC-07 | H12: Must | I12: Pha 1 | J12: Cập nhật lưu đúng; đổi email chưa xác thực OTP không có hiệu lực. | L12: Nhu cầu người dùng | M12: Dự thảo
A13: BR-F-009 | B13: Functional BR | C13: KYC | D13: Sổ địa chỉ | E13: Hệ thống cho phép người gửi lưu, sửa, xóa các địa chỉ thường dùng (nhà, ký túc xá, cơ quan) kèm tọa độ để chọn nhanh khi tạo đơn. | F13: Người gửi | G13: UC-07, UC-12 | H13: Must | I13: Pha 1 | J13: Chọn địa chỉ đã lưu tự điền điểm lấy/giao và tọa độ. | L13: Nhu cầu người dùng | M13: Dự thảo
A14: BR-F-010 | B14: Functional BR | C14: KYC | D14: Nộp hồ sơ xác minh | E14: Hệ thống cho phép người dùng tải ảnh CCCD hai mặt và ảnh chân dung cầm CCCD, nhập thông tin CCCD và gửi hồ sơ xác minh. | F14: Người dùng | G14: UC-08 | H14: Must | I14: Pha 1 | J14: Hồ sơ gửi đi ở trạng thái Chờ duyệt; ảnh lưu mã hóa. | L14: Nhu cầu người dùng | M14: Dự thảo
A15: BR-F-011 | B15: Functional BR | C15: KYC | D15: Hàng đợi duyệt hồ sơ | E15: Hệ thống cung cấp cho Kiểm duyệt hàng đợi hồ sơ KYC với ảnh, thông tin đối chiếu và cảnh báo trùng; cho phép duyệt hoặc từ chối kèm lý do. | F15: Kiểm duyệt | G15: UC-09 | H15: Must | I15: Pha 1 | J15: Duyệt/từ chối cập nhật trạng thái và gửi thông báo cho người dùng. | L15: Nhu cầu người dùng | M15: Dự thảo
A16: BR-F-012 | B16: Functional BR | C16: KYC | D16: Đăng ký làm Người giao | E16: Hệ thống cho phép người dùng đã xác minh đăng ký vai trò Người giao: chọn phương tiện, khu vực hoạt động, khung giờ thường rảnh và xác nhận cam kết trách nhiệm. | F16: Người dùng | G16: UC-10 | H16: Must | I16: Pha 1 | J16: Đăng ký xong người dùng thấy được sàn đơn và chức năng nhận đơn. | L16: Nhu cầu người dùng | M16: Dự thảo
... A124: BR-F-120 | B124: Functional BR | C124: GAM | D124: Huy hiệu và thưởng chuyến | E124: Hệ thống trao huy hiệu và thưởng theo thành tích (số đơn trong tuần, chuỗi giao đúng hạn) theo cấu hình của Admin. | F124: Người giao | G124: UC-62 | H124: Could | I124: Pha 3 | J124: Đạt điều kiện thì tự động nhận huy hiệu/thưởng. | L124: Nhu cầu người dùng | M124: Dự thảo
A125: BR-F-121 | B125: Functional BR | C125: GAM | D125: Giới thiệu bạn bè | E125: Hệ thống cung cấp mã giới thiệu và trao thưởng 10.000đ [PRM-109] cho cả hai bên sau khi người được mời hoàn tất đơn đầu tiên. | F125: Người dùng | G125: UC-62 | H125: Could | I125: Pha 3 | J125: Thưởng chỉ ghi nhận một lần cho mỗi người được mời. | K125: PRM-109 | L125: Nhu cầu người dùng | M125: Dự thảo
A126: BR-F-122 | B126: Functional BR | C126: SYS | D126: Tìm kiếm địa chỉ và bản đồ | E126: Hệ thống cung cấp tìm kiếm địa chỉ gợi ý (geocoding), hiển thị bản đồ và tính quãng đường cho các chức năng chọn điểm và theo dõi. | F126: Người dùng | G126: UC-11, UC-12, UC-27 | H126: Must | I126: Pha 1 | J126: Gợi ý địa chỉ trả về trong ≤ 1 giây; có chế độ dự phòng khi dịch vụ lỗi. | L126: Nhu cầu người dùng | M126: Dự thảo
A127: BR-F-123 | B127: Functional BR | C127: SYS | D127: Quản lý tệp tải lên | E127: Hệ thống cung cấp dịch vụ tải và lưu trữ ảnh/tệp bằng chứng với kiểm tra loại tệp, giới hạn dung lượng và cấp liên kết truy cập có thời hạn cho dữ liệu nhạy cảm. | F127: Người dùng | G127: UC-08, UC-12, UC-25, UC-28 | H127: Must | I127: Pha 1 | J127: Tệp hợp lệ lưu thành công; liên kết nhạy cảm hết hạn đúng thời gian. | L127: Nhu cầu người dùng | M127: Dự thảo
A128: BR-F-124 | B128: Functional BR | C128: SYS | D128: Xuất dữ liệu và xóa tài khoản | E128: Hệ thống cho phép người dùng yêu cầu xuất dữ liệu cá nhân và yêu cầu xóa/ẩn danh tài khoản, Admin xử lý theo quy trình. | F128: Người dùng | G128: UC-07, UC-57 | H128: Should | I128: Pha 2 | J128: Yêu cầu tạo hồ sơ xử lý; sau xử lý dữ liệu cá nhân được xóa/ẩn danh. | L128: Nhu cầu người dùng | M128: Dự thảo
A129: BR-N-001 | B129: Non-functional BR | C129: SYS | D129: Hiệu năng – API đọc | E129: Với 500 người dùng đồng thời, 95% yêu cầu API đọc (danh sách, chi tiết) phải phản hồi trong ≤ 500 ms (không tính thời gian mạng của client). | F129: Hệ thống | G129: UC-13, UC-16 | H129: Must | I129: Pha 1 | J129: Kiểm thử tải JMeter/k6 500 VU: p95 ≤ 500 ms, lỗi < 1%. | L129: Chất lượng hệ thống | M129: Dự thảo
A130: BR-N-002 | B130: Non-functional BR | C130: SYS | D130: Hiệu năng – API ghi | E130: 95% yêu cầu API ghi thông thường (tạo đơn, gửi chào giá, đánh giá) phải phản hồi trong ≤ 1 giây. | F130: Hệ thống | G130: UC-12, UC-18, UC-47 | H130: Must | I130: Pha 1 | J130: Kiểm thử tải: p95 ≤ 1.000 ms. | L130: Chất lượng hệ thống | M130: Dự thảo
A131: BR-N-003 | B131: Non-functional BR | C131: PAY | D131: Hiệu năng – Tạo thanh toán VNPay | E131: Hệ thống phải tạo xong liên kết thanh toán VNPay và chuyển hướng người dùng trong ≤ 3 giây kể từ khi bấm thanh toán. | F131: Hệ thống | G131: UC-34, UC-35 | H131: Must | I131: Pha 1 | J131: Đo thời gian từ request đến response có URL: p95 ≤ 3 giây. | L131: Chất lượng hệ thống | M131: Dự thảo
A132: BR-N-004 | B132: Non-functional BR | C132: PAY | D132: Hiệu năng – Xử lý IPN | E132: Endpoint IPN của VNPay phải xử lý và phản hồi trong ≤ 2 giây với định dạng phản hồi mà VNPay yêu cầu; xử lý nặng phải tách bất đồng bộ. | F132: Hệ thống | G132: UC-42 | H132: Must | I132: Pha 1 | J132: Log thời gian xử lý IPN p99 ≤ 2 giây trong test với 100 IPN/phút. | L132: Chất lượng hệ thống | M132: Dự thảo
A133: BR-N-005 | B133: Non-functional BR | C133: SYS | D133: Hiệu năng – Tải trang đầu | E133: Trang đầu tiên của SPA tải xong (LCP) trong ≤ 3 giây trên mạng 4G; gói JavaScript khởi tạo ≤ 300 KB (gzip) nhờ tách mã (code splitting) và tải lười. | F133: Hệ thống | H133: Should | I133: Pha 2 | J133: Lighthouse (mobile, 4G giả lập): LCP ≤ 3 s; kích thước bundle ban đầu ≤ 300 KB gzip. | L133: Chất lượng hệ thống | M133: Dự thảo
A134: BR-N-006 | B134: Non-functional BR | C134: MKT | D134: Hiệu năng – Tìm kiếm sàn đơn | E134: Tìm kiếm/lọc/sắp xếp trên sàn đơn với 50.000 đơn phải phản hồi p95 ≤ 800 ms; có phân trang và chỉ mục phù hợp. | F134: Hệ thống | G134: UC-16 | H134: Must | I134: Pha 1 | J134: Kiểm thử với dữ liệu 50.000 đơn: p95 ≤ 800 ms. | L134: Chất lượng hệ thống | M134: Dự thảo
A135: BR-N-007 | B135: Non-functional BR | C135: TRK | D135: Hiệu năng – Độ trễ theo dõi | E135: Vị trí mới của người giao phải đến màn hình người theo dõi trong ≤ 3 giây kể từ khi gửi (trải nghiệm thời gian thực). | F135: Hệ thống | G135: UC-26, UC-27 | H135: Must | I135: Pha 1 | J135: Đo thời gian gửi–nhận trong môi trường staging: p95 ≤ 3 giây. | L135: Chất lượng hệ thống | M135: Dự thảo
A136: BR-N-008 | B136: Non-functional BR | C136: MKT | D136: Hiệu năng – Gợi ý ghép đơn | E136: Việc tính gợi ý ghép đơn–chuyến phải trả kết quả trong ≤ 2 giây với 5.000 đơn đang mở. | F136: Hệ thống | G136: UC-21 | H136: Should | I136: Pha 2 | J136: Benchmark: 5.000 đơn mở, p95 ≤ 2 giây. | L136: Chất lượng hệ thống | M136: Dự thảo
A137: BR-N-009 | B137: Non-functional BR | C137: NTF | D137: Hiệu năng – Thông báo | E137: Thông báo trong ứng dụng phải hiển thị trong ≤ 2 giây sau khi sự kiện nghiệp vụ xảy ra. | F137: Hệ thống | G137: UC-53 | H137: Should | I137: Pha 2 | J137: Đo thời gian từ sự kiện đến hiển thị: p95 ≤ 2 giây. | L137: Chất lượng hệ thống | M137: Dự thảo
A138: BR-N-010 | B138: Non-functional BR | C138: SYS | D138: Mở rộng – Số người dùng | E138: Hệ thống đáp ứng tối thiểu 500 người dùng đồng thời và 5.000 đơn/ngày; backend không giữ trạng thái phiên (stateless) để mở rộng ngang. | F138: Hệ thống | H138: Must | I138: Pha 1 | J138: Chạy 2 instance backend sau load balancer, kết quả test đạt chỉ tiêu; không dùng session cục bộ. | L138: Chất lượng hệ thống | M138: Dự thảo
A139: BR-N-011 | B139: Non-functional BR | C139: TRK | D139: Mở rộng – Kết nối thời gian thực | E139: Kênh WebSocket hỗ trợ tối thiểu 1.000 kết nối đồng thời trên một cụm triển khai. | F139: Hệ thống | G139: UC-24, UC-27 | H139: Should | I139: Pha 2 | J139: Kiểm thử 1.000 kết nối WebSocket, tỷ lệ rớt < 1%. | L139: Chất lượng hệ thống | M139: Dự thảo
A140: BR-N-012 | B140: Non-functional BR | C140: SYS | D140: Sẵn sàng – Thời gian hoạt động | E140: Độ khả dụng ≥ 99,5% mỗi tháng trong giai đoạn pilot (không tính bảo trì đã thông báo trước ≥ 24 giờ). | F140: Hệ thống | H140: Should | I140: Pha 2 | J140: Giám sát uptime hằng tháng ≥ 99,5%. | L140: Chất lượng hệ thống | M140: Dự thảo
A141: BR-N-013 | B141: Non-functional BR | C141: SYS | D141: Sẵn sàng – Sao lưu và khôi phục | E141: Sao lưu SQL Server và MongoDB hằng ngày; RPO ≤ 24 giờ, RTO ≤ 4 giờ; kiểm thử khôi phục tối thiểu 1 lần/tháng. | F141: Hệ thống | H141: Should | I141: Pha 2 | J141: Biên bản diễn tập khôi phục thành công; có script backup tự động. | L141: Chất lượng hệ thống | M141: Dự thảo
A142: BR-N-014 | B142: Non-functional BR | C142: SYS | D142: Tin cậy – Chịu lỗi dịch vụ ngoài | E142: Mọi lời gọi dịch vụ ngoài (VNPay, định tuyến, email/SMS) phải có timeout, thử lại có giới hạn và ngắt mạch (circuit breaker); lỗi dịch vụ ngoài không được làm sập hệ thống. | F142: Hệ thống | G142: UC-34, UC-11, UC-53 | H142: Must | I142: Pha 1 | J142: Giả lập dịch vụ ngoài lỗi: hệ thống trả lỗi có kiểm soát, các chức năng khác vẫn hoạt động. | L142: Chất lượng hệ thống | M142: Dự thảo
A143: BR-N-015 | B143: Non-functional BR | C143: SYS | D143: Tin cậy – Tác vụ định kỳ | E143: Tác vụ nền (hết hạn đơn, tự giải ngân, đối soát) chỉ chạy đúng một lần khi có nhiều instance, có khả năng chạy lại an toàn (idempotent) và ghi nhật ký kết quả. | F143: Hệ thống | G143: UC-63, UC-43 | H143: Must | I143: Pha 1 | J143: Chạy 2 instance: mỗi job thực thi 1 lần/chu kỳ; chạy lại không tạo dữ liệu trùng. | L143: Chất lượng hệ thống | M143: Dự thảo
A144: BR-N-016 | B144: Non-functional BR | C144: AUTH | D144: Bảo mật – Băm mật khẩu | E144: Mật khẩu chỉ được lưu dưới dạng băm BCrypt (cost ≥ 10); không lưu và không ghi log mật khẩu bản rõ. | F144: Hệ thống | G144: UC-01, UC-06 | H144: Must | I144: Pha 1 | J144: Rà soát CSDL và log: không có mật khẩu rõ; cost factor ≥ 10. | L144: Chất lượng hệ thống | M144: Dự thảo
A145: BR-N-017 | B145: Non-functional BR | C145: SYS | D145: Bảo mật – Mã hóa đường truyền | E145: Toàn bộ truy cập qua HTTPS (TLS ≥ 1.2) và bật HSTS; WebSocket dùng WSS. | F145: Hệ thống | H145: Must | I145: Pha 1 | J145: Quét SSL Labs/testssl: không cho phép giao thức < TLS 1.2. | L145: Chất lượng hệ thống | M145: Dự thảo
A146: BR-N-018 | B146: Non-functional BR | C146: KYC | D146: Bảo mật – Mã hóa dữ liệu nhạy cảm | E146: Ảnh CCCD, ảnh chân dung và số tài khoản ngân hàng được mã hóa khi lưu (AES-256-GCM); khóa mã hóa quản lý ngoài mã nguồn và có quy trình xoay khóa. | F146: Hệ thống | G146: UC-08, UC-39 | H146: Must | I146: Pha 1 | J146: Kiểm tra dữ liệu thô trong kho lưu trữ không đọc được; khóa lấy từ biến môi trường/secret store. | L146: Chất lượng hệ thống | M146: Dự thảo
A147: BR-N-019 | B147: Non-functional BR | C147: SYS | D147: Bảo mật – OWASP Top 10 | E147: Hệ thống phải được kiểm thử và phòng chống các rủi ro OWASP Top 10 (injection, XSS, CSRF, broken access control, SSRF…); nghiệm thu không còn lỗ hổng mức Cao/Nghiêm trọng. | F147: Hệ thống | H147: Must | I147: Pha 1 | J147: Báo cáo kiểm thử bảo mật (ZAP/checklist OWASP ASVS cơ bản): 0 lỗ hổng Cao/Nghiêm trọng. | L147: Chất lượng hệ thống | M147: Dự thảo
A148: BR-N-020 | B148: Non-functional BR | C148: SYS | D148: Bảo mật – Kiểm soát truy cập đối tượng | E148: Người dùng chỉ truy cập được đơn, ví, chat và hồ sơ thuộc quyền của mình; mọi endpoint phải kiểm tra quyền sở hữu phía máy chủ (chống BOLA/IDOR). | F148: Hệ thống | G148: UC-13, UC-38 | H148: Must | I148: Pha 1 | J148: Kiểm thử thay đổi ID trong URL: trả 403/404 cho dữ liệu không thuộc quyền. | L148: Chất lượng hệ thống | M148: Dự thảo
A149: BR-N-021 | B149: Non-functional BR | C149: PAY | D149: Bảo mật – Giao dịch tiền idempotent | E149: Mọi thao tác ghi sổ cái (nạp, ký quỹ, giải ngân, hoàn tiền, rút) phải idempotent theo khóa idempotency (24 giờ [PRM-073]) và an toàn khi đồng thời (khóa lạc quan/bi quan); gửi lặp cùng yêu cầu không tạo bút toán thứ hai. | F149: Hệ thống | G149: UC-35, UC-36, UC-37, UC-40, UC-42 | H149: Must | I149: Pha 1 | J149: Test đồng thời 50 request trùng: chỉ 1 bút toán được tạo. | K149: PRM-073 | L149: Chất lượng hệ thống | M149: Dự thảo
A150: BR-N-022 | B150: Non-functional BR | C150: PAY | D150: Bảo mật – Chữ ký VNPay | E150: Mọi phản hồi/IPN từ VNPay phải được xác minh chữ ký (HMAC-SHA512) và đối chiếu số tiền, mã tham chiếu trước khi cập nhật trạng thái; từ chối nếu sai. | F150: Hệ thống | G150: UC-42 | H150: Must | I150: Pha 1 | J150: Test gửi IPN sai chữ ký/sai số tiền: bị từ chối, không đổi trạng thái. | L150: Chất lượng hệ thống | M150: Dự thảo
A151: BR-N-023 | B151: Non-functional BR | C151: SYS | D151: Bảo mật – Tải tệp lên | E151: Tệp tải lên chỉ chấp nhận JPG/PNG/WEBP trong giới hạn 5 MB [PRM-019]; kiểm tra loại tệp theo nội dung, đổi tên ngẫu nhiên, lưu ngoài thư mục thực thi. | F151: Hệ thống | G151: UC-08, UC-12, UC-25 | H151: Must | I151: Pha 1 | J151: Test tải tệp .exe/.html đổi đuôi: bị từ chối. | K151: PRM-019 | L151: Chất lượng hệ thống | M151: Dự thảo
A152: BR-N-024 | B152: Non-functional BR | C152: AUTH | D152: Bảo mật – Giới hạn tần suất | E152: Áp dụng giới hạn 100 request/phút/người dùng [PRM-010] cho API thường và 10 request/phút/IP [PRM-011] cho API xác thực; vượt ngưỡng trả HTTP 429 kèm Retry-After. | F152: Hệ thống | G152: UC-03, UC-05 | H152: Must | I152: Pha 1 | J152: Test vượt ngưỡng nhận 429. | K152: PRM-010, PRM-011 | L152: Chất lượng hệ thống | M152: Dự thảo
A153: BR-N-025 | B153: Non-functional BR | C153: SYS | D153: Bảo mật – Quản lý bí mật và log | E153: Khóa API, mật khẩu CSDL, hash secret VNPay không nằm trong mã nguồn; log che (mask) dữ liệu nhạy cảm như số điện thoại, số tài khoản, token. | F153: Hệ thống | H153: Must | I153: Pha 1 | J153: Quét mã nguồn bằng công cụ phát hiện secret: 0 kết quả; kiểm tra mẫu log. | L153: Chất lượng hệ thống | M153: Dự thảo
A154: BR-N-026 | B154: Non-functional BR | C154: ADM | D154: Bảo mật – Nhật ký kiểm toán | E154: Mọi hành động nhạy cảm (tiền, KYC, phân quyền, khóa tài khoản, đổi tham số) phải được ghi nhật ký kiểm toán không thể sửa/xóa qua giao diện, kèm người thực hiện, thời điểm, IP, giá trị trước/sau. | F154: Hệ thống | G154: UC-60 | H154: Must | I154: Pha 1 | J154: Thực hiện 10 hành động nhạy cảm: đủ 10 bản ghi audit với trường bắt buộc. | L154: Chất lượng hệ thống | M154: Dự thảo
A155: BR-N-027 | B155: Non-functional BR | C155: SYS | D155: Trải nghiệm – Responsive và thao tác nhanh | E155: Giao diện hiển thị đúng từ 360 px; các thao tác chính (đăng đơn, nhận đơn, xác nhận giao) hoàn thành trong ≤ 5 lần chạm sau khi đã đăng nhập. | F155: Người dùng | G155: UC-12, UC-17, UC-28 | H155: Must | I155: Pha 1 | J155: Kiểm thử thủ công theo kịch bản trên 3 kích thước màn hình. | L155: Chất lượng hệ thống | M155: Dự thảo
A156: BR-N-028 | B156: Non-functional BR | C156: SYS | D156: Trải nghiệm – Thông báo lỗi | E156: Thông báo lỗi bằng tiếng Việt, nêu nguyên nhân và hướng khắc phục; không hiển thị thông tin kỹ thuật (stack trace) cho người dùng. | F156: Người dùng | H156: Must | I156: Pha 1 | J156: Rà soát danh mục mã lỗi: 100% có thông điệp thân thiện. | L156: Chất lượng hệ thống | M156: Dự thảo
A157: BR-N-029 | B157: Non-functional BR | C157: SYS | D157: Trải nghiệm – Khả năng truy cập | E157: Đáp ứng mức cơ bản WCAG 2.1 AA: độ tương phản chữ ≥ 4,5:1, nhãn cho mọi trường nhập, điều hướng được bằng bàn phím. | F157: Người dùng | H157: Could | I157: Pha 3 | J157: Kiểm tra bằng Lighthouse Accessibility ≥ 90. | L157: Chất lượng hệ thống | M157: Dự thảo
A158: BR-N-030 | B158: Non-functional BR | C158: SYS | D158: Trải nghiệm – Người dùng mới | E158: Người dùng mới hoàn thành đăng ký, xác thực và đăng đơn đầu tiên trong ≤ 5 phút. | F158: Người dùng | G158: UC-01, UC-12 | H158: Should | I158: Pha 2 | J158: Kiểm thử khả dụng với ≥ 5 người dùng: ≥ 4 người đạt. | L158: Chất lượng hệ thống | M158: Dự thảo
A159: BR-N-031 | B159: Non-functional BR | C159: SYS | D159: Trải nghiệm – Trạng thái giao diện | E159: Mọi danh sách và trang dữ liệu phải có trạng thái đang tải, rỗng và lỗi rõ ràng; thao tác lỗi do mạng cho phép thử lại. | F159: Người dùng | G159: UC-13, UC-16 | H159: Must | I159: Pha 1 | J159: Checklist UI: mỗi màn hình danh sách có đủ 3 trạng thái. | L159: Chất lượng hệ thống | M159: Dự thảo
A160: BR-N-032 | B160: Non-functional BR | C160: SYS | D160: Chất lượng – Kiểm thử tự động | E160: Độ bao phủ kiểm thử đơn vị của tầng service ≥ 70% cho các module Ví/Thanh toán và Đơn hàng; kiểm thử tích hợp cho mọi API tiền. | F160: Nhóm phát triển | H160: Must | I160: Pha 1 | J160: Báo cáo JaCoCo: ≥ 70% cho module chỉ định; CI fail khi dưới ngưỡng. | L160: Chất lượng hệ thống | M160: Dự thảo
A161: BR-N-033 | B161: Non-functional BR | C161: SYS | D161: Chất lượng – Kiến trúc module | E161: Backend tổ chức theo module độc lập (modular monolith), không phụ thuộc vòng giữa các module; giao tiếp qua giao diện dịch vụ hoặc sự kiện nội bộ. | F161: Nhóm phát triển | H161: Must | I161: Pha 1 | J161: Kiểm tra bằng ArchUnit trong CI: 0 vi phạm. | L161: Chất lượng hệ thống | M161: Dự thảo
A162: BR-N-034 | B162: Non-functional BR | C162: SYS | D162: Chất lượng – Quy ước và review | E162: Mọi thay đổi mã vào nhánh chính phải qua pull request, ≥ 1 người review và vượt kiểm tra lint (Checkstyle/ESLint) cùng build xanh. | F162: Nhóm phát triển | H162: Must | I162: Pha 1 | J162: Cấu hình bảo vệ nhánh bật; không có commit trực tiếp vào main. | L162: Chất lượng hệ thống | M162: Dự thảo
A163: BR-N-035 | B163: Non-functional BR | C163: SYS | D163: Chất lượng – Khả năng quan sát | E163: Mỗi yêu cầu có correlation ID xuyên suốt log; bật Actuator health/metrics; có thể truy vết một lỗi từ ID trả về cho người dùng. | F163: Nhóm phát triển | H163: Should | I163: Pha 2 | J163: Từ mã lỗi hiển thị tìm được log đầy đủ của request. | L163: Chất lượng hệ thống | M163: Dự thảo
A164: BR-N-036 | B164: Non-functional BR | C164: SYS | D164: Chất lượng – Tài liệu API đồng bộ | E164: Tài liệu OpenAPI được sinh tự động từ mã nguồn và luôn khớp phiên bản hiện hành. | F164: Nhóm phát triển | H164: Must | I164: Pha 1 | J164: Swagger UI khớp 100% với endpoint; CI kiểm tra spec hợp lệ. | L164: Chất lượng hệ thống | M164: Dự thảo
A165: BR-N-037 | B165: Non-functional BR | C165: SYS | D165: Chất lượng – Quản lý thay đổi CSDL | E165: Thay đổi cấu trúc CSDL SQL Server quản lý bằng công cụ migration (Flyway/Liquibase), chạy tự động khi triển khai và có thể lặp lại trên mọi môi trường. | F165: Nhóm phát triển | H165: Must | I165: Pha 1 | J165: Dựng CSDL rỗng từ migration thành công trong CI. | L165: Chất lượng hệ thống | M165: Dự thảo
A166: BR-N-038 | B166: Non-functional BR | C166: SYS | D166: Dữ liệu – Chính sách lưu trữ | E166: Dữ liệu được lưu và xóa theo thời hạn cấu hình: vị trí 12 tháng [PRM-092], chat 12 tháng [PRM-093], nhật ký kiểm toán 5 năm [PRM-107], sổ cái 10 năm [PRM-108]. | F166: Hệ thống | G166: UC-60 | H166: Should | I166: Pha 2 | J166: Cấu hình TTL index và job dọn dẹp hoạt động đúng theo tham số. | K166: PRM-092, PRM-093, PRM-107, PRM-108 | L166: Chất lượng hệ thống | M166: Dự thảo
A167: BR-N-039 | B167: Non-functional BR | C167: PAY | D167: Dữ liệu – Toàn vẹn sổ cái | E167: Sổ cái dùng bút toán kép; tổng ghi nợ luôn bằng tổng ghi có; không cho phép sửa/xóa bút toán, chỉ ghi bút toán điều chỉnh. | F167: Hệ thống | G167: UC-35, UC-36, UC-43 | H167: Must | I167: Pha 1 | J167: Truy vấn kiểm tra tổng nợ = tổng có = 0 chênh lệch; không có lệnh UPDATE/DELETE trên bảng sổ cái. | L167: Chất lượng hệ thống | M167: Dự thảo
A168: BR-N-040 | B168: Non-functional BR | C168: KYC | D168: Dữ liệu – Quyền xóa dữ liệu cá nhân | E168: Hỗ trợ yêu cầu xóa hoặc ẩn danh tài khoản trong ≤ 30 ngày, giữ lại dữ liệu bắt buộc theo quy định pháp luật (giao dịch, thuế) ở dạng ẩn danh. | F168: Người dùng | G168: UC-07, UC-57 | H168: Should | I168: Pha 2 | J168: Quy trình xóa chạy thử: dữ liệu cá nhân bị xóa/ẩn, sổ cái còn nguyên. | L168: Chất lượng hệ thống | M168: Dự thảo
A169: BR-N-041 | B169: Non-functional BR | C169: SYS | D169: Dữ liệu – Thời gian chuẩn | E169: Thời gian nghiệp vụ lưu theo UTC, hiển thị theo UTC+7; máy chủ đồng bộ NTP; mọi so sánh hạn chót dùng giờ máy chủ. | F169: Hệ thống | G169: UC-63 | H169: Must | I169: Pha 1 | J169: Test chuyển múi giờ trình duyệt không làm sai hạn chót của đơn. | L169: Chất lượng hệ thống | M169: Dự thảo
A170: BR-R-001 | B170: Business Rule | C170: AUTH | D170: Duy nhất email và số điện thoại | E170: Mỗi email và mỗi số điện thoại chỉ được gắn với một tài khoản duy nhất. | F170: Khách | G170: UC-01 | H170: Must | I170: Pha 1 | J170: Đăng ký lần hai với email/SĐT đã tồn tại bị từ chối với thông báo phù hợp. | L170: Chính sách nghiệp vụ | M170: Dự thảo
A171: BR-R-002 | B171: Business Rule | C171: AUTH | D171: Quy tắc mật khẩu | E171: Mật khẩu tối thiểu 8 ký tự [PRM-008], gồm ít nhất 1 chữ hoa, 1 chữ thường, 1 chữ số và không được trùng với email hoặc số điện thoại của chính tài khoản. | F171: Người dùng | G171: UC-01, UC-05, UC-06 | H171: Must | I171: Pha 1 | J171: Test các mật khẩu vi phạm từng điều kiện đều bị từ chối. | K171: PRM-008 | L171: Chính sách nghiệp vụ | M171: Dự thảo
A172: BR-R-003 | B172: Business Rule | C172: AUTH | D172: Quy tắc OTP | E172: OTP có hiệu lực 5 phút [PRM-001]; nhập sai tối đa 5 lần [PRM-002] thì OTP bị vô hiệu; yêu cầu gửi lại cách nhau tối thiểu 60 giây [PRM-003]. | F172: Người dùng | G172: UC-02, UC-05 | H172: Must | I172: Pha 1 | J172: Test hết hạn, nhập sai quá số lần và gửi lại sớm đều bị chặn. | K172: PRM-001, PRM-002, PRM-003 | L172: Chính sách nghiệp vụ | M172: Dự thảo
A173: BR-R-004 | B173: Business Rule | C173: AUTH | D173: Khóa đăng nhập tạm thời | E173: Đăng nhập sai 5 lần [PRM-004] liên tiếp thì khóa đăng nhập trong 15 phút [PRM-005]; đăng nhập đúng trước đó sẽ đặt lại bộ đếm. | F173: Người dùng | G173: UC-03 | H173: Must | I173: Pha 1 | J173: Nhập sai 5 lần: lần thứ 6 bị từ chối kèm thời gian mở khóa. | K173: PRM-004, PRM-005 | L173: Chính sách nghiệp vụ | M173: Dự thảo
A174: BR-R-005 | B174: Business Rule | C174: AUTH | D174: Vòng đời token | E174: Access Token hiệu lực 15 phút [PRM-006], Refresh Token hiệu lực 7 ngày [PRM-007] và xoay vòng sau mỗi lần dùng; nếu một Refresh Token đã dùng bị dùng lại thì thu hồi toàn bộ phiên của tài khoản. | F174: Hệ thống | G174: UC-03, UC-04 | H174: Must | I174: Pha 1 | J174: Dùng lại refresh token cũ: mọi phiên bị thu hồi, người dùng phải đăng nhập lại. | K174: PRM-006, PRM-007 | L174: Chính sách nghiệp vụ | M174: Dự thảo
A175: BR-R-006 | B175: Business Rule | C175: AUTH | D175: Giới hạn thiết bị | E175: Mỗi tài khoản tối đa 5 thiết bị [PRM-009] đăng nhập đồng thời; khi vượt thì thiết bị đăng nhập cũ nhất bị đăng xuất. | F175: Người dùng | G175: UC-03, UC-04 | H175: Should | I175: Pha 2 | J175: Đăng nhập thiết bị thứ 6: thiết bị đầu tiên mất phiên. | K175: PRM-009 | L175: Chính sách nghiệp vụ | M175: Dự thảo
A176: BR-R-007 | B176: Business Rule | C176: AUTH | D176: Tài khoản chưa xác thực bị hạn chế | E176: Tài khoản chưa xác thực OTP chỉ được xem công khai; không được tạo đơn, nhận đơn, nạp tiền hoặc rút tiền. | F176: Người dùng | G176: UC-02, UC-12, UC-34 | H176: Must | I176: Pha 1 | J176: Gọi API tạo đơn bằng tài khoản chưa xác thực trả 403 với mã lỗi riêng. | L176: Chính sách nghiệp vụ | M176: Dự thảo
A177: BR-R-008 | B177: Business Rule | C177: AUTH | D177: Vai trò kép và không tự giao dịch | E177: Một tài khoản có thể giữ đồng thời vai trò Người gửi và Người giao, nhưng không được tự nhận, tự chào giá, tự đánh giá hoặc tự khiếu nại đơn do chính mình tạo. | F177: Người dùng | G177: UC-17, UC-18, UC-47 | H177: Must | I177: Pha 1 | J177: Người dùng nhận đơn của chính mình bị từ chối. | L177: Chính sách nghiệp vụ | M177: Dự thảo
A178: BR-R-009 | B178: Business Rule | C178: KYC | D178: Điều kiện người giao | E178: Chỉ tài khoản có hồ sơ xác minh KYC ở trạng thái đã duyệt và đã đăng ký vai trò Người giao mới được nhận đơn hoặc chào giá. | F178: Người giao | G178: UC-10, UC-17, UC-18 | H178: Must | I178: Pha 1 | J178: Người dùng chưa duyệt KYC gọi API nhận đơn bị từ chối. | L178: Chính sách nghiệp vụ | M178: Dự thảo
A179: BR-R-010 | B179: Business Rule | C179: KYC | D179: Thành phần hồ sơ KYC | E179: Hồ sơ KYC gồm ảnh CCCD mặt trước, mặt sau và ảnh chân dung cầm CCCD; họ tên và ngày sinh phải khớp với hồ sơ cá nhân; người dùng phải đủ 18 tuổi. | F179: Người dùng | G179: UC-08 | H179: Must | I179: Pha 1 | J179: Hồ sơ thiếu ảnh hoặc dưới 18 tuổi bị từ chối ngay khi gửi. | L179: Chính sách nghiệp vụ | M179: Dự thảo
A180: BR-R-011 | B180: Business Rule | C180: KYC | D180: Duy nhất CCCD | E180: Mỗi số CCCD chỉ được gắn với một tài khoản; hồ sơ trùng CCCD với tài khoản khác bị từ chối và đánh dấu để Kiểm duyệt rà soát gian lận. | F180: Kiểm duyệt | G180: UC-08, UC-09 | H180: Must | I180: Pha 1 | J180: Nộp CCCD đã dùng: bị từ chối, tạo cảnh báo. | L180: Chính sách nghiệp vụ | M180: Dự thảo
A181: BR-R-012 | B181: Business Rule | C181: KYC | D181: Từ chối phải có lý do | E181: Hồ sơ KYC bị từ chối phải kèm lý do chọn từ danh mục; người dùng được nộp lại tối đa 3 lần trong 7 ngày. | F181: Kiểm duyệt | G181: UC-09 | H181: Must | I181: Pha 1 | J181: Từ chối không lý do bị hệ thống chặn; lần nộp thứ 4 bị từ chối. | L181: Chính sách nghiệp vụ | M181: Dự thảo
A182: BR-R-013 | B182: Business Rule | C182: KYC | D182: Điều kiện rút tiền | E182: Chỉ người dùng có KYC đã duyệt mới được liên kết tài khoản ngân hàng và rút tiền. | F182: Người giao | G182: UC-39, UC-40 | H182: Must | I182: Pha 1 | J182: Người dùng chưa KYC không thấy chức năng rút tiền. | L182: Chính sách nghiệp vụ | M182: Dự thảo
A183: BR-R-014 | B183: Business Rule | C183: KYC | D183: Huy hiệu cộng đồng FPT | E183: Huy hiệu 'Cộng đồng FPT' chỉ cấp khi người dùng xác thực thành công OTP gửi tới email thuộc tên miền của FPT được cấu hình; huy hiệu mất khi email bị thu hồi. | F183: Người dùng | G183: UC-07 | H183: Should | I183: Pha 2 | J183: Email ngoài miền cấu hình không nhận được huy hiệu. | L183: Chính sách nghiệp vụ | M183: Dự thảo
A184: BR-R-015 | B184: Business Rule | C184: ORD | D184: Điều kiện tạo đơn | E184: Người gửi chỉ tạo được đơn mới khi đã xác thực OTP, không bị khóa và số đơn đang mở không vượt 10 đơn [PRM-024]. | F184: Người gửi | G184: UC-12 | H184: Must | I184: Pha 1 | J184: Tạo đơn thứ 11 khi đang có 10 đơn mở bị chặn. | K184: PRM-024 | L184: Chính sách nghiệp vụ | M184: Dự thảo
A185: BR-R-016 | B185: Business Rule | C185: ORD | D185: Giới hạn hàng hóa | E185: Mỗi đơn có khối lượng ≤ 20 kg [PRM-012], cạnh dài nhất ≤ 80 cm [PRM-013] và giá trị khai báo ≤ 3.000.000đ [PRM-016]. | F185: Người gửi | G185: UC-12 | H185: Must | I185: Pha 1 | J185: Mỗi giới hạn vượt đều có test từ chối kèm thông báo. | K185: PRM-012, PRM-013, PRM-016 | L185: Chính sách nghiệp vụ | M185: Dự thảo
A186: BR-R-017 | B186: Business Rule | C186: ORD | D186: Phân cỡ hàng | E186: Cỡ hàng xác định theo cạnh dài nhất: Nhỏ ≤ 30 cm [PRM-014]; Vừa ≤ 50 cm [PRM-015]; còn lại là Lớn. | F186: Hệ thống | G186: UC-11, UC-12 | H186: Must | I186: Pha 1 | J186: Bảng test biên 30/31/50/51/80/81 cm cho kết quả cỡ đúng. | K186: PRM-014, PRM-015 | L186: Chính sách nghiệp vụ | M186: Dự thảo
A187: BR-R-018 | B187: Business Rule | C187: ORD | D187: Ảnh hàng hóa bắt buộc | E187: Mỗi đơn phải có ít nhất 1 và tối đa 5 ảnh [PRM-018] ảnh hàng, mỗi ảnh ≤ 5 MB [PRM-019]. | F187: Người gửi | G187: UC-12 | H187: Must | I187: Pha 1 | J187: Đơn không ảnh hoặc ảnh quá cỡ bị từ chối. | K187: PRM-018, PRM-019 | L187: Chính sách nghiệp vụ | M187: Dự thảo
A188: BR-R-019 | B188: Business Rule | C188: ORD | D188: Tính hợp lệ về thời gian | E188: Giờ hẹn lấy hàng phải ở tương lai; hạn giao phải sau giờ hẹn lấy ít nhất bằng thời gian di chuyển ước tính. | F188: Người gửi | G188: UC-12, UC-14 | H188: Must | I188: Pha 1 | J188: Đặt hạn giao quá gấp so với quãng đường bị cảnh báo/chặn. | L188: Chính sách nghiệp vụ | M188: Dự thảo
A189: BR-R-020 | B189: Business Rule | C189: ORD | D189: Thời hạn mở đơn | E189: Đơn mở nhận mặc định 24 giờ [PRM-020], tối đa 7 ngày [PRM-021]; hết thời hạn mà chưa có người giao thì tự chuyển sang Hết hạn. | F189: Hệ thống | G189: UC-12, UC-63 | H189: Must | I189: Pha 1 | J189: Đơn quá hạn được job định kỳ chuyển EXPIRED và thông báo người gửi. | K189: PRM-020, PRM-021 | L189: Chính sách nghiệp vụ | M189: Dự thảo
A190: BR-R-021 | B190: Business Rule | C190: ORD | D190: Điều kiện sửa đơn | E190: Chỉ sửa đơn khi đơn đang Chờ kiểm duyệt hoặc Đang mở và chưa có chào giá được chấp nhận; sửa điểm lấy, điểm giao hoặc giá trị khai báo làm vô hiệu mọi chào giá hiện có. | F190: Người gửi | G190: UC-14 | H190: Must | I190: Pha 1 | J190: Sửa đơn đã có người giao bị từ chối; sửa điểm giao làm chào giá hết hiệu lực. | L190: Chính sách nghiệp vụ | M190: Dự thảo
A191: BR-R-022 | B191: Business Rule | C191: ORD | D191: Quy tắc hủy đơn và phí hủy | E191: Hủy trước khi có người giao: miễn phí. Hủy sau khi ký quỹ và trước khi lấy hàng: người gửi chịu phí 10% [PRM-050] phí giao (tối thiểu 5.000đ [PRM-051]) trả cho người giao, trừ khi do lỗi người giao. Sau khi đã lấy hàng: không được hủy mà phải xử lý bằng báo sự cố/giao thất bại. | F191: Người gửi | G191: UC-15, UC-37 | H191: Must | I191: Pha 1 | J191: Ba kịch bản hủy cho ba kết quả tiền đúng theo quy tắc. | K191: PRM-050, PRM-051 | L191: Chính sách nghiệp vụ | M191: Dự thảo
A192: BR-R-023 | B192: Business Rule | C192: ORD | D192: Thông tin người nhận | E192: Mỗi đơn bắt buộc có tên và số điện thoại người nhận hợp lệ; số điện thoại người nhận và địa chỉ chi tiết chỉ hiển thị cho người giao sau khi đơn ở trạng thái Đã ký quỹ. | F192: Người gửi | G192: UC-12, UC-13 | H192: Must | I192: Pha 1 | J192: Người giao chưa được chọn không thấy SĐT người nhận trong API. | L192: Chính sách nghiệp vụ | M192: Dự thảo
A193: BR-R-024 | B193: Business Rule | C193: ORD | D193: Hàng giá trị cao | E193: Đơn có giá trị khai báo vượt 1.000.000đ [PRM-017] chỉ người giao hạng Bạc trở lên và đã KYC mới được nhận hoặc chào giá. | F193: Người giao | G193: UC-16, UC-17 | H193: Must | I193: Pha 1 | J193: Người giao hạng Đồng nhận đơn 1,5 triệu bị từ chối. | K193: PRM-017 | L193: Chính sách nghiệp vụ | M193: Dự thảo
A194: BR-R-025 | B194: Business Rule | C194: ORD | D194: Một người giao một đơn | E194: Tại mỗi thời điểm một đơn (hoặc một chặng của đơn tiếp sức) chỉ gắn với một người giao; khi nhiều người cùng nhận chỉ yêu cầu đến trước thành công. | F194: Người giao | G194: UC-17, UC-19 | H194: Must | I194: Pha 1 | J194: Test 20 yêu cầu nhận đồng thời: 1 thành công, 19 thất bại có thông báo. | L194: Chính sách nghiệp vụ | M194: Dự thảo
A195: BR-R-026 | B195: Business Rule | C195: ORD | D195: Mã vận đơn | E195: Mỗi đơn có mã vận đơn duy nhất theo định dạng FPT-yyMMdd-xxxxxx, không đổi trong suốt vòng đời đơn. | F195: Hệ thống | G195: UC-12 | H195: Must | I195: Pha 1 | J195: Mã không trùng trên 100.000 đơn thử nghiệm. | L195: Chính sách nghiệp vụ | M195: Dự thảo
A196: BR-R-027 | B196: Business Rule | C196: MKT | D196: Hiển thị trên sàn | E196: Chỉ đơn ở trạng thái Đang mở được hiển thị trên sàn; thông tin chi tiết nhạy cảm (SĐT, địa chỉ cụ thể) bị ẩn, chỉ hiển thị khu vực và khoảng cách cho đến khi người giao được chọn. | F196: Người giao | G196: UC-16 | H196: Must | I196: Pha 1 | J196: API sàn đơn không trả SĐT và số nhà. | L196: Chính sách nghiệp vụ | M196: Dự thảo
A197: BR-R-028 | B197: Business Rule | C197: MKT | D197: Hạn mức nhận đơn theo hạng | E197: Người giao chỉ được giữ đồng thời số đơn tối đa và tổng giá trị khai báo tối đa theo hạng (Tân binh 3 / Đồng 5 / Bạc 8 / Vàng 12 / Kim cương 15 [PRM-083]; Tân binh 3 / Đồng 6 / Bạc 10 / Vàng 15 / Kim cương 20 (triệu đồng) [PRM-084]). | F197: Người giao | G197: UC-17, UC-18, UC-49 | H197: Must | I197: Pha 1 | J197: Người giao hạng Tân binh nhận đơn thứ 4 bị từ chối. | K197: PRM-083, PRM-084 | L197: Chính sách nghiệp vụ | M197: Dự thảo
A198: BR-R-029 | B198: Business Rule | C198: MKT | D198: Biên giá chào | E198: Giá chào và giá phản giá phải nằm trong khoảng từ 70% [PRM-039] đến 150% [PRM-040] của giá gợi ý; mỗi chào giá có hiệu lực 120 phút [PRM-041]. | F198: Người giao | G198: UC-18, UC-19 | H198: Must | I198: Pha 1 | J198: Chào giá ngoài biên bị từ chối; chào giá hết hạn tự chuyển Hết hạn. | K198: PRM-039, PRM-040, PRM-041 | L198: Chính sách nghiệp vụ | M198: Dự thảo
A199: BR-R-030 | B199: Business Rule | C199: MKT | D199: Một chào giá hiệu lực mỗi người giao | E199: Mỗi người giao chỉ có một chào giá hiệu lực cho một đơn; chào giá mới thay thế chào giá cũ. | F199: Người giao | G199: UC-18 | H199: Must | I199: Pha 1 | J199: Gửi chào giá lần 2: bản ghi cũ chuyển Đã rút. | L199: Chính sách nghiệp vụ | M199: Dự thảo
A200: BR-R-031 | B200: Business Rule | C200: MKT | D200: Chốt chào giá | E200: Khi người gửi chấp nhận một chào giá thì các chào giá còn lại của đơn bị từ chối tự động và đơn chuyển sang Chờ ký quỹ; người gửi có 15 phút [PRM-023] để ký quỹ, quá hạn đơn quay về Đang mở và thông báo cho người giao. | F200: Người gửi | G200: UC-19, UC-35, UC-63 | H200: Must | I200: Pha 1 | J200: Không ký quỹ trong 15 phút: đơn về OPEN, chào giá được ghi nhận Hết hạn. | K200: PRM-023 | L200: Chính sách nghiệp vụ | M200: Dự thảo
A201: BR-R-032 | B201: Business Rule | C201: NEG | D201: Giới hạn vòng phản giá | E201: Người gửi và người giao thương lượng tối đa 3 vòng [PRM-054] cho một chào giá; hết số vòng thì chỉ còn chấp nhận hoặc từ chối. | F201: Người gửi | G201: UC-19 | H201: Should | I201: Pha 2 | J201: Vòng phản giá thứ 4 bị chặn. | K201: PRM-054 | L201: Chính sách nghiệp vụ | M201: Dự thảo
A202: BR-R-033 | B202: Business Rule | C202: NEG | D202: Phạm vi và thời hạn chat | E202: Cuộc trò chuyện chỉ mở giữa hai bên có chào giá hoặc nhận đơn trên cùng một đơn; chuyển sang chỉ-đọc khi hết 48 giờ [PRM-071] kể từ khi đơn kết thúc. | F202: Người dùng | G202: UC-24 | H202: Must | I202: Pha 1 | J202: Người ngoài đơn không truy cập được phòng chat; sau thời hạn không gửi được tin mới. | K202: PRM-071 | L202: Chính sách nghiệp vụ | M202: Dự thảo
A203: BR-R-034 | B203: Business Rule | C203: NEG | D203: Chống giao dịch ngoài nền tảng | E203: Hệ thống phát hiện mẫu số điện thoại, số tài khoản ngân hàng, đường dẫn trong tin nhắn trước khi người giao được chọn, che nội dung và cảnh báo; vi phạm lặp lại bị xem là vi phạm quy tắc cộng đồng. | F203: Hệ thống | G203: UC-24, UC-55 | H203: Should | I203: Pha 2 | J203: Gửi chuỗi số điện thoại trước khi chọn người giao: bị che và cảnh báo. | L203: Chính sách nghiệp vụ | M203: Dự thảo
A204: BR-R-035 | B204: Business Rule | C204: TRP | D204: Thông tin bắt buộc của chuyến đi | E204: Chuyến đi phải có điểm đi, điểm đến, giờ khởi hành ở tương lai, phương tiện và sức chứa tối đa. | F204: Người giao | G204: UC-22 | H204: Should | I204: Pha 2 | J204: Thiếu bất kỳ trường nào bị từ chối. | L204: Chính sách nghiệp vụ | M204: Dự thảo
A205: BR-R-036 | B205: Business Rule | C205: TRP | D205: Điều kiện ghép đơn–chuyến | E205: Chỉ gợi ý đơn có điểm lấy và điểm giao nằm trong độ lệch ≤ 3 km [PRM-099] so với tuyến của chuyến và thời gian phù hợp khung giờ chuyến; trả tối đa 10 gợi ý [PRM-100]. | F205: Hệ thống | G205: UC-21 | H205: Should | I205: Pha 2 | J205: Đơn lệch tuyến 5 km không xuất hiện trong gợi ý. | K205: PRM-099, PRM-100 | L205: Chính sách nghiệp vụ | M205: Dự thảo
A206: BR-R-037 | B206: Business Rule | C206: TRP | D206: Hủy chuyến có đơn | E206: Chuyến đã có đơn được chọn không thể hủy trực tiếp; người giao phải hủy từng đơn theo quy tắc hủy của người giao hoặc chuyển đơn về sàn. | F206: Người giao | G206: UC-23 | H206: Should | I206: Pha 2 | J206: Hủy chuyến có đơn bị chặn và hướng dẫn cách xử lý. | L206: Chính sách nghiệp vụ | M206: Dự thảo
A207: BR-R-038 | B207: Business Rule | C207: TRK | D207: Điều kiện chuyển sang Đã lấy hàng | E207: Đơn chỉ chuyển sang Đã lấy hàng khi người giao xác nhận mã/QR lấy hàng với người gửi và chụp ảnh hàng tại điểm lấy. | F207: Người giao | G207: UC-25 | H207: Must | I207: Pha 1 | J207: Chuyển trạng thái thiếu ảnh hoặc mã bị từ chối. | L207: Chính sách nghiệp vụ | M207: Dự thảo
A208: BR-R-039 | B208: Business Rule | C208: TRK | D208: Điều kiện chuyển sang Đã giao | E208: Đơn chỉ chuyển sang Đã giao khi nhập đúng OTP giao hàng (6 chữ số [PRM-094]) hoặc quét QR của người nhận; nhập sai quá 5 lần [PRM-095] thì khóa 30 phút [PRM-096]. | F208: Người nhận | G208: UC-28 | H208: Must | I208: Pha 1 | J208: Sai OTP 5 lần: khóa 30 phút, có hướng dẫn liên hệ Hỗ trợ. | K208: PRM-094, PRM-095, PRM-096 | L208: Chính sách nghiệp vụ | M208: Dự thảo
...

Sheet 04_UC
A1: Danh mục Use Case
A2: 63 UC • luồng chính và ngoại lệ • BR liên quan tự động tổng hợp từ sheet 03 • giờ ước lượng, người phụ trách và sprint (nguồn cho sheet 13 và 14)
A4: Mã UC | B4: Tên Use Case | C4: Phân hệ | D4: Tác nhân chính | E4: Tác nhân phụ | F4: Ưu tiên | G4: Pha | H4: Tiền điều kiện | I4: Hậu điều kiện | J4: Luồng chính | K4: Luồng thay thế / ngoại lệ | L4: BR liên quan | M4: Màn hình | N4: Số API | O4: Dev | P4: Sprint hoàn thành | Q4: Tổng giờ | R4: Trạng thái | S4: Ngày bắt đầu | T4: Hạn chót
A5: UC-01 | B5: Đăng ký tài khoản | C5: AUTH | D5: Khách | E5: Dịch vụ Email/SMS | F5: Must | G5: Pha 1 | H5: Email/SĐT chưa có tài khoản. | I5: Tài khoản trạng thái Chờ xác thực được tạo; OTP đã gửi. | J5: 1. Khách mở trang đăng ký 2. Nhập họ tên, email, SĐT, mật khẩu, xác nhận đủ 18 tuổi 3. Đồng ý Điều khoản và Chính sách dữ liệu 4. Hệ thống kiểm tra định dạng và trùng lặp 5. Hệ thống tạo tài khoản (băm mật khẩu), gán vai trò Người gửi 6. Hệ thống gửi OTP và chuyển sang UC-02 | K5: • A1 Email/SĐT đã tồn tại: báo lỗi, gợi ý đăng nhập/quên mật khẩu • A2 Mật khẩu không đạt: hiển thị yêu cầu • A3 SĐT/CCCD thuộc danh sách đen: từ chối | L5: BR-F-001, BR-N-016, BR-N-030, BR-R-001, BR-R-002, BR-C-011, BR-C-022, BR-G-002 | M5: SCR-03 | N5: =COUNTIF('10_API'!$G:$G,A5) -> 1 | O5: =VLOOKUP(A5, '15_Chia task(UC)'!$D$7:$G$69, 3, FALSE) -> Lư Hữu Luân | P5: =VLOOKUP(A5, '15_Chia task(UC)'!$D$7:$G$69, 4, FALSE) -> Sprint 1 | Q5: =IF(O5="Trần Công Thuận", 6, 8) -> 8 | R5: Dự thảo | S5: =VLOOKUP(A5, '15_Chia task(UC)'!$D$7:$I$69, 5, FALSE) -> 46305 | T5: =VLOOKUP(A5, '15_Chia task(UC)'!$D$7:$I$69, 6, FALSE) -> 46307
A6: UC-02 | B6: Xác thực OTP email/SĐT | C6: AUTH | D6: Người dùng | E6: Dịch vụ Email/SMS | F6: Must | G6: Pha 1 | H6: Có tài khoản Chờ xác thực hoặc yêu cầu xác thực mới. | I6: Tài khoản/kênh liên lạc được xác thực. | J6: 1. Người dùng nhập OTP 2. Hệ thống kiểm tra mã, thời hạn, số lần thử 3. Hệ thống đánh dấu đã xác thực, kích hoạt tài khoản 4. Chuyển người dùng vào ứng dụng | K6: • A1 OTP sai: tăng đếm, báo lỗi • A2 OTP hết hạn: cho gửi lại sau thời gian chờ • A3 Quá số lần sai: vô hiệu OTP | L6: BR-F-002, BR-F-102, BR-R-003, BR-R-007 | M6: SCR-04 | N6: =COUNTIF('10_API'!$G:$G,A6) -> 2 | O6: =VLOOKUP(A6, '15_Chia task(UC)'!$D$7:$G$69, 3, FALSE) -> Lư Hữu Luân | P6: =VLOOKUP(A6, '15_Chia task(UC)'!$D$7:$G$69, 4, FALSE) -> Sprint 1 | Q6: =IF(O6="Trần Công Thuận", 6, 8) -> 8 | R6: Dự thảo | S6: =VLOOKUP(A6, '15_Chia task(UC)'!$D$7:$I$69, 5, FALSE) -> 46305 | T6: =VLOOKUP(A6, '15_Chia task(UC)'!$D$7:$I$69, 6, FALSE) -> 46307
A7: UC-03 | B7: Đăng nhập | C7: AUTH | D7: Người dùng | F7: Must | G7: Pha 1 | H7: Tài khoản tồn tại, không bị khóa. | I7: Phiên đăng nhập được tạo, trả Access/Refresh Token. | J7: 1. Người dùng nhập tài khoản và mật khẩu 2. Hệ thống xác thực thông tin 3. Hệ thống kiểm tra trạng thái, số thiết bị 4. Hệ thống cấp token và trả thông tin vai trò 5. Giao diện điều hướng theo vai trò | K7: • A1 Sai thông tin: tăng đếm sai • A2 Quá số lần sai: khóa tạm • A3 Tài khoản bị khóa: thông báo lý do chung • A4 Đăng nhập Google (Could) | L7: BR-F-003, BR-F-004, BR-N-024, BR-R-004, BR-R-005, BR-R-006, BR-C-005 | M7: SCR-05 | N7: =COUNTIF('10_API'!$G:$G,A7) -> 3 | O7: =VLOOKUP(A7, '15_Chia task(UC)'!$D$7:$G$69, 3, FALSE) -> Lư Hữu Luân | P7: =VLOOKUP(A7, '15_Chia task(UC)'!$D$7:$G$69, 4, FALSE) -> Sprint 2 | Q7: =IF(O7="Trần Công Thuận", 6, 8) -> 8 | R7: Dự thảo | S7: =VLOOKUP(A7, '15_Chia task(UC)'!$D$7:$I$69, 5, FALSE) -> 46308 | T7: =VLOOKUP(A7, '15_Chia task(UC)'!$D$7:$I$69, 6, FALSE) -> 46314
A8: UC-04 | B8: Đăng xuất và quản lý phiên/thiết bị | C8: AUTH | D8: Người dùng | F8: Must | G8: Pha 1 | H8: Đã đăng nhập. | I8: Phiên bị thu hồi. | J8: 1. Người dùng chọn Đăng xuất hoặc mở danh sách thiết bị 2. Hệ thống hiển thị phiên đang hoạt động 3. Người dùng thu hồi phiên 4. Hệ thống vô hiệu refresh token của phiên | K8: • A1 Thu hồi phiên hiện tại: chuyển về trang đăng nhập | L8: BR-F-005, BR-R-005, BR-R-006 | M8: SCR-12 | N8: =COUNTIF('10_API'!$G:$G,A8) -> 3 | O8: =VLOOKUP(A8, '15_Chia task(UC)'!$D$7:$G$69, 3, FALSE) -> Lư Hữu Luân | P8: =VLOOKUP(A8, '15_Chia task(UC)'!$D$7:$G$69, 4, FALSE) -> Sprint 2 | Q8: =IF(O8="Trần Công Thuận", 6, 8) -> 8 | R8: Dự thảo | S8: =VLOOKUP(A8, '15_Chia task(UC)'!$D$7:$I$69, 5, FALSE) -> 46308 | T8: =VLOOKUP(A8, '15_Chia task(UC)'!$D$7:$I$69, 6, FALSE) -> 46314
A9: UC-05 | B9: Quên và đặt lại mật khẩu | C9: AUTH | D9: Người dùng | E9: Dịch vụ Email/SMS | F9: Must | G9: Pha 1 | H9: Tài khoản tồn tại. | I9: Mật khẩu mới có hiệu lực; mọi phiên cũ bị thu hồi. | J9: 1. Người dùng nhập email/SĐT 2. Hệ thống gửi OTP 3. Người dùng nhập OTP và mật khẩu mới 4. Hệ thống cập nhật mật khẩu, thu hồi phiên 5. Thông báo bảo mật | K9: • A1 Email/SĐT không tồn tại: vẫn báo đã gửi (chống dò tài khoản) • A2 OTP sai/hết hạn | L9: BR-F-006, BR-N-024, BR-R-002, BR-R-003 | M9: SCR-06, SCR-07 | N9: =COUNTIF('10_API'!$G:$G,A9) -> 2 | O9: =VLOOKUP(A9, '15_Chia task(UC)'!$D$7:$G$69, 3, FALSE) -> Lư Hữu Luân | P9: =VLOOKUP(A9, '15_Chia task(UC)'!$D$7:$G$69, 4, FALSE) -> Sprint 5 | Q9: =IF(O9="Trần Công Thuận", 6, 8) -> 8 | R9: Dự thảo | S9: =VLOOKUP(A9, '15_Chia task(UC)'!$D$7:$I$69, 5, FALSE) -> 46329 | T9: =VLOOKUP(A9, '15_Chia task(UC)'!$D$7:$I$69, 6, FALSE) -> 46339
A10: UC-06 | B10: Đổi mật khẩu | C10: AUTH | D10: Người dùng | F10: Must | G10: Pha 1 | H10: Đã đăng nhập. | I10: Mật khẩu được đổi. | J10: 1. Người dùng nhập mật khẩu hiện tại và mật khẩu mới 2. Hệ thống kiểm tra 3. Hệ thống cập nhật và gửi thông báo bảo mật | K10: • A1 Sai mật khẩu hiện tại: từ chối • A2 Mật khẩu mới không đạt quy tắc | L10: BR-F-007, BR-N-016, BR-R-002 | M10: SCR-12 | N10: =COUNTIF('10_API'!$G:$G,A10) -> 1 | O10: =VLOOKUP(A10, '15_Chia task(UC)'!$D$7:$G$69, 3, FALSE) -> Lư Hữu Luân | P10: =VLOOKUP(A10, '15_Chia task(UC)'!$D$7:$G$69, 4, FALSE) -> Sprint 3 | Q10: =IF(O10="Trần Công Thuận", 6, 8) -> 8 | R10: Dự thảo | S10: =VLOOKUP(A10, '15_Chia task(UC)'!$D$7:$I$69, 5, FALSE) -> 46315 | T10: =VLOOKUP(A10, '15_Chia task(UC)'!$D$7:$I$69, 6, FALSE) -> 46321
A11: UC-07 | B11: Quản lý hồ sơ cá nhân và sổ địa chỉ | C11: KYC | D11: Người dùng | F11: Must | G11: Pha 1 | H11: Đã đăng nhập. | I11: Hồ sơ/địa chỉ được cập nhật. | J11: 1. Người dùng mở trang hồ sơ 2. Chỉnh sửa thông tin hoặc thêm/sửa/xóa địa chỉ trên bản đồ 3. Hệ thống kiểm tra và lưu 4. Nếu đổi email/SĐT, yêu cầu OTP xác thực lại | K11: • A1 Email thuộc miền FPT: cấp huy hiệu Cộng đồng FPT • A2 Yêu cầu xuất dữ liệu/xóa tài khoản: tạo hồ sơ xử lý | L11: BR-F-004, BR-F-008, BR-F-009, BR-F-124, BR-N-040, BR-R-014 | M11: SCR-10, SCR-11 | N11: =COUNTIF('10_API'!$G:$G,A11) -> 9 | O11: =VLOOKUP(A11, '15_Chia task(UC)'!$D$7:$G$69, 3, FALSE) -> Lư Hữu Luân | P11: =VLOOKUP(A11, '15_Chia task(UC)'!$D$7:$G$69, 4, FALSE) -> Sprint 4 | Q11: =IF(O11="Trần Công Thuận", 6, 8) -> 8 | R11: Dự thảo | S11: =VLOOKUP(A11, '15_Chia task(UC)'!$D$7:$I$69, 5, FALSE) -> 46322 | T11: =VLOOKUP(A11, '15_Chia task(UC)'!$D$7:$I$69, 6, FALSE) -> 46328
A12: UC-08 | B12: Gửi hồ sơ xác minh danh tính (KYC) | C12: KYC | D12: Người dùng | F12: Must | G12: Pha 1 | H12: Đã xác thực OTP. | I12: Hồ sơ KYC ở trạng thái Chờ duyệt. | J12: 1. Người dùng mở màn hình xác minh 2. Nhập thông tin CCCD 3. Tải ảnh CCCD hai mặt và ảnh chân dung cầm CCCD 4. Hệ thống kiểm tra tệp, trùng CCCD, độ tuổi 5. Hệ thống mã hóa lưu và tạo hồ sơ chờ duyệt | K12: • A1 CCCD đã gắn tài khoản khác: từ chối, đánh dấu rà soát • A2 Dưới 18 tuổi: từ chối • A3 Vượt số lần nộp lại cho phép | L12: BR-F-010, BR-F-123, BR-N-018, BR-N-023, BR-R-010, BR-R-011, BR-C-011, BR-G-002 | M12: SCR-13 | N12: =COUNTIF('10_API'!$G:$G,A12) -> 2 | O12: =VLOOKUP(A12, '15_Chia task(UC)'!$D$7:$G$69, 3, FALSE) -> Lư Hữu Luân | P12: =VLOOKUP(A12, '15_Chia task(UC)'!$D$7:$G$69, 4, FALSE) -> Sprint 4 | Q12: =IF(O12="Trần Công Thuận", 6, 8) -> 8 | R12: Dự thảo | S12: =VLOOKUP(A12, '15_Chia task(UC)'!$D$7:$I$69, 5, FALSE) -> 46322 | T12: =VLOOKUP(A12, '15_Chia task(UC)'!$D$7:$I$69, 6, FALSE) -> 46328
A13: UC-09 | B13: Duyệt hồ sơ xác minh | C13: KYC | D13: Kiểm duyệt | E13: Người dùng | F13: Must | G13: Pha 1 | H13: Có hồ sơ Chờ duyệt. | I13: Hồ sơ Đã duyệt hoặc Từ chối kèm lý do. | J13: 1. Kiểm duyệt mở hàng đợi KYC 2. Xem ảnh và thông tin đối chiếu 3. Chọn Duyệt hoặc Từ chối (chọn lý do) 4. Hệ thống cập nhật trạng thái, ghi audit 5. Hệ thống thông báo người dùng | K13: • A1 Nghi ngờ gian lận: đánh dấu và chuyển Admin • A2 Quá SLA: hệ thống cảnh báo | L13: BR-F-011, BR-R-011, BR-R-012, BR-R-082, BR-R-084 | M13: SCR-50 | N13: =COUNTIF('10_API'!$G:$G,A13) -> 4 | O13: =VLOOKUP(A13, '15_Chia task(UC)'!$D$7:$G$69, 3, FALSE) -> Trần Công Thuận | P13: =VLOOKUP(A13, '15_Chia task(UC)'!$D$7:$G$69, 4, FALSE) -> Sprint 1 | Q13: =IF(O13="Trần Công Thuận", 6, 8) -> 6 | R13: Dự thảo | S13: =VLOOKUP(A13, '15_Chia task(UC)'!$D$7:$I$69, 5, FALSE) -> 46305 | T13: =VLOOKUP(A13, '15_Chia task(UC)'!$D$7:$I$69, 6, FALSE) -> 46307
A14: UC-10 | B14: Đăng ký làm Người giao | C14: KYC | D14: Người dùng | F14: Must | G14: Pha 1 | H14: KYC đã duyệt. | I14: Tài khoản có vai trò Người giao. | J14: 1. Người dùng chọn Trở thành Người giao 2. Chọn phương tiện, khu vực, khung giờ 3. Đọc và xác nhận cam kết trách nhiệm 4. Hệ thống gán vai trò Người giao, hạng Tân binh 5. Giao diện cho phép chuyển chế độ | K14: • A1 KYC chưa duyệt: hướng dẫn đi UC-08 | L14: BR-F-012, BR-F-013, BR-R-009, BR-C-022, BR-G-002 | M14: SCR-14 | N14: =COUNTIF('10_API'!$G:$G,A14) -> 1 | O14: =VLOOKUP(A14, '15_Chia task(UC)'!$D$7:$G$69, 3, FALSE) -> Lư Hữu Luân | P14: =VLOOKUP(A14, '15_Chia task(UC)'!$D$7:$G$69, 4, FALSE) -> Sprint 3 | Q14: =IF(O14="Trần Công Thuận", 6, 8) -> 8 | R14: Dự thảo | S14: =VLOOKUP(A14, '15_Chia task(UC)'!$D$7:$I$69, 5, FALSE) -> 46315 | T14: =VLOOKUP(A14, '15_Chia task(UC)'!$D$7:$I$69, 6, FALSE) -> 46321
A15: UC-11 | B15: Ước tính giá và phí | C15: ORD | D15: Người gửi | E15: Dịch vụ Bản đồ | F15: Must | G15: Pha 1 | H15: Có điểm lấy, điểm giao, thông tin hàng. | I15: Hiển thị giá gợi ý và cấu thành phí. | J15: 1. Người gửi nhập điểm lấy và điểm giao 2. Hệ thống tính quãng đường 3. Người gửi nhập khối lượng, kích thước, mức khẩn cấp, bảo hiểm 4. Hệ thống tính giá gợi ý theo công thức 5. Hiển thị bảng cấu thành phí | K15: • A1 Dịch vụ định tuyến lỗi: dùng khoảng cách dự phòng và đánh dấu ước tính • A2 Vượt giới hạn tuyến/hàng: thông báo | L15: BR-F-014, BR-F-015, BR-F-018, BR-F-086, BR-F-122, BR-N-014, BR-R-017, BR-R-063, BR-R-065, BR-R-066, BR-R-068, BR-C-021, BR-G-001 | M15: SCR-01, SCR-02, SCR-17 | N15: =COUNTIF('10_API'!$G:$G,A15) -> 2 | O15: =VLOOKUP(A15, '15_Chia task(UC)'!$D$7:$G$69, 3, FALSE) -> Nguyễn Thành Huy | P15: =VLOOKUP(A15, '15_Chia task(UC)'!$D$7:$G$69, 4, FALSE) -> Sprint 1 | Q15: =IF(O15="Trần Công Thuận", 6, 8) -> 8 | R15: Dự thảo | S15: =VLOOKUP(A15, '15_Chia task(UC)'!$D$7:$I$69, 5, FALSE) -> 46305 | T15: =VLOOKUP(A15, '15_Chia task(UC)'!$D$7:$I$69, 6, FALSE) -> 46307
A16: UC-12 | B16: Tạo đơn giao hàng | C16: ORD | D16: Người gửi | E16: Dịch vụ Bản đồ | F16: Must | G16: Pha 1 | H16: Đã xác thực OTP, không bị khóa, chưa vượt số đơn mở. | I16: Đơn được tạo ở trạng thái Chờ kiểm duyệt hoặc Đang mở. | J16: 1. Người gửi chọn Tạo đơn 2. Chọn điểm lấy/giao 3. Khai báo hàng, tải ảnh, nhập người nhận 4. Chọn tùy chọn giao và cách tìm người giao 5. Xem giá và xác nhận đăng 6. Hệ thống kiểm tra giới hạn, sinh mã vận đơn 7. Hệ thống chạy kiểm duyệt tự động (UC-54) 8. Hệ thống đưa đơn lên sàn hoặc chuyển Kiểm duyệt | K16: • A1 Vượt giới hạn hàng: chặn và nêu lý do • A2 Lưu nháp: đơn chưa lên sàn • A3 Đơn vi phạm từ khóa: chờ kiểm duyệt | L16: BR-F-009, BR-F-015, BR-F-016, BR-F-017, BR-F-018, BR-F-019, BR-F-020, BR-F-025, BR-F-122, BR-F-123, BR-N-002, BR-N-023, BR-N-027, BR-N-030, BR-R-007, BR-R-015, BR-R-016, BR-R-017, BR-R-018, BR-R-019, BR-R-020, BR-R-023, BR-R-026, BR-R-080, BR-C-012, BR-C-020, BR-G-001 | M16: SCR-17 | N16: =COUNTIF('10_API'!$G:$G,A16) -> 6 | O16: =VLOOKUP(A16, '15_Chia task(UC)'!$D$7:$G$69, 3, FALSE) -> Nguyễn Thành Huy | P16: =VLOOKUP(A16, '15_Chia task(UC)'!$D$7:$G$69, 4, FALSE) -> Sprint 1 | Q16: =IF(O16="Trần Công Thuận", 6, 8) -> 8 | R16: Dự thảo | S16: =VLOOKUP(A16, '15_Chia task(UC)'!$D$7:$I$69, 5, FALSE) -> 46305 | T16: =VLOOKUP(A16, '15_Chia task(UC)'!$D$7:$I$69, 6, FALSE) -> 46307
A17: UC-13 | B17: Xem danh sách và chi tiết đơn của tôi | C17: ORD | D17: Người dùng | F17: Must | G17: Pha 1 | H17: Đã đăng nhập. | I17: Hiển thị dữ liệu đơn thuộc quyền. | J17: 1. Người dùng mở Đơn của tôi 2. Lọc theo trạng thái/thời gian, tìm theo mã 3. Chọn một đơn 4. Hệ thống hiển thị chi tiết, người giao, giá, bằng chứng, timeline | K17: • A1 Truy cập đơn không thuộc quyền: 403/404 | L17: BR-F-020, BR-F-021, BR-F-022, BR-F-025, BR-N-001, BR-N-020, BR-N-031, BR-R-023, BR-R-045 | M17: SCR-16, SCR-18, SCR-19, SCR-31 | N17: =COUNTIF('10_API'!$G:$G,A17) -> 3 | O17: =VLOOKUP(A17, '15_Chia task(UC)'!$D$7:$G$69, 3, FALSE) -> Nguyễn Thành Huy | P17: =VLOOKUP(A17, '15_Chia task(UC)'!$D$7:$G$69, 4, FALSE) -> Sprint 2 | Q17: =IF(O17="Trần Công Thuận", 6, 8) -> 8 | R17: Dự thảo | S17: =VLOOKUP(A17, '15_Chia task(UC)'!$D$7:$I$69, 5, FALSE) -> 46308 | T17: =VLOOKUP(A17, '15_Chia task(UC)'!$D$7:$I$69, 6, FALSE) -> 46314
A18: UC-14 | B18: Sửa đơn | C18: ORD | D18: Người gửi | F18: Must | G18: Pha 1 | H18: Đơn ở Chờ kiểm duyệt/Đang mở, chưa có chào giá được chấp nhận. | I18: Đơn được cập nhật; chào giá bị ảnh hưởng được hủy. | J18: 1. Người gửi chọn Sửa đơn 2. Chỉnh thông tin 3. Hệ thống cảnh báo ảnh hưởng đến chào giá 4. Người gửi xác nhận 5. Hệ thống lưu, kiểm duyệt lại nếu cần, thông báo người đã chào giá | K18: • A1 Đơn đã có người giao: không cho sửa | L18: BR-F-023, BR-R-019, BR-R-021 | M18: SCR-20 | N18: =COUNTIF('10_API'!$G:$G,A18) -> 1 | O18: =VLOOKUP(A18, '15_Chia task(UC)'!$D$7:$G$69, 3, FALSE) -> Nguyễn Thành Huy | P18: =VLOOKUP(A18, '15_Chia task(UC)'!$D$7:$G$69, 4, FALSE) -> Sprint 2 | Q18: =IF(O18="Trần Công Thuận", 6, 8) -> 8 | R18: Dự thảo | S18: =VLOOKUP(A18, '15_Chia task(UC)'!$D$7:$I$69, 5, FALSE) -> 46308 | T18: =VLOOKUP(A18, '15_Chia task(UC)'!$D$7:$I$69, 6, FALSE) -> 46314
A19: UC-15 | B19: Hủy đơn | C19: ORD | D19: Người gửi | E19: Người giao | F19: Must | G19: Pha 1 | H19: Đơn chưa ở trạng thái Đã lấy hàng. | I19: Đơn Đã hủy; tiền xử lý theo quy tắc hủy. | J19: 1. Người dùng chọn Hủy đơn 2. Hệ thống hiển thị phí hủy và số tiền hoàn 3. Người dùng nhập lý do và xác nhận 4. Hệ thống cập nhật trạng thái, thực hiện hoàn tiền (UC-37), thông báo bên còn lại | K19: • A1 Người giao hủy: trừ điểm uy tín, đơn quay về sàn • A2 Đơn đã lấy hàng: hướng dẫn UC-29/UC-30 | L19: BR-F-024, BR-R-022, BR-R-075 | N19: =COUNTIF('10_API'!$G:$G,A19) -> 1 | O19: =VLOOKUP(A19, '15_Chia task(UC)'!$D$7:$G$69, 3, FALSE) -> Nguyễn Thành Huy | P19: =VLOOKUP(A19, '15_Chia task(UC)'!$D$7:$G$69, 4, FALSE) -> Sprint 5 | Q19: =IF(O19="Trần Công Thuận", 6, 8) -> 8 | R19: Dự thảo | S19: =VLOOKUP(A19, '15_Chia task(UC)'!$D$7:$I$69, 5, FALSE) -> 46329 | T19: =VLOOKUP(A19, '15_Chia task(UC)'!$D$7:$I$69, 6, FALSE) -> 46339
A20: UC-16 | B20: Duyệt và tìm kiếm sàn đơn | C20: MKT | D20: Người giao | F20: Must | G20: Pha 1 | H20: Người giao đã được duyệt. | I20: Hiển thị danh sách đơn đủ điều kiện. | J20: 1. Người giao mở Sàn đơn 2. Hệ thống hiển thị đơn Đang mở (ẩn thông tin nhạy cảm) 3. Người giao lọc/sắp xếp hoặc xem bản đồ 4. Chọn một đơn để xem chi tiết | K20: • A1 Không có đơn phù hợp: gợi ý đăng ký thông báo khu vực | L20: BR-F-026, BR-F-027, BR-F-028, BR-F-035, BR-N-001, BR-N-006, BR-N-031, BR-R-024, BR-R-027, BR-G-003 | M20: SCR-28, SCR-29 | N20: =COUNTIF('10_API'!$G:$G,A20) -> 4 | O20: =VLOOKUP(A20, '15_Chia task(UC)'!$D$7:$G$69, 3, FALSE) -> Võ Quốc An | P20: =VLOOKUP(A20, '15_Chia task(UC)'!$D$7:$G$69, 4, FALSE) -> Sprint 1 | Q20: =IF(O20="Trần Công Thuận", 6, 8) -> 8 | R20: Dự thảo | S20: =VLOOKUP(A20, '15_Chia task(UC)'!$D$7:$I$69, 5, FALSE) -> 46305 | T20: =VLOOKUP(A20, '15_Chia task(UC)'!$D$7:$I$69, 6, FALSE) -> 46307
A21: UC-17 | B21: Nhận đơn (giá niêm yết) | C21: MKT | D21: Người giao | E21: Người gửi | F21: Must | G21: Pha 1 | H21: Đơn Đang mở; người giao đủ điều kiện hạng/hạn mức. | I21: Đơn chuyển Chờ ký quỹ, gắn người giao. | J21: 1. Người giao chọn Nhận đơn 2. Hệ thống kiểm tra KYC, hạn mức, hạng, giá trị cao 3. Hệ thống khóa đơn cho người giao (xử lý tranh chấp đồng thời) 4. Hệ thống chuyển trạng thái, thông báo người gửi để ký quỹ | K21: • A1 Người khác đã nhận: báo đơn không còn khả dụng • A2 Vượt hạn mức: từ chối kèm lý do | L21: BR-F-029, BR-N-027, BR-R-008, BR-R-009, BR-R-024, BR-R-025, BR-R-028, BR-G-003 | M21: SCR-30 | N21: =COUNTIF('10_API'!$G:$G,A21) -> 1 | O21: =VLOOKUP(A21, '15_Chia task(UC)'!$D$7:$G$69, 3, FALSE) -> Võ Quốc An | P21: =VLOOKUP(A21, '15_Chia task(UC)'!$D$7:$G$69, 4, FALSE) -> Sprint 1 | Q21: =IF(O21="Trần Công Thuận", 6, 8) -> 8 | R21: Dự thảo | S21: =VLOOKUP(A21, '15_Chia task(UC)'!$D$7:$I$69, 5, FALSE) -> 46305 | T21: =VLOOKUP(A21, '15_Chia task(UC)'!$D$7:$I$69, 6, FALSE) -> 46307
A22: UC-18 | B22: Gửi chào giá | C22: MKT | D22: Người giao | E22: Người gửi | F22: Must | G22: Pha 1 | H22: Đơn Đang mở; người giao đủ điều kiện. | I22: Chào giá ở trạng thái Chờ phản hồi. | J22: 1. Người giao nhập giá chào, lời nhắn, thời gian lấy dự kiến 2. Hệ thống kiểm tra biên giá 3. Hệ thống lưu chào giá (thay thế chào giá cũ nếu có) 4. Thông báo người gửi | K22: • A1 Giá ngoài biên: từ chối | L22: BR-F-030, BR-N-002, BR-R-008, BR-R-009, BR-R-028, BR-R-029, BR-R-030, BR-G-003 | M22: SCR-30 | N22: =COUNTIF('10_API'!$G:$G,A22) -> 3 | O22: =VLOOKUP(A22, '15_Chia task(UC)'!$D$7:$G$69, 3, FALSE) -> Võ Quốc An | P22: =VLOOKUP(A22, '15_Chia task(UC)'!$D$7:$G$69, 4, FALSE) -> Sprint 2 | Q22: =IF(O22="Trần Công Thuận", 6, 8) -> 8 | R22: Dự thảo | S22: =VLOOKUP(A22, '15_Chia task(UC)'!$D$7:$I$69, 5, FALSE) -> 46308 | T22: =VLOOKUP(A22, '15_Chia task(UC)'!$D$7:$I$69, 6, FALSE) -> 46314
A23: UC-19 | B23: Xử lý chào giá (chấp nhận, từ chối, phản giá) | C23: MKT | D23: Người gửi | E23: Người giao | F23: Must | G23: Pha 1 | H23: Đơn có chào giá hiệu lực. | I23: Chào giá được chấp nhận/từ chối/phản giá. | J23: 1. Người gửi mở danh sách chào giá 2. So sánh giá, hạng, điểm uy tín 3. Chọn chấp nhận, từ chối hoặc phản giá 4. Nếu chấp nhận: chốt người giao, từ chối các chào giá khác, đơn sang Chờ ký quỹ 5. Thông báo các bên | K23: • A1 Phản giá: người giao có thể chấp nhận hoặc phản giá lại theo giới hạn vòng • A2 Chào giá hết hạn: tự động Hết hạn | L23: BR-F-031, BR-F-032, BR-F-086, BR-F-094, BR-R-025, BR-R-029, BR-R-031, BR-R-032 | M23: SCR-21 | N23: =COUNTIF('10_API'!$G:$G,A23) -> 4 | O23: =VLOOKUP(A23, '15_Chia task(UC)'!$D$7:$G$69, 3, FALSE) -> Võ Quốc An | P23: =VLOOKUP(A23, '15_Chia task(UC)'!$D$7:$G$69, 4, FALSE) -> Sprint 2 | Q23: =IF(O23="Trần Công Thuận", 6, 8) -> 8 | R23: Dự thảo | S23: =VLOOKUP(A23, '15_Chia task(UC)'!$D$7:$I$69, 5, FALSE) -> 46308 | T23: =VLOOKUP(A23, '15_Chia task(UC)'!$D$7:$I$69, 6, FALSE) -> 46314
A24: UC-20 | B24: Mời trực tiếp người giao | C24: MKT | D24: Người gửi | E24: Người giao | F24: Could | G24: Pha 3 | H24: Người gửi có đơn Đang mở hoặc đang tạo. | I24: Lời mời được gửi. | J24: 1. Người gửi chọn người giao yêu thích hoặc tìm theo mã 2. Gửi lời mời kèm đơn 3. Người giao nhận thông báo, chấp nhận hoặc từ chối | K24: • A1 Lời mời hết hạn: đơn lên sàn công khai | L24: BR-F-019, BR-F-033 | N24: =COUNTIF('10_API'!$G:$G,A24) -> 2 | O24: =VLOOKUP(A24, '15_Chia task(UC)'!$D$7:$G$69, 3, FALSE) -> Võ Quốc An | P24: =VLOOKUP(A24, '15_Chia task(UC)'!$D$7:$G$69, 4, FALSE) -> Sprint 4 | Q24: =IF(O24="Trần Công Thuận", 6, 8) -> 8 | R24: Dự thảo | S24: =VLOOKUP(A24, '15_Chia task(UC)'!$D$7:$I$69, 5, FALSE) -> 46322 | T24: =VLOOKUP(A24, '15_Chia task(UC)'!$D$7:$I$69, 6, FALSE) -> 46328
A25: UC-21 | B25: Gợi ý ghép đơn–chuyến | C25: MKT | D25: Hệ thống | E25: Người giao, Người gửi | F25: Should | G25: Pha 2 | H25: Có chuyến đi và đơn đang mở. | I25: Danh sách gợi ý được tạo và hiển thị. | J25: 1. Hệ thống tải chuyến đi và đơn mở 2. Tính khoảng cách lệch tuyến và độ phù hợp thời gian 3. Chấm điểm phù hợp và xếp hạng 4. Hiển thị gợi ý cho người giao và người gửi 5. Cho phép nhận hoặc chào giá nhanh | K25: • A1 Không có đơn trong độ lệch cho phép: không gợi ý | L25: BR-F-034, BR-F-038, BR-N-008, BR-R-036, BR-G-008 | M25: SCR-34 | N25: =COUNTIF('10_API'!$G:$G,A25) -> 2 | O25: =VLOOKUP(A25, '15_Chia task(UC)'!$D$7:$G$69, 3, FALSE) -> Võ Quốc An | P25: =VLOOKUP(A25, '15_Chia task(UC)'!$D$7:$G$69, 4, FALSE) -> Sprint 4 | Q25: =IF(O25="Trần Công Thuận", 6, 8) -> 8 | R25: Dự thảo | S25: =VLOOKUP(A25, '15_Chia task(UC)'!$D$7:$I$69, 5, FALSE) -> 46322 | T25: =VLOOKUP(A25, '15_Chia task(UC)'!$D$7:$I$69, 6, FALSE) -> 46328
A26: UC-22 | B26: Đăng chuyến đi | C26: TRP | D26: Người giao | E26: Dịch vụ Bản đồ | F26: Should | G26: Pha 2 | H26: Người giao đã được duyệt. | I26: Chuyến đi được tạo. | J26: 1. Người giao nhập điểm đi, điểm đến, giờ khởi hành 2. Chọn phương tiện, sức chứa, giá sàn 3. Hệ thống tính tuyến đường 4. Lưu chuyến và kích hoạt gợi ý ghép | K26: • A1 Chuyến định kỳ (Could): sinh các lần khởi hành | L26: BR-F-036, BR-F-037, BR-F-038, BR-R-035, BR-G-008 | M26: SCR-33 | N26: =COUNTIF('10_API'!$G:$G,A26) -> 2 | O26: =VLOOKUP(A26, '15_Chia task(UC)'!$D$7:$G$69, 3, FALSE) -> Võ Quốc An | P26: =VLOOKUP(A26, '15_Chia task(UC)'!$D$7:$G$69, 4, FALSE) -> Sprint 3 | Q26: =IF(O26="Trần Công Thuận", 6, 8) -> 8 | R26: Dự thảo | S26: =VLOOKUP(A26, '15_Chia task(UC)'!$D$7:$I$69, 5, FALSE) -> 46315 | T26: =VLOOKUP(A26, '15_Chia task(UC)'!$D$7:$I$69, 6, FALSE) -> 46321
A27: UC-23 | B27: Quản lý chuyến đi | C27: TRP | D27: Người giao | F27: Should | G27: Pha 2 | H27: Có chuyến đi. | I27: Chuyến được cập nhật/hủy/kết thúc. | J27: 1. Người giao mở danh sách chuyến 2. Sửa, tạm dừng nhận đơn, hủy hoặc kết thúc 3. Hệ thống kiểm tra quy tắc chuyến có đơn | K27: • A1 Chuyến có đơn đã chọn: không hủy trực tiếp | L27: BR-F-039, BR-F-040, BR-R-037 | M27: SCR-34 | N27: =COUNTIF('10_API'!$G:$G,A27) -> 5 | O27: =VLOOKUP(A27, '15_Chia task(UC)'!$D$7:$G$69, 3, FALSE) -> Võ Quốc An | P27: =VLOOKUP(A27, '15_Chia task(UC)'!$D$7:$G$69, 4, FALSE) -> Sprint 3 | Q27: =IF(O27="Trần Công Thuận", 6, 8) -> 8 | R27: Dự thảo | S27: =VLOOKUP(A27, '15_Chia task(UC)'!$D$7:$I$69, 5, FALSE) -> 46315 | T27: =VLOOKUP(A27, '15_Chia task(UC)'!$D$7:$I$69, 6, FALSE) -> 46321
A28: UC-24 | B28: Chat theo đơn | C28: NEG | D28: Người dùng | F28: Must | G28: Pha 1 | H28: Đơn có chào giá hoặc đã có người giao. | I28: Tin nhắn được gửi và lưu. | J28: 1. Người dùng mở phòng chat của đơn 2. Hệ thống nạp lịch sử 3. Người dùng gửi tin nhắn hoặc ảnh 4. Hệ thống kiểm tra mẫu thông tin liên hệ, lưu MongoDB, đẩy cho bên kia 5. Cập nhật đã đọc | K28: • A1 Tin nhắn chứa SĐT/tài khoản trước khi chọn người giao: che và cảnh báo • A2 Báo cáo tin nhắn: UC-55 | L28: BR-F-041, BR-F-042, BR-F-043, BR-F-044, BR-F-045, BR-N-011, BR-R-033, BR-R-034, BR-C-004 | M28: SCR-38 | N28: =COUNTIF('10_API'!$G:$G,A28) -> 4 | O28: =VLOOKUP(A28, '15_Chia task(UC)'!$D$7:$G$69, 3, FALSE) -> Huỳnh Phi Long | P28: =VLOOKUP(A28, '15_Chia task(UC)'!$D$7:$G$69, 4, FALSE) -> Sprint 1 | Q28: =IF(O28="Trần Công Thuận", 6, 8) -> 8 | R28: Dự thảo | S28: =VLOOKUP(A28, '15_Chia task(UC)'!$D$7:$I$69, 5, FALSE) -> 46305 | T28: =VLOOKUP(A28, '15_Chia task(UC)'!$D$7:$I$69, 6, FALSE) -> 46307
A29: UC-25 | B29: Xác nhận lấy hàng (QR + ảnh) | C29: TRK | D29: Người giao | E29: Người gửi | F29: Must | G29: Pha 1 | H29: Đơn Đã ký quỹ. | I29: Đơn chuyển Đã lấy hàng. | J29: 1. Người giao đến điểm lấy, mở Lấy hàng 2. Người gửi hiển thị mã QR lấy hàng 3. Người giao quét/nhập mã 4. Người giao chụp ảnh hàng 5. Hệ thống chuyển trạng thái, bắt đầu chia sẻ vị trí, thông báo | K29: • A1 Mã sai/hết hạn: làm mới mã • A2 Quá hạn lấy hàng: hệ thống xử lý theo UC-63 | L29: BR-F-046, BR-F-047, BR-F-123, BR-N-023, BR-R-038, BR-G-009 | M29: SCR-24, SCR-32 | N29: =COUNTIF('10_API'!$G:$G,A29) -> 2 | O29: =VLOOKUP(A29, '15_Chia task(UC)'!$D$7:$G$69, 3, FALSE) -> Huỳnh Phi Long | P29: =VLOOKUP(A29, '15_Chia task(UC)'!$D$7:$G$69, 4, FALSE) -> Sprint 3 | Q29: =IF(O29="Trần Công Thuận", 6, 8) -> 8 | R29: Dự thảo | S29: =VLOOKUP(A29, '15_Chia task(UC)'!$D$7:$I$69, 5, FALSE) -> 46315 | T29: =VLOOKUP(A29, '15_Chia task(UC)'!$D$7:$I$69, 6, FALSE) -> 46321
A30: UC-26 | B30: Chia sẻ vị trí và cập nhật hành trình | C30: TRK | D30: Người giao | F30: Must | G30: Pha 1 | H30: Đơn Đã lấy hàng/Đang giao. | I30: Điểm vị trí và mốc hành trình được lưu. | J30: 1. Người giao cấp quyền vị trí 2. Ứng dụng gửi vị trí theo chu kỳ 3. Hệ thống lưu MongoDB và đẩy tới người theo dõi 4. Người giao cập nhật mốc Đang giao, Đã đến điểm giao | K30: • A1 Không có quyền vị trí: chặn chuyển trạng thái và hướng dẫn • A2 Mất mạng: gửi bù khi có lại • A3 Đứng yên/lệch tuyến: cảnh báo (Could) | L30: BR-F-048, BR-F-049, BR-F-056, BR-N-007, BR-R-041, BR-C-017 | M30: SCR-32 | N30: =COUNTIF('10_API'!$G:$G,A30) -> 2 | O30: =VLOOKUP(A30, '15_Chia task(UC)'!$D$7:$G$69, 3, FALSE) -> Huỳnh Phi Long | P30: =VLOOKUP(A30, '15_Chia task(UC)'!$D$7:$G$69, 4, FALSE) -> Sprint 1 | Q30: =IF(O30="Trần Công Thuận", 6, 8) -> 8 | R30: Dự thảo | S30: =VLOOKUP(A30, '15_Chia task(UC)'!$D$7:$I$69, 5, FALSE) -> 46305 | T30: =VLOOKUP(A30, '15_Chia task(UC)'!$D$7:$I$69, 6, FALSE) -> 46307
A31: UC-27 | B31: Theo dõi đơn thời gian thực | C31: TRK | D31: Người gửi | E31: Người nhận | F31: Must | G31: Pha 1 | H31: Đơn đang giao hoặc có liên kết theo dõi. | I31: Hiển thị vị trí, timeline, ETA. | J31: 1. Người gửi hoặc người nhận mở màn hình theo dõi 2. Hệ thống nạp timeline và vị trí gần nhất 3. Nhận cập nhật qua WebSocket 4. Hiển thị bản đồ, ETA, trạng thái | K31: • A1 Người nhận mở liên kết công khai: chỉ thấy thông tin tối thiểu • A2 Liên kết hết hạn: thông báo | L31: BR-F-022, BR-F-050, BR-F-051, BR-F-062, BR-F-122, BR-N-007, BR-N-011, BR-R-042, BR-C-004 | M31: SCR-09, SCR-23 | N31: =COUNTIF('10_API'!$G:$G,A31) -> 3 | O31: =VLOOKUP(A31, '15_Chia task(UC)'!$D$7:$G$69, 3, FALSE) -> Huỳnh Phi Long | P31: =VLOOKUP(A31, '15_Chia task(UC)'!$D$7:$G$69, 4, FALSE) -> Sprint 2 | Q31: =IF(O31="Trần Công Thuận", 6, 8) -> 8 | R31: Dự thảo | S31: =VLOOKUP(A31, '15_Chia task(UC)'!$D$7:$I$69, 5, FALSE) -> 46308 | T31: =VLOOKUP(A31, '15_Chia task(UC)'!$D$7:$I$69, 6, FALSE) -> 46314
A32: UC-28 | B32: Xác nhận giao hàng (OTP/QR + ảnh) | C32: TRK | D32: Người giao | E32: Người nhận | F32: Must | G32: Pha 1 | H32: Đơn Đang giao, người giao đã đến điểm giao. | I32: Đơn Đã giao; bắt đầu đếm giải ngân. | J32: 1. Hệ thống gửi OTP cho người nhận 2. Người nhận đưa OTP hoặc QR 3. Người giao nhập/quét và chụp ảnh giao 4. Hệ thống kiểm tra, chuyển Đã giao, ngừng chia sẻ vị trí 5. Thông báo người gửi và đặt lịch giải ngân | K32: • A1 OTP sai: tăng đếm, khóa khi quá số lần • A2 Người nhận không có OTP: giao ngoại lệ kèm ảnh, tọa độ, lý do • A3 Người nhận vắng: UC-30 | L32: BR-F-052, BR-F-053, BR-F-103, BR-F-123, BR-N-027, BR-R-039, BR-R-040, BR-G-004, BR-G-009 | M32: SCR-32 | N32: =COUNTIF('10_API'!$G:$G,A32) -> 3 | O32: =VLOOKUP(A32, '15_Chia task(UC)'!$D$7:$G$69, 3, FALSE) -> Huỳnh Phi Long | P32: =VLOOKUP(A32, '15_Chia task(UC)'!$D$7:$G$69, 4, FALSE) -> Sprint 2 | Q32: =IF(O32="Trần Công Thuận", 6, 8) -> 8 | R32: Dự thảo | S32: =VLOOKUP(A32, '15_Chia task(UC)'!$D$7:$I$69, 5, FALSE) -> 46308 | T32: =VLOOKUP(A32, '15_Chia task(UC)'!$D$7:$I$69, 6, FALSE) -> 46314
A33: UC-29 | B33: Báo sự cố khi giao | C33: TRK | D33: Người giao | E33: Người gửi, Kiểm duyệt | F33: Must | G33: Pha 1 | H33: Đơn đã Đã lấy hàng/Đang giao. | I33: Sự cố được ghi nhận, các bên được thông báo. | J33: 1. Người giao chọn Báo sự cố 2. Chọn loại sự cố, mô tả, ảnh 3. Hệ thống ghi vào timeline 4. Thông báo người gửi và Kiểm duyệt | K33: • A1 SOS khẩn cấp: cảnh báo ưu tiên kèm vị trí | L33: BR-F-054, BR-F-110 | M33: SCR-32 | N33: =COUNTIF('10_API'!$G:$G,A33) -> 2 | O33: =VLOOKUP(A33, '15_Chia task(UC)'!$D$7:$G$69, 3, FALSE) -> Huỳnh Phi Long | P33: =VLOOKUP(A33, '15_Chia task(UC)'!$D$7:$G$69, 4, FALSE) -> Sprint 3 | Q33: =IF(O33="Trần Công Thuận", 6, 8) -> 8 | R33: Dự thảo | S33: =VLOOKUP(A33, '15_Chia task(UC)'!$D$7:$I$69, 5, FALSE) -> 46315 | T33: =VLOOKUP(A33, '15_Chia task(UC)'!$D$7:$I$69, 6, FALSE) -> 46321
A34: UC-30 | B34: Giao thất bại và hoàn hàng | C34: TRK | D34: Người giao | E34: Người gửi | F34: Must | G34: Pha 1 | H34: Đơn Đang giao; không giao được. | I34: Đơn Đang hoàn rồi Đã hoàn hàng. | J34: 1. Người giao ghi nhận không liên lạc được người nhận 2. Hệ thống kiểm tra bằng chứng liên hệ 3. Đơn chuyển Giao thất bại rồi Đang hoàn 4. Người giao trả hàng, người gửi xác nhận bằng mã 5. Hệ thống tính phí giao và phí hoàn | K34: • A1 Người nhận liên lạc lại: tiếp tục giao | L34: BR-F-055, BR-R-044 | M34: SCR-24, SCR-32 | N34: =COUNTIF('10_API'!$G:$G,A34) -> 2 | O34: =VLOOKUP(A34, '15_Chia task(UC)'!$D$7:$G$69, 3, FALSE) -> Huỳnh Phi Long | P34: =VLOOKUP(A34, '15_Chia task(UC)'!$D$7:$G$69, 4, FALSE) -> Sprint 4 | Q34: =IF(O34="Trần Công Thuận", 6, 8) -> 8 | R34: Dự thảo | S34: =VLOOKUP(A34, '15_Chia task(UC)'!$D$7:$I$69, 5, FALSE) -> 46322 | T34: =VLOOKUP(A34, '15_Chia task(UC)'!$D$7:$I$69, 6, FALSE) -> 46328
A35: UC-31 | B35: Gộp đơn và gợi ý lộ trình | C35: REL | D35: Người giao | F35: Could | G35: Pha 3 | H35: Người giao có từ 2 đơn trở lên. | I35: Lượt giao gộp được tạo. | J35: 1. Người giao chọn các đơn cùng tuyến 2. Hệ thống kiểm tra giới hạn gộp 3. Hệ thống tính thứ tự điểm dừng 4. Người giao xác nhận lộ trình | K35: • A1 Vượt giới hạn số đơn/sức chứa: từ chối | L35: BR-F-057, BR-F-058, BR-R-046 | M35: SCR-36 | N35: =COUNTIF('10_API'!$G:$G,A35) -> 2 | O35: =VLOOKUP(A35, '15_Chia task(UC)'!$D$7:$G$69, 3, FALSE) -> Võ Quốc An | P35: =VLOOKUP(A35, '15_Chia task(UC)'!$D$7:$G$69, 4, FALSE) -> Sprint 5 | Q35: =IF(O35="Trần Công Thuận", 6, 8) -> 8 | R35: Dự thảo | S35: =VLOOKUP(A35, '15_Chia task(UC)'!$D$7:$I$69, 5, FALSE) -> 46329 | T35: =VLOOKUP(A35, '15_Chia task(UC)'!$D$7:$I$69, 6, FALSE) -> 46339
A36: UC-32 | B36: Tạo đơn giao tiếp sức | C36: REL | D36: Người gửi | E36: Người giao | F36: Could | G36: Pha 3 | H36: Tuyến đủ dài và đủ điều kiện chia chặng. | I36: Đơn có nhiều chặng ở trạng thái Đang mở theo chặng. | J36: 1. Người gửi chọn Giao tiếp sức 2. Hệ thống đề xuất điểm bàn giao và chặng 3. Người gửi xác nhận, hệ thống chia phí theo quãng đường 4. Mỗi chặng lên sàn riêng | K36: • A1 Không đủ người giao cho chặng: giữ đơn mở | L36: BR-F-059, BR-F-062, BR-R-047 | N36: =COUNTIF('10_API'!$G:$G,A36) -> 1 | O36: =VLOOKUP(A36, '15_Chia task(UC)'!$D$7:$G$69, 3, FALSE) -> Nguyễn Thành Huy | P36: =VLOOKUP(A36, '15_Chia task(UC)'!$D$7:$G$69, 4, FALSE) -> Sprint 4 | Q36: =IF(O36="Trần Công Thuận", 6, 8) -> 8 | R36: Dự thảo | S36: =VLOOKUP(A36, '15_Chia task(UC)'!$D$7:$I$69, 5, FALSE) -> 46322 | T36: =VLOOKUP(A36, '15_Chia task(UC)'!$D$7:$I$69, 6, FALSE) -> 46328
A37: UC-33 | B37: Bàn giao giữa các chặng | C37: REL | D37: Người giao | F37: Could | G37: Pha 3 | H37: Đơn tiếp sức có chặng kế tiếp. | I37: Trách nhiệm chuyển sang người giao kế tiếp. | J37: 1. Hai người giao gặp nhau tại điểm hẹn 2. Người giao kế tiếp quét QR bàn giao 3. Hai bên chụp ảnh hàng 4. Hệ thống xác nhận, bắt đầu chặng tiếp theo | K37: • A1 QR hết hạn: làm mới • A2 Bàn giao không thành: sự cố | L37: BR-F-060, BR-F-061, BR-R-048 | N37: =COUNTIF('10_API'!$G:$G,A37) -> 1 | O37: =VLOOKUP(A37, '15_Chia task(UC)'!$D$7:$G$69, 3, FALSE) -> Võ Quốc An | P37: =VLOOKUP(A37, '15_Chia task(UC)'!$D$7:$G$69, 4, FALSE) -> Sprint 5 | Q37: =IF(O37="Trần Công Thuận", 6, 8) -> 8 | R37: Dự thảo | S37: =VLOOKUP(A37, '15_Chia task(UC)'!$D$7:$I$69, 5, FALSE) -> 46329 | T37: =VLOOKUP(A37, '15_Chia task(UC)'!$D$7:$I$69, 6, FALSE) -> 46336
A38: UC-34 | B38: Nạp tiền vào ví qua VNPay | C38: PAY | D38: Người dùng | E38: VNPay | F38: Must | G38: Pha 1 | H38: Đã xác thực OTP; không vượt số dư tối đa. | I38: Giao dịch nạp tạo; ví tăng khi IPN thành công. | J38: 1. Người dùng chọn Nạp tiền và nhập số tiền 2. Hệ thống kiểm tra hạn mức, tạo giao dịch và liên kết có chữ ký 3. Chuyển người dùng sang VNPay 4. Người dùng thanh toán 5. VNPay gọi IPN (UC-42) và chuyển người dùng về Return URL 6. Hệ thống hiển thị kết quả theo dữ liệu đã xác minh | K38: • A1 Người dùng hủy/đóng trang: giao dịch hết hạn • A2 Thanh toán thất bại: hiển thị lý do • A3 IPN đến trễ: dùng truy vấn kết quả | L38: BR-F-063, BR-F-064, BR-F-065, BR-F-071, BR-N-003, BR-N-014, BR-R-007, BR-R-050, BR-R-051, BR-R-052, BR-C-006, BR-C-019 | M38: SCR-42, SCR-43 | N38: =COUNTIF('10_API'!$G:$G,A38) -> 2 | O38: =VLOOKUP(A38, '15_Chia task(UC)'!$D$7:$G$69, 3, FALSE) -> Lê Nhựt Huy | P38: =VLOOKUP(A38, '15_Chia task(UC)'!$D$7:$G$69, 4, FALSE) -> Sprint 1 | Q38: =IF(O38="Trần Công Thuận", 6, 8) -> 8 | R38: Dự thảo | S38: =VLOOKUP(A38, '15_Chia task(UC)'!$D$7:$I$69, 5, FALSE) -> 46305 | T38: =VLOOKUP(A38, '15_Chia task(UC)'!$D$7:$I$69, 6, FALSE) -> 46307
A39: UC-35 | B39: Thanh toán đơn và ký quỹ | C39: PAY | D39: Người gửi | E39: VNPay | F39: Must | G39: Pha 1 | H39: Đơn Chờ ký quỹ, trong thời gian giữ chỗ. | I39: Tiền ký quỹ được giữ; đơn Đã ký quỹ. | J39: 1. Người gửi xem số tiền cần ký quỹ, áp mã (nếu có) 2. Chọn thanh toán bằng ví hoặc VNPay trực tiếp 3. Hệ thống kiểm tra số dư/tạo giao dịch VNPay 4. Hệ thống ghi bút toán ký quỹ 5. Đơn chuyển Đã ký quỹ, thông báo người giao | K39: • A1 Ví không đủ: gợi ý nạp thêm hoặc VNPay • A2 Hết thời gian giữ chỗ: đơn về Đang mở • A3 VNPay thất bại: cho thử lại trong thời hạn | L39: BR-F-064, BR-F-070, BR-F-071, BR-F-072, BR-F-086, BR-N-003, BR-N-021, BR-N-039, BR-R-031, BR-R-052, BR-R-053, BR-R-068, BR-C-006, BR-C-009, BR-G-012 | M39: SCR-22, SCR-43 | N39: =COUNTIF('10_API'!$G:$G,A39) -> 1 | O39: =VLOOKUP(A39, '15_Chia task(UC)'!$D$7:$G$69, 3, FALSE) -> Lê Nhựt Huy | P39: =VLOOKUP(A39, '15_Chia task(UC)'!$D$7:$G$69, 4, FALSE) -> Sprint 1 | Q39: =IF(O39="Trần Công Thuận", 6, 8) -> 8 | R39: Dự thảo | S39: =VLOOKUP(A39, '15_Chia task(UC)'!$D$7:$I$69, 5, FALSE) -> 46305 | T39: =VLOOKUP(A39, '15_Chia task(UC)'!$D$7:$I$69, 6, FALSE) -> 46307
A40: UC-36 | B40: Giải ngân cho người giao | C40: PAY | D40: Hệ thống | E40: Người giao | F40: Must | G40: Pha 1 | H40: Đơn Đã giao và thỏa điều kiện giải ngân. | I40: Thu nhập vào ví người giao; hoa hồng và quỹ được ghi nhận. | J40: 1. Hệ thống xác định điều kiện giải ngân 2. Tính hoa hồng theo hạng đã khóa và phần trích quỹ 3. Ghi bút toán giải ngân 4. Đơn chuyển Hoàn tất, tạo biên lai 5. Thông báo người giao | K40: • A1 Có khiếu nại: dừng, đóng băng • A2 Người giao bị khóa: giữ tiền chờ Admin | L40: BR-F-073, BR-F-074, BR-N-021, BR-N-039, BR-R-040, BR-R-054, BR-R-055, BR-R-063, BR-R-064, BR-R-067, BR-C-010, BR-G-006, BR-G-012 | N40: =COUNTIF('10_API'!$G:$G,A40) -> 2 | O40: =VLOOKUP(A40, '15_Chia task(UC)'!$D$7:$G$69, 3, FALSE) -> Lê Nhựt Huy | P40: =VLOOKUP(A40, '15_Chia task(UC)'!$D$7:$G$69, 4, FALSE) -> Sprint 2 | Q40: =IF(O40="Trần Công Thuận", 6, 8) -> 8 | R40: Dự thảo | S40: =VLOOKUP(A40, '15_Chia task(UC)'!$D$7:$I$69, 5, FALSE) -> 46308 | T40: =VLOOKUP(A40, '15_Chia task(UC)'!$D$7:$I$69, 6, FALSE) -> 46314
A41: UC-37 | B41: Hoàn tiền | C41: PAY | D41: Hệ thống | E41: Người gửi, VNPay | F41: Must | G41: Pha 1 | H41: Đơn bị hủy/hết hạn/giao thất bại do người giao. | I41: Tiền được hoàn vào ví hoặc về nguồn VNPay. | J41: 1. Hệ thống xác định số tiền hoàn theo quy tắc 2. Ghi bút toán hoàn vào ví người gửi 3. Nếu người dùng yêu cầu hoàn về nguồn: gọi API hoàn tiền VNPay 4. Theo dõi kết quả, cập nhật trạng thái 5. Thông báo người gửi | K41: • A1 VNPay từ chối hoàn: giữ tiền ở ví, báo Admin • A2 Giao dịch gốc không phải VNPay: chỉ hoàn ví | L41: BR-F-075, BR-F-076, BR-N-021, BR-R-022, BR-R-043, BR-R-044, BR-R-056, BR-C-007 | N41: =COUNTIF('10_API'!$G:$G,A41) -> 1 | O41: =VLOOKUP(A41, '15_Chia task(UC)'!$D$7:$G$69, 3, FALSE) -> Lê Nhựt Huy | P41: =VLOOKUP(A41, '15_Chia task(UC)'!$D$7:$G$69, 4, FALSE) -> Sprint 5 | Q41: =IF(O41="Trần Công Thuận", 6, 8) -> 8 | R41: Dự thảo | S41: =VLOOKUP(A41, '15_Chia task(UC)'!$D$7:$I$69, 5, FALSE) -> 46329 | T41: =VLOOKUP(A41, '15_Chia task(UC)'!$D$7:$I$69, 6, FALSE) -> 46339
A42: UC-38 | B42: Xem ví và lịch sử giao dịch | C42: PAY | D42: Người dùng | F42: Must | G42: Pha 1 | H42: Đã đăng nhập. | I42: Hiển thị số dư và giao dịch. | J42: 1. Người dùng mở Ví 2. Hệ thống hiển thị số dư khả dụng, đang ký quỹ, chờ rút 3. Người dùng lọc lịch sử, xem chi tiết 4. Xuất sao kê (tùy chọn) | K42: • A1 Số liệu lệch sổ cái: cảnh báo Admin | L42: BR-F-068, BR-F-069, BR-N-020, BR-R-049, BR-C-009 | M42: SCR-41, SCR-44 | N42: =COUNTIF('10_API'!$G:$G,A42) -> 3 | O42: =VLOOKUP(A42, '15_Chia task(UC)'!$D$7:$G$69, 3, FALSE) -> Lê Nhựt Huy | P42: =VLOOKUP(A42, '15_Chia task(UC)'!$D$7:$G$69, 4, FALSE) -> Sprint 3 | Q42: =IF(O42="Trần Công Thuận", 6, 8) -> 8 | R42: Dự thảo | S42: =VLOOKUP(A42, '15_Chia task(UC)'!$D$7:$I$69, 5, FALSE) -> 46315 | T42: =VLOOKUP(A42, '15_Chia task(UC)'!$D$7:$I$69, 6, FALSE) -> 46321
A43: UC-39 | B43: Quản lý tài khoản ngân hàng nhận tiền | C43: PAY | D43: Người giao | F43: Must | G43: Pha 1 | H43: KYC đã duyệt. | I43: Tài khoản ngân hàng được liên kết. | J43: 1. Người giao nhập ngân hàng, số tài khoản, tên chủ tài khoản 2. Hệ thống đối chiếu tên với KYC 3. Hệ thống mã hóa lưu, đặt thời gian chờ 4. Hiển thị số đã che | K43: • A1 Tên không khớp KYC: từ chối | L43: BR-F-077, BR-N-018, BR-R-013, BR-R-058 | M43: SCR-45 | N43: =COUNTIF('10_API'!$G:$G,A43) -> 3 | O43: =VLOOKUP(A43, '15_Chia task(UC)'!$D$7:$G$69, 3, FALSE) -> Lê Nhựt Huy | P43: =VLOOKUP(A43, '15_Chia task(UC)'!$D$7:$G$69, 4, FALSE) -> Sprint 4 | Q43: =IF(O43="Trần Công Thuận", 6, 8) -> 8 | R43: Dự thảo | S43: =VLOOKUP(A43, '15_Chia task(UC)'!$D$7:$I$69, 5, FALSE) -> 46322 | T43: =VLOOKUP(A43, '15_Chia task(UC)'!$D$7:$I$69, 6, FALSE) -> 46328
A44: UC-40 | B44: Yêu cầu rút tiền | C44: PAY | D44: Người giao | F44: Must | G44: Pha 1 | H44: KYC đã duyệt, có tài khoản ngân hàng hết thời gian chờ, số dư khả dụng ≥ ngưỡng. | I44: Yêu cầu rút tạo, tiền chuyển sang chờ rút. | J44: 1. Người giao mở Rút tiền, nhập số tiền 2. Hệ thống kiểm tra hạn mức, số lần rút, phí 3. Hiển thị số tiền thực nhận, người giao xác nhận (OTP) 4. Hệ thống chuyển tiền sang chờ rút, tạo yêu cầu 5. Thông báo đã tiếp nhận | K44: • A1 Số dư dưới ngưỡng: không cho tạo • A2 Đang có yêu cầu chờ xử lý: từ chối • A3 Người giao hủy yêu cầu khi chưa duyệt: hoàn ví | L44: BR-F-078, BR-N-021, BR-R-013, BR-R-057, BR-R-058, BR-R-059, BR-R-061, BR-C-008, BR-G-011 | M44: SCR-46 | N44: =COUNTIF('10_API'!$G:$G,A44) -> 3 | O44: =VLOOKUP(A44, '15_Chia task(UC)'!$D$7:$G$69, 3, FALSE) -> Lê Nhựt Huy | P44: =VLOOKUP(A44, '15_Chia task(UC)'!$D$7:$G$69, 4, FALSE) -> Sprint 3 | Q44: =IF(O44="Trần Công Thuận", 6, 8) -> 8 | R44: Dự thảo | S44: =VLOOKUP(A44, '15_Chia task(UC)'!$D$7:$I$69, 5, FALSE) -> 46315 | T44: =VLOOKUP(A44, '15_Chia task(UC)'!$D$7:$I$69, 6, FALSE) -> 46321
A45: UC-41 | B45: Duyệt và chi trả rút tiền | C45: PAY | D45: Admin | E45: Dịch vụ chi trả | F45: Must | G45: Pha 1 | H45: Có yêu cầu rút chờ xử lý. | I45: Yêu cầu Đã chi hoặc Từ chối. | J45: 1. Admin mở hàng đợi rút tiền 2. Xem thông tin đối chiếu 3. Duyệt hoặc từ chối (hai cấp khi vượt ngưỡng) 4. Hệ thống gọi PayoutProvider hoặc xuất lệnh chi 5. Admin nhập mã tham chiếu hoặc nhận kết quả 6. Hệ thống cập nhật Đã chi, thông báo người dùng | K45: • A1 Từ chối: hoàn tiền về ví khả dụng • A2 Chi thất bại: hoàn ví, ghi nguyên nhân • A3 Cùng Admin duyệt hai cấp: chặn | L45: BR-F-079, BR-F-080, BR-F-081, BR-R-060, BR-R-061, BR-C-008, BR-G-011 | M45: SCR-54 | N45: =COUNTIF('10_API'!$G:$G,A45) -> 6 | O45: =VLOOKUP(A45, '15_Chia task(UC)'!$D$7:$G$69, 3, FALSE) -> Trần Công Thuận | P45: =VLOOKUP(A45, '15_Chia task(UC)'!$D$7:$G$69, 4, FALSE) -> Sprint 2 | Q45: =IF(O45="Trần Công Thuận", 6, 8) -> 6 | R45: Dự thảo | S45: =VLOOKUP(A45, '15_Chia task(UC)'!$D$7:$I$69, 5, FALSE) -> 46308 | T45: =VLOOKUP(A45, '15_Chia task(UC)'!$D$7:$I$69, 6, FALSE) -> 46314
A46: UC-42 | B46: Xử lý IPN và kết quả từ VNPay | C46: PAY | D46: Hệ thống | E46: VNPay | F46: Must | G46: Pha 1 | H46: Giao dịch VNPay đã tạo. | I46: Giao dịch chốt trạng thái cuối; ví/ký quỹ cập nhật. | J46: 1. VNPay gọi endpoint IPN 2. Hệ thống xác minh chữ ký 3. Đối chiếu mã tham chiếu và số tiền 4. Cập nhật giao dịch và ghi sổ cái idempotent 5. Phản hồi theo định dạng VNPay | K46: • A1 Sai chữ ký: từ chối, ghi cảnh báo • A2 IPN trùng: phản hồi đã xử lý, không ghi lại • A3 Số tiền lệch: không ghi nhận, báo Admin • A4 Giao dịch treo: job truy vấn kết quả | L46: BR-F-066, BR-F-067, BR-N-004, BR-N-021, BR-N-022, BR-R-051, BR-C-006 | N46: =COUNTIF('10_API'!$G:$G,A46) -> 1 | O46: =VLOOKUP(A46, '15_Chia task(UC)'!$D$7:$G$69, 3, FALSE) -> Lê Nhựt Huy | P46: =VLOOKUP(A46, '15_Chia task(UC)'!$D$7:$G$69, 4, FALSE) -> Sprint 2 | Q46: =IF(O46="Trần Công Thuận", 6, 8) -> 8 | R46: Dự thảo | S46: =VLOOKUP(A46, '15_Chia task(UC)'!$D$7:$I$69, 5, FALSE) -> 46308 | T46: =VLOOKUP(A46, '15_Chia task(UC)'!$D$7:$I$69, 6, FALSE) -> 46314
A47: UC-43 | B47: Đối soát giao dịch hằng ngày | C47: PAY | D47: Hệ thống | E47: Admin | F47: Should | G47: Pha 2 | H47: Có giao dịch trong ngày. | I47: Báo cáo đối soát được tạo. | J47: 1. Hệ thống lấy giao dịch nội bộ ngày hôm trước 2. Truy vấn trạng thái các giao dịch VNPay cần xác minh 3. So khớp với sổ cái 4. Tạo báo cáo khớp/lệch 5. Admin xử lý chênh lệch bằng bút toán điều chỉnh | K47: • A1 Có chênh lệch: cảnh báo Admin, không tự điều chỉnh | L47: BR-F-082, BR-F-083, BR-F-084, BR-N-015, BR-N-039, BR-R-062, BR-G-012 | M47: SCR-55 | N47: =COUNTIF('10_API'!$G:$G,A47) -> 4 | O47: =VLOOKUP(A47, '15_Chia task(UC)'!$D$7:$G$69, 3, FALSE) -> Lê Nhựt Huy | P47: =VLOOKUP(A47, '15_Chia task(UC)'!$D$7:$G$69, 4, FALSE) -> Sprint 4 | Q47: =IF(O47="Trần Công Thuận", 6, 8) -> 8 | R47: Dự thảo | S47: =VLOOKUP(A47, '15_Chia task(UC)'!$D$7:$I$69, 5, FALSE) -> 46322 | T47: =VLOOKUP(A47, '15_Chia task(UC)'!$D$7:$I$69, 6, FALSE) -> 46328
A48: UC-44 | B48: Áp dụng mã khuyến mãi | C48: FEE | D48: Người gửi | F48: Could | G48: Pha 3 | H48: Đơn Chờ ký quỹ. | I48: Số tiền giảm được áp dụng. | J48: 1. Người gửi nhập mã 2. Hệ thống kiểm tra điều kiện mã 3. Hiển thị số tiền giảm và tổng mới | K48: • A1 Mã hết hạn/hết lượt/không đủ điều kiện: báo lý do | L48: BR-F-087, BR-R-069 | M48: SCR-22 | N48: =COUNTIF('10_API'!$G:$G,A48) -> 1 | O48: =VLOOKUP(A48, '15_Chia task(UC)'!$D$7:$G$69, 3, FALSE) -> Nguyễn Thành Huy | P48: =VLOOKUP(A48, '15_Chia task(UC)'!$D$7:$G$69, 4, FALSE) -> Sprint 3 | Q48: =IF(O48="Trần Công Thuận", 6, 8) -> 8 | R48: Dự thảo | S48: =VLOOKUP(A48, '15_Chia task(UC)'!$D$7:$I$69, 5, FALSE) -> 46315 | T48: =VLOOKUP(A48, '15_Chia task(UC)'!$D$7:$I$69, 6, FALSE) -> 46321
A49: UC-45 | B49: Quản lý khuyến mãi | C49: FEE | D49: Admin | F49: Could | G49: Pha 3 | H49: Admin đã đăng nhập. | I49: Mã khuyến mãi được tạo/sửa/tạm dừng. | J49: 1. Admin tạo mã: giá trị, hạn dùng, số lượt, đối tượng 2. Hệ thống lưu và kích hoạt 3. Theo dõi số lượt dùng | K49: • A1 Trùng mã: từ chối | L49: BR-F-088, BR-R-069 | M49: SCR-59 | N49: =COUNTIF('10_API'!$G:$G,A49) -> 3 | O49: =VLOOKUP(A49, '15_Chia task(UC)'!$D$7:$G$69, 3, FALSE) -> Trần Công Thuận | P49: =VLOOKUP(A49, '15_Chia task(UC)'!$D$7:$G$69, 4, FALSE) -> Sprint 3 | Q49: =IF(O49="Trần Công Thuận", 6, 8) -> 6 | R49: Dự thảo | S49: =VLOOKUP(A49, '15_Chia task(UC)'!$D$7:$I$69, 5, FALSE) -> 46315 | T49: =VLOOKUP(A49, '15_Chia task(UC)'!$D$7:$I$69, 6, FALSE) -> 46321
A50: UC-46 | B50: Cấu hình tham số hệ thống và biểu phí | C50: ADM | D50: Admin | F50: Must | G50: Pha 1 | H50: Admin có quyền. | I50: Tham số được cập nhật, có lịch sử. | J50: 1. Admin mở trang tham số 2. Chỉnh giá trị, xem mô phỏng ảnh hưởng 3. Xác nhận 4. Hệ thống lưu phiên bản mới, ghi audit 5. Có hiệu lực cho đơn tạo sau | K50: • A1 Giá trị ngoài biên cho phép: từ chối | L50: BR-F-085, BR-F-089, BR-R-055, BR-R-067, BR-R-083, BR-G-006 | M50: SCR-57 | N50: =COUNTIF('10_API'!$G:$G,A50) -> 3 | O50: =VLOOKUP(A50, '15_Chia task(UC)'!$D$7:$G$69, 3, FALSE) -> Trần Công Thuận | P50: =VLOOKUP(A50, '15_Chia task(UC)'!$D$7:$G$69, 4, FALSE) -> Sprint 1 | Q50: =IF(O50="Trần Công Thuận", 6, 8) -> 6 | R50: Dự thảo | S50: =VLOOKUP(A50, '15_Chia task(UC)'!$D$7:$I$69, 5, FALSE) -> 46305 | T50: =VLOOKUP(A50, '15_Chia task(UC)'!$D$7:$I$69, 6, FALSE) -> 46307
A51: UC-47 | B51: Đánh giá hai chiều | C51: REP | D51: Người dùng | F51: Must | G51: Pha 1 | H51: Đơn Hoàn tất, trong thời hạn đánh giá. | I51: Đánh giá được ghi nhận. | J51: 1. Người dùng mở đánh giá của đơn 2. Chọn số sao, thẻ nhận xét, viết nội dung 3. Hệ thống lưu và ẩn đến khi bên kia gửi/hết hạn 4. Cập nhật số liệu điểm | K51: • A1 Quá hạn: không cho đánh giá | L51: BR-F-090, BR-N-002, BR-R-008, BR-R-070, BR-R-071, BR-G-010 | M51: SCR-25 | N51: =COUNTIF('10_API'!$G:$G,A51) -> 1 | O51: =VLOOKUP(A51, '15_Chia task(UC)'!$D$7:$G$69, 3, FALSE) -> Huỳnh Phi Long | P51: =VLOOKUP(A51, '15_Chia task(UC)'!$D$7:$G$69, 4, FALSE) -> Sprint 4 | Q51: =IF(O51="Trần Công Thuận", 6, 8) -> 8 | R51: Dự thảo | S51: =VLOOKUP(A51, '15_Chia task(UC)'!$D$7:$I$69, 5, FALSE) -> 46322 | T51: =VLOOKUP(A51, '15_Chia task(UC)'!$D$7:$I$69, 6, FALSE) -> 46328
A52: UC-48 | B52: Xem hồ sơ công khai và điểm uy tín | C52: REP | D52: Người dùng | F52: Must | G52: Pha 1 | I52: Hiển thị hồ sơ công khai. | J52: 1. Người dùng chọn xem người giao 2. Hệ thống hiển thị hạng, điểm, số đơn, tỷ lệ đúng hạn, huy hiệu, đánh giá 3. Người được đánh giá phản hồi (Could) | K52: • A1 Hồ sơ bị khóa: hiển thị trạng thái hạn chế | L52: BR-F-031, BR-F-091, BR-F-093, BR-R-071 | M52: SCR-15 | N52: =COUNTIF('10_API'!$G:$G,A52) -> 3 | O52: =VLOOKUP(A52, '15_Chia task(UC)'!$D$7:$G$69, 3, FALSE) -> Huỳnh Phi Long | P52: =VLOOKUP(A52, '15_Chia task(UC)'!$D$7:$G$69, 4, FALSE) -> Sprint 5 | Q52: =IF(O52="Trần Công Thuận", 6, 8) -> 8 | R52: Dự thảo | S52: =VLOOKUP(A52, '15_Chia task(UC)'!$D$7:$I$69, 5, FALSE) -> 46329 | T52: =VLOOKUP(A52, '15_Chia task(UC)'!$D$7:$I$69, 6, FALSE) -> 46339
A53: UC-49 | B53: Tính điểm uy tín và xếp hạng | C53: REP | D53: Hệ thống | F53: Must | G53: Pha 1 | H53: Có dữ liệu đơn và đánh giá. | I53: Điểm và hạng được cập nhật. | J53: 1. Hệ thống tổng hợp chỉ số theo từng người giao 2. Tính điểm theo trọng số 3. Xác định hạng và quyền lợi 4. Lưu lịch sử điểm, thông báo khi đổi hạng | K53: • A1 Điểm dưới ngưỡng: hạn chế/đưa vào xem xét | L53: BR-F-092, BR-F-094, BR-F-119, BR-R-028, BR-R-072, BR-R-073, BR-R-074, BR-R-075, BR-G-007 | N53: =COUNTIF('10_API'!$G:$G,A53) -> 1 | O53: =VLOOKUP(A53, '15_Chia task(UC)'!$D$7:$G$69, 3, FALSE) -> Trần Công Thuận | P53: =VLOOKUP(A53, '15_Chia task(UC)'!$D$7:$G$69, 4, FALSE) -> Sprint 2 | Q53: =IF(O53="Trần Công Thuận", 6, 8) -> 6 | R53: Dự thảo | S53: =VLOOKUP(A53, '15_Chia task(UC)'!$D$7:$I$69, 5, FALSE) -> 46308 | T53: =VLOOKUP(A53, '15_Chia task(UC)'!$D$7:$I$69, 6, FALSE) -> 46314
A54: UC-50 | B54: Tạo khiếu nại | C54: DSP | D54: Người dùng | F54: Must | G54: Pha 1 | H54: Đơn Đã giao trong thời hạn khiếu nại. | I54: Hồ sơ khiếu nại được tạo; ký quỹ đóng băng. | J54: 1. Người dùng chọn Khiếu nại trên đơn 2. Chọn lý do, mô tả, đính kèm bằng chứng 3. Hệ thống kiểm tra thời hạn và điều kiện 4. Hệ thống tạo hồ sơ, đóng băng khoản ký quỹ 5. Thông báo bên liên quan và Kiểm duyệt | K54: • A1 Quá hạn: từ chối • A2 Đã có khiếu nại mở: từ chối | L54: BR-F-095, BR-R-054, BR-R-076, BR-R-077, BR-G-005 | M54: SCR-26 | N54: =COUNTIF('10_API'!$G:$G,A54) -> 1 | O54: =VLOOKUP(A54, '15_Chia task(UC)'!$D$7:$G$69, 3, FALSE) -> Huỳnh Phi Long | P54: =VLOOKUP(A54, '15_Chia task(UC)'!$D$7:$G$69, 4, FALSE) -> Sprint 5 | Q54: =IF(O54="Trần Công Thuận", 6, 8) -> 8 | R54: Dự thảo | S54: =VLOOKUP(A54, '15_Chia task(UC)'!$D$7:$I$69, 5, FALSE) -> 46329 | T54: =VLOOKUP(A54, '15_Chia task(UC)'!$D$7:$I$69, 6, FALSE) -> 46339
A55: UC-51 | B55: Xử lý khiếu nại và phán quyết | C55: DSP | D55: Kiểm duyệt | E55: Người gửi, Người giao | F55: Must | G55: Pha 1 | H55: Có khiếu nại đang mở. | I55: Khiếu nại có phán quyết, tiền được xử lý. | J55: 1. Kiểm duyệt nhận hồ sơ, xem chat và bằng chứng 2. Trao đổi với các bên 3. Đưa ra phán quyết và lý do 4. Hệ thống thực hiện bút toán tương ứng 5. Thông báo các bên, mở kháng nghị | K55: • A1 Kháng nghị: chuyển Admin xem xét lại • A2 Thiếu bằng chứng: yêu cầu bổ sung | L55: BR-F-045, BR-F-096, BR-F-097, BR-F-099, BR-F-100, BR-R-077, BR-R-078, BR-G-005 | M55: SCR-52, SCR-53 | N55: =COUNTIF('10_API'!$G:$G,A55) -> 5 | O55: =VLOOKUP(A55, '15_Chia task(UC)'!$D$7:$G$69, 3, FALSE) -> Trần Công Thuận | P55: =VLOOKUP(A55, '15_Chia task(UC)'!$D$7:$G$69, 4, FALSE) -> Sprint 3 | Q55: =IF(O55="Trần Công Thuận", 6, 8) -> 6 | R55: Dự thảo | S55: =VLOOKUP(A55, '15_Chia task(UC)'!$D$7:$I$69, 5, FALSE) -> 46315 | T55: =VLOOKUP(A55, '15_Chia task(UC)'!$D$7:$I$69, 6, FALSE) -> 46321
A56: UC-52 | B56: Xét duyệt bồi thường từ Quỹ bảo đảm | C56: DSP | D56: Admin | F56: Must | G56: Pha 1 | H56: Phán quyết bồi thường cho đơn có bảo hiểm. | I56: Khoản bồi thường được chi. | J56: 1. Admin xem phán quyết và số dư quỹ 2. Xác nhận mức bồi thường 3. Hệ thống ghi bút toán chi quỹ vào ví người nhận bồi thường 4. Thông báo | K56: • A1 Quỹ không đủ: xếp hàng chờ | L56: BR-F-098, BR-R-064, BR-R-077, BR-R-079 | M56: SCR-56 | N56: =COUNTIF('10_API'!$G:$G,A56) -> 2 | O56: =VLOOKUP(A56, '15_Chia task(UC)'!$D$7:$G$69, 3, FALSE) -> Trần Công Thuận | P56: =VLOOKUP(A56, '15_Chia task(UC)'!$D$7:$G$69, 4, FALSE) -> Sprint 4 | Q56: =IF(O56="Trần Công Thuận", 6, 8) -> 6 | R56: Dự thảo | S56: =VLOOKUP(A56, '15_Chia task(UC)'!$D$7:$I$69, 5, FALSE) -> 46322 | T56: =VLOOKUP(A56, '15_Chia task(UC)'!$D$7:$I$69, 6, FALSE) -> 46328
A57: UC-53 | B57: Nhận và cấu hình thông báo | C57: NTF | D57: Người dùng | E57: Dịch vụ Email/SMS | F57: Must | G57: Pha 1 | I57: Thông báo được gửi/hiển thị theo cài đặt. | J57: 1. Sự kiện nghiệp vụ xảy ra 2. Hệ thống chọn mẫu và kênh theo cài đặt 3. Gửi thông báo trong ứng dụng, email, SMS 4. Người dùng xem, đánh dấu đã đọc 5. Người dùng thay đổi cài đặt kênh | K57: • A1 Gửi lỗi: thử lại theo cấu hình • A2 Loại bắt buộc: không cho tắt | L57: BR-F-035, BR-F-101, BR-F-102, BR-F-103, BR-F-104, BR-F-105, BR-N-009, BR-N-014, BR-R-085 | M57: SCR-39, SCR-40 | N57: =COUNTIF('10_API'!$G:$G,A57) -> 6 | O57: =VLOOKUP(A57, '15_Chia task(UC)'!$D$7:$G$69, 3, FALSE) -> Trần Công Thuận | P57: =VLOOKUP(A57, '15_Chia task(UC)'!$D$7:$G$69, 4, FALSE) -> Sprint 1 | Q57: =IF(O57="Trần Công Thuận", 6, 8) -> 6 | R57: Dự thảo | S57: =VLOOKUP(A57, '15_Chia task(UC)'!$D$7:$I$69, 5, FALSE) -> 46305 | T57: =VLOOKUP(A57, '15_Chia task(UC)'!$D$7:$I$69, 6, FALSE) -> 46307
A58: UC-54 | B58: Kiểm duyệt đơn hàng | C58: SAF | D58: Hệ thống | E58: Kiểm duyệt | F58: Must | G58: Pha 1 | H58: Có đơn vừa đăng hoặc bị đánh dấu. | I58: Đơn Đang mở hoặc Bị từ chối. | J58: 1. Hệ thống kiểm tra từ khóa và danh mục 2. Đơn sạch chuyển Đang mở 3. Đơn nghi ngờ vào hàng đợi Kiểm duyệt 4. Kiểm duyệt duyệt hoặc từ chối kèm lý do 5. Thông báo người gửi | K58: • A1 Từ chối lặp lại: cảnh báo người gửi | L58: BR-F-106, BR-F-107, BR-R-080, BR-C-012 | M58: SCR-51 | N58: =COUNTIF('10_API'!$G:$G,A58) -> 3 | O58: =VLOOKUP(A58, '15_Chia task(UC)'!$D$7:$G$69, 3, FALSE) -> Trần Công Thuận | P58: =VLOOKUP(A58, '15_Chia task(UC)'!$D$7:$G$69, 4, FALSE) -> Sprint 2 | Q58: =IF(O58="Trần Công Thuận", 6, 8) -> 6 | R58: Dự thảo | S58: =VLOOKUP(A58, '15_Chia task(UC)'!$D$7:$I$69, 5, FALSE) -> 46308 | T58: =VLOOKUP(A58, '15_Chia task(UC)'!$D$7:$I$69, 6, FALSE) -> 46314
A59: UC-55 | B59: Báo cáo vi phạm | C59: SAF | D59: Người dùng | E59: Kiểm duyệt | F59: Must | G59: Pha 1 | H59: Đã đăng nhập. | I59: Báo cáo được ghi nhận. | J59: 1. Người dùng chọn Báo cáo trên đơn/người dùng/tin nhắn 2. Chọn lý do, bằng chứng 3. Hệ thống tạo hồ sơ 4. Kiểm duyệt xử lý, có thể cảnh cáo hoặc khóa | K59: • A1 Báo cáo trùng: gộp | L59: BR-F-044, BR-F-056, BR-F-108, BR-F-110, BR-R-034 | M59: SCR-64 | N59: =COUNTIF('10_API'!$G:$G,A59) -> 2 | O59: =VLOOKUP(A59, '15_Chia task(UC)'!$D$7:$G$69, 3, FALSE) -> Trần Công Thuận | P59: =VLOOKUP(A59, '15_Chia task(UC)'!$D$7:$G$69, 4, FALSE) -> Sprint 4 | Q59: =IF(O59="Trần Công Thuận", 6, 8) -> 6 | R59: Dự thảo | S59: =VLOOKUP(A59, '15_Chia task(UC)'!$D$7:$I$69, 5, FALSE) -> 46322 | T59: =VLOOKUP(A59, '15_Chia task(UC)'!$D$7:$I$69, 6, FALSE) -> 46328
A60: UC-56 | B60: Khóa và mở khóa tài khoản | C60: SAF | D60: Admin | F60: Must | G60: Pha 1 | H60: Admin có quyền. | I60: Trạng thái tài khoản thay đổi, phiên bị thu hồi. | J60: 1. Admin chọn tài khoản và hành động 2. Nhập lý do 3. Hệ thống cập nhật, thu hồi phiên 4. Xử lý đơn đang chạy của tài khoản 5. Thông báo người dùng | K60: • A1 Tài khoản đang có tiền ký quỹ: xử lý theo quy tắc trước khi khóa | L60: BR-F-109, BR-R-074, BR-R-081, BR-R-082 | M60: SCR-49 | N60: =COUNTIF('10_API'!$G:$G,A60) -> 3 | O60: =VLOOKUP(A60, '15_Chia task(UC)'!$D$7:$G$69, 3, FALSE) -> Trần Công Thuận | P60: =VLOOKUP(A60, '15_Chia task(UC)'!$D$7:$G$69, 4, FALSE) -> Sprint 4 | Q60: =IF(O60="Trần Công Thuận", 6, 8) -> 6 | R60: Dự thảo | S60: =VLOOKUP(A60, '15_Chia task(UC)'!$D$7:$I$69, 5, FALSE) -> 46322 | T60: =VLOOKUP(A60, '15_Chia task(UC)'!$D$7:$I$69, 6, FALSE) -> 46328
A61: UC-57 | B61: Quản lý người dùng và nhân sự | C61: ADM | D61: Admin | F61: Must | G61: Pha 1 | H61: Admin có quyền. | I61: Dữ liệu người dùng/nhân sự được quản lý. | J61: 1. Admin tìm kiếm người dùng 2. Xem hồ sơ, lịch sử đơn, giao dịch 3. Gán vai trò hoặc tạo tài khoản nhân sự 4. Xử lý yêu cầu xuất/xóa dữ liệu | K61: • A1 Thao tác vượt quyền: bị chặn | L61: BR-F-111, BR-F-112, BR-F-124, BR-N-040 | M61: SCR-48, SCR-49, SCR-63 | N61: =COUNTIF('10_API'!$G:$G,A61) -> 4 | O61: =VLOOKUP(A61, '15_Chia task(UC)'!$D$7:$G$69, 3, FALSE) -> Trần Công Thuận | P61: =VLOOKUP(A61, '15_Chia task(UC)'!$D$7:$G$69, 4, FALSE) -> Sprint 3 | Q61: =IF(O61="Trần Công Thuận", 6, 8) -> 6 | R61: Dự thảo | S61: =VLOOKUP(A61, '15_Chia task(UC)'!$D$7:$I$69, 5, FALSE) -> 46315 | T61: =VLOOKUP(A61, '15_Chia task(UC)'!$D$7:$I$69, 6, FALSE) -> 46321
A62: UC-58 | B62: Quản lý danh mục | C62: ADM | D62: Admin | F62: Must | G62: Pha 1 | H62: Admin có quyền. | I62: Danh mục được cập nhật. | J62: 1. Admin chọn danh mục: loại hàng, từ khóa hàng cấm, khu vực, điểm hẹn, điều khoản 2. Thêm/sửa/ẩn mục 3. Hệ thống lưu và áp dụng | K62: • A1 Xóa mục đang được dùng: chỉ cho ẩn | L62: BR-F-061, BR-F-113, BR-C-012 | M62: SCR-58 | N62: =COUNTIF('10_API'!$G:$G,A62) -> 6 | O62: =VLOOKUP(A62, '15_Chia task(UC)'!$D$7:$G$69, 3, FALSE) -> Nguyễn Thành Huy | P62: =VLOOKUP(A62, '15_Chia task(UC)'!$D$7:$G$69, 4, FALSE) -> Sprint 3 | Q62: =IF(O62="Trần Công Thuận", 6, 8) -> 8 | R62: Dự thảo | S62: =VLOOKUP(A62, '15_Chia task(UC)'!$D$7:$I$69, 5, FALSE) -> 46315 | T62: =VLOOKUP(A62, '15_Chia task(UC)'!$D$7:$I$69, 6, FALSE) -> 46321
A63: UC-59 | B63: Dashboard và báo cáo | C63: ADM | D63: Admin | F63: Must | G63: Pha 1 | H63: Admin có quyền. | I63: Hiển thị số liệu và tệp báo cáo. | J63: 1. Admin mở dashboard, chọn khoảng thời gian 2. Hệ thống tổng hợp chỉ số 3. Hiển thị biểu đồ và bảng 4. Xuất báo cáo Excel/CSV | K63: • A1 Không có dữ liệu: hiển thị trạng thái rỗng | L63: BR-F-084, BR-F-100, BR-F-114, BR-F-115, BR-C-010 | M63: SCR-47, SCR-62 | N63: =COUNTIF('10_API'!$G:$G,A63) -> 3 | O63: =VLOOKUP(A63, '15_Chia task(UC)'!$D$7:$G$69, 3, FALSE) -> Trần Công Thuận | P63: =VLOOKUP(A63, '15_Chia task(UC)'!$D$7:$G$69, 4, FALSE) -> Sprint 5 | Q63: =IF(O63="Trần Công Thuận", 6, 8) -> 6 | R63: Dự thảo | S63: =VLOOKUP(A63, '15_Chia task(UC)'!$D$7:$I$69, 5, FALSE) -> 46329 | T63: =VLOOKUP(A63, '15_Chia task(UC)'!$D$7:$I$69, 6, FALSE) -> 46336
A64: UC-60 | B64: Xem nhật ký kiểm toán | C64: ADM | D64: Admin | F64: Should | G64: Pha 2 | H64: Admin có quyền. | I64: Hiển thị bản ghi audit. | J64: 1. Admin mở nhật ký kiểm toán 2. Lọc theo người thực hiện, đối tượng, thời gian 3. Xem chi tiết giá trị trước/sau | K64: • A1 Không có chức năng sửa/xóa bản ghi | L64: BR-F-083, BR-F-116, BR-N-026, BR-N-038, BR-R-045, BR-R-084 | M64: SCR-60 | N64: =COUNTIF('10_API'!$G:$G,A64) -> 1 | O64: =VLOOKUP(A64, '15_Chia task(UC)'!$D$7:$G$69, 3, FALSE) -> Trần Công Thuận | P64: =VLOOKUP(A64, '15_Chia task(UC)'!$D$7:$G$69, 4, FALSE) -> Sprint 5 | Q64: =IF(O64="Trần Công Thuận", 6, 8) -> 6 | R64: Dự thảo | S64: =VLOOKUP(A64, '15_Chia task(UC)'!$D$7:$I$69, 5, FALSE) -> 46329 | T64: =VLOOKUP(A64, '15_Chia task(UC)'!$D$7:$I$69, 6, FALSE) -> 46336
A65: UC-61 | B65: Xem thu nhập và thống kê | C65: GAM | D65: Người giao | F65: Should | G65: Pha 2 | H65: Người giao có dữ liệu. | I65: Hiển thị thu nhập, hiệu suất. | J65: 1. Người giao mở Thu nhập 2. Chọn ngày/tuần/tháng 3. Hệ thống tổng hợp doanh thu, hoa hồng, thu nhập ròng 4. Hiển thị biểu đồ và tiến độ lên hạng | K65: • A1 Chưa có đơn: trạng thái rỗng kèm gợi ý | L65: BR-F-074, BR-F-118, BR-F-119, BR-G-014 | M65: SCR-27, SCR-35 | N65: =COUNTIF('10_API'!$G:$G,A65) -> 2 | O65: =VLOOKUP(A65, '15_Chia task(UC)'!$D$7:$G$69, 3, FALSE) -> Lê Nhựt Huy | P65: =VLOOKUP(A65, '15_Chia task(UC)'!$D$7:$G$69, 4, FALSE) -> Sprint 5 | Q65: =IF(O65="Trần Công Thuận", 6, 8) -> 8 | R65: Dự thảo | S65: =VLOOKUP(A65, '15_Chia task(UC)'!$D$7:$I$69, 5, FALSE) -> 46329 | T65: =VLOOKUP(A65, '15_Chia task(UC)'!$D$7:$I$69, 6, FALSE) -> 46339
A66: UC-62 | B66: Huy hiệu, thưởng và giới thiệu bạn bè | C66: GAM | D66: Người dùng | F66: Could | G66: Pha 3 | H66: Có cấu hình thưởng. | I66: Huy hiệu/thưởng được trao. | J66: 1. Hệ thống theo dõi thành tích 2. Đạt điều kiện thì trao huy hiệu/thưởng 3. Người dùng xem huy hiệu, mã giới thiệu 4. Thưởng giới thiệu ghi vào ví sau đơn đầu tiên của người được mời | K66: • A1 Mã giới thiệu đã dùng: từ chối | L66: BR-F-120, BR-F-121, BR-G-014 | M66: SCR-37 | N66: =COUNTIF('10_API'!$G:$G,A66) -> 2 | O66: =VLOOKUP(A66, '15_Chia task(UC)'!$D$7:$G$69, 3, FALSE) -> Lư Hữu Luân | P66: =VLOOKUP(A66, '15_Chia task(UC)'!$D$7:$G$69, 4, FALSE) -> Sprint 5 | Q66: =IF(O66="Trần Công Thuận", 6, 8) -> 8 | R66: Dự thảo | S66: =VLOOKUP(A66, '15_Chia task(UC)'!$D$7:$I$69, 5, FALSE) -> 46329 | T66: =VLOOKUP(A66, '15_Chia task(UC)'!$D$7:$I$69, 6, FALSE) -> 46336
A67: UC-63 | B67: Xử lý tác vụ định kỳ | C67: ADM | D67: Hệ thống | E67: Admin | F67: Must | G67: Pha 1 | H67: Scheduler hoạt động. | I67: Các tác vụ nền được thực thi và ghi nhật ký. | J67: 1. Scheduler kích hoạt job theo lịch 2. Job lấy khóa phân tán 3. Xử lý: hết hạn đơn/chào giá, quá hạn lấy hàng, tự giải ngân, truy vấn giao dịch treo, nhắc nhở, tính lại điểm 4. Ghi kết quả, cảnh báo nếu lỗi | K67: • A1 Job lỗi: thử lại, cảnh báo Admin • A2 Instance khác đang chạy: bỏ qua | L67: BR-F-067, BR-F-073, BR-F-117, BR-N-015, BR-N-041, BR-R-020, BR-R-031, BR-R-043 | M67: SCR-61 | N67: =COUNTIF('10_API'!$G:$G,A67) -> 3 | O67: =VLOOKUP(A67, '15_Chia task(UC)'!$D$7:$G$69, 3, FALSE) -> Trần Công Thuận | P67: =VLOOKUP(A67, '15_Chia task(UC)'!$D$7:$G$69, 4, FALSE) -> Sprint 5 | Q67: =IF(O67="Trần Công Thuận", 6, 8) -> 6 | R67: Dự thảo | S67: =VLOOKUP(A67, '15_Chia task(UC)'!$D$7:$I$69, 5, FALSE) -> 46329 | T67: =VLOOKUP(A67, '15_Chia task(UC)'!$D$7:$I$69, 6, FALSE) -> 46339
A69: Ghi chú: Lộ trình 5 tuần (5 Sprint) trước ngày Deploy (16/11/2026). Toàn bộ 63 Use Case đã được phân bổ ngày bắt đầu và hạn chót tương ứng với từng Sprint.

Sheet 05_Truy_vết
A1: Ma trận truy vết
A2: UC → số BR theo loại (tính tự động từ sheet 03) → danh sách BR, màn hình, API
A4: Mã UC | B4: Tên Use Case | C4: Phân hệ | D4: Ưu tiên | E4: Functional | F4: Non-functional | G4: Business Rule | H4: Constraint | I4: Goal | J4: Tổng BR | K4: Danh sách BR liên quan | L4: Màn hình | M4: Số API
A5: UC-01 | B5: Đăng ký tài khoản | C5: AUTH | D5: Must | E5: =COUNTIFS('03_BR'!$B:$B,"Functional BR",'03_BR'!$G:$G,"*"&$A5&"*") -> 1 | F5: =COUNTIFS('03_BR'!$B:$B,"Non-functional BR",'03_BR'!$G:$G,"*"&$A5&"*") -> 2 | G5: =COUNTIFS('03_BR'!$B:$B,"Business Rule",'03_BR'!$G:$G,"*"&$A5&"*") -> 2 | H5: =COUNTIFS('03_BR'!$B:$B,"Business Constraint",'03_BR'!$G:$G,"*"&$A5&"*") -> 2 | I5: =COUNTIFS('03_BR'!$B:$B,"Business Goal",'03_BR'!$G:$G,"*"&$A5&"*") -> 1 | J5: =SUM(E5:I5) -> 8 | K5: BR-F-001, BR-N-016, BR-N-030, BR-R-001, BR-R-002, BR-C-011, BR-C-022, BR-G-002 | L5: SCR-03 | M5: =COUNTIF('10_API'!$G:$G,A5) -> 1
A6: UC-02 | B6: Xác thực OTP email/SĐT | C6: AUTH | D6: Must | E6: =COUNTIFS('03_BR'!$B:$B,"Functional BR",'03_BR'!$G:$G,"*"&$A6&"*") -> 2 | F6: =COUNTIFS('03_BR'!$B:$B,"Non-functional BR",'03_BR'!$G:$G,"*"&$A6&"*") -> 0 | G6: =COUNTIFS('03_BR'!$B:$B,"Business Rule",'03_BR'!$G:$G,"*"&$A6&"*") -> 2 | H6: =COUNTIFS('03_BR'!$B:$B,"Business Constraint",'03_BR'!$G:$G,"*"&$A6&"*") -> 0 | I6: =COUNTIFS('03_BR'!$B:$B,"Business Goal",'03_BR'!$G:$G,"*"&$A6&"*") -> 0 | J6: =SUM(E6:I6) -> 4 | K6: BR-F-002, BR-F-102, BR-R-003, BR-R-007 | L6: SCR-04 | M6: =COUNTIF('10_API'!$G:$G,A6) -> 2
A7: UC-03 | B7: Đăng nhập | C7: AUTH | D7: Must | E7: =COUNTIFS('03_BR'!$B:$B,"Functional BR",'03_BR'!$G:$G,"*"&$A7&"*") -> 2 | F7: =COUNTIFS('03_BR'!$B:$B,"Non-functional BR",'03_BR'!$G:$G,"*"&$A7&"*") -> 1 | G7: =COUNTIFS('03_BR'!$B:$B,"Business Rule",'03_BR'!$G:$G,"*"&$A7&"*") -> 3 | H7: =COUNTIFS('03_BR'!$B:$B,"Business Constraint",'03_BR'!$G:$G,"*"&$A7&"*") -> 1 | I7: =COUNTIFS('03_BR'!$B:$B,"Business Goal",'03_BR'!$G:$G,"*"&$A7&"*") -> 0 | J7: =SUM(E7:I7) -> 7 | K7: BR-F-003, BR-F-004, BR-N-024, BR-R-004, BR-R-005, BR-R-006, BR-C-005 | L7: SCR-05 | M7: =COUNTIF('10_API'!$G:$G,A7) -> 3
A8: UC-04 | B8: Đăng xuất và quản lý phiên/thiết bị | C8: AUTH | D8: Must | E8: =COUNTIFS('03_BR'!$B:$B,"Functional BR",'03_BR'!$G:$G,"*"&$A8&"*") -> 1 | F8: =COUNTIFS('03_BR'!$B:$B,"Non-functional BR",'03_BR'!$G:$G,"*"&$A8&"*") -> 0 | G8: =COUNTIFS('03_BR'!$B:$B,"Business Rule",'03_BR'!$G:$G,"*"&$A8&"*") -> 2 | H8: =COUNTIFS('03_BR'!$B:$B,"Business Constraint",'03_BR'!$G:$G,"*"&$A8&"*") -> 0 | I8: =COUNTIFS('03_BR'!$B:$B,"Business Goal",'03_BR'!$G:$G,"*"&$A8&"*") -> 0 | J8: =SUM(E8:I8) -> 3 | K8: BR-F-005, BR-R-005, BR-R-006 | L8: SCR-12 | M8: =COUNTIF('10_API'!$G:$G,A8) -> 3
A9: UC-05 | B9: Quên và đặt lại mật khẩu | C9: AUTH | D9: Must | E9: =COUNTIFS('03_BR'!$B:$B,"Functional BR",'03_BR'!$G:$G,"*"&$A9&"*") -> 1 | F9: =COUNTIFS('03_BR'!$B:$B,"Non-functional BR",'03_BR'!$G:$G,"*"&$A9&"*") -> 1 | G9: =COUNTIFS('03_BR'!$B:$B,"Business Rule",'03_BR'!$G:$G,"*"&$A9&"*") -> 2 | H9: =COUNTIFS('03_BR'!$B:$B,"Business Constraint",'03_BR'!$G:$G,"*"&$A9&"*") -> 0 | I9: =COUNTIFS('03_BR'!$B:$B,"Business Goal",'03_BR'!$G:$G,"*"&$A9&"*") -> 0 | J9: =SUM(E9:I9) -> 4 | K9: BR-F-006, BR-N-024, BR-R-002, BR-R-003 | L9: SCR-06, SCR-07 | M9: =COUNTIF('10_API'!$G:$G,A9) -> 2
A10: UC-06 | B10: Đổi mật khẩu | C10: AUTH | D10: Must | E10: =COUNTIFS('03_BR'!$B:$B,"Functional BR",'03_BR'!$G:$G,"*"&$A10&"*") -> 1 | F10: =COUNTIFS('03_BR'!$B:$B,"Non-functional BR",'03_BR'!$G:$G,"*"&$A10&"*") -> 1 | G10: =COUNTIFS('03_BR'!$B:$B,"Business Rule",'03_BR'!$G:$G,"*"&$A10&"*") -> 1 | H10: =COUNTIFS('03_BR'!$B:$B,"Business Constraint",'03_BR'!$G:$G,"*"&$A10&"*") -> 0 | I10: =COUNTIFS('03_BR'!$B:$B,"Business Goal",'03_BR'!$G:$G,"*"&$A10&"*") -> 0 | J10: =SUM(E10:I10) -> 3 | K10: BR-F-007, BR-N-016, BR-R-002 | L10: SCR-12 | M10: =COUNTIF('10_API'!$G:$G,A10) -> 1
A11: UC-07 | B11: Quản lý hồ sơ cá nhân và sổ địa chỉ | C11: KYC | D11: Must | E11: =COUNTIFS('03_BR'!$B:$B,"Functional BR",'03_BR'!$G:$G,"*"&$A11&"*") -> 4 | F11: =COUNTIFS('03_BR'!$B:$B,"Non-functional BR",'03_BR'!$G:$G,"*"&$A11&"*") -> 1 | G11: =COUNTIFS('03_BR'!$B:$B,"Business Rule",'03_BR'!$G:$G,"*"&$A11&"*") -> 1 | H11: =COUNTIFS('03_BR'!$B:$B,"Business Constraint",'03_BR'!$G:$G,"*"&$A11&"*") -> 0 | I11: =COUNTIFS('03_BR'!$B:$B,"Business Goal",'03_BR'!$G:$G,"*"&$A11&"*") -> 0 | J11: =SUM(E11:I11) -> 6 | K11: BR-F-004, BR-F-008, BR-F-009, BR-F-124, BR-N-040, BR-R-014 | L11: SCR-10, SCR-11 | M11: =COUNTIF('10_API'!$G:$G,A11) -> 9
A12: UC-08 | B12: Gửi hồ sơ xác minh danh tính (KYC) | C12: KYC | D12: Must | E12: =COUNTIFS('03_BR'!$B:$B,"Functional BR",'03_BR'!$G:$G,"*"&$A12&"*") -> 2 | F12: =COUNTIFS('03_BR'!$B:$B,"Non-functional BR",'03_BR'!$G:$G,"*"&$A12&"*") -> 2 | G12: =COUNTIFS('03_BR'!$B:$B,"Business Rule",'03_BR'!$G:$G,"*"&$A12&"*") -> 2 | H12: =COUNTIFS('03_BR'!$B:$B,"Business Constraint",'03_BR'!$G:$G,"*"&$A12&"*") -> 1 | I12: =COUNTIFS('03_BR'!$B:$B,"Business Goal",'03_BR'!$G:$G,"*"&$A12&"*") -> 1 | J12: =SUM(E12:I12) -> 8 | K12: BR-F-010, BR-F-123, BR-N-018, BR-N-023, BR-R-010, BR-R-011, BR-C-011, BR-G-002 | L12: SCR-13 | M12: =COUNTIF('10_API'!$G:$G,A12) -> 2
A13: UC-09 | B13: Duyệt hồ sơ xác minh | C13: KYC | D13: Must | E13: =COUNTIFS('03_BR'!$B:$B,"Functional BR",'03_BR'!$G:$G,"*"&$A13&"*") -> 1 | F13: =COUNTIFS('03_BR'!$B:$B,"Non-functional BR",'03_BR'!$G:$G,"*"&$A13&"*") -> 0 | G13: =COUNTIFS('03_BR'!$B:$B,"Business Rule",'03_BR'!$G:$G,"*"&$A13&"*") -> 4 | H13: =COUNTIFS('03_BR'!$B:$B,"Business Constraint",'03_BR'!$G:$G,"*"&$A13&"*") -> 0 | I13: =COUNTIFS('03_BR'!$B:$B,"Business Goal",'03_BR'!$G:$G,"*"&$A13&"*") -> 0 | J13: =SUM(E13:I13) -> 5 | K13: BR-F-011, BR-R-011, BR-R-012, BR-R-082, BR-R-084 | L13: SCR-50 | M13: =COUNTIF('10_API'!$G:$G,A13) -> 4
A14: UC-10 | B14: Đăng ký làm Người giao | C14: KYC | D14: Must | E14: =COUNTIFS('03_BR'!$B:$B,"Functional BR",'03_BR'!$G:$G,"*"&$A14&"*") -> 2 | F14: =COUNTIFS('03_BR'!$B:$B,"Non-functional BR",'03_BR'!$G:$G,"*"&$A14&"*") -> 0 | G14: =COUNTIFS('03_BR'!$B:$B,"Business Rule",'03_BR'!$G:$G,"*"&$A14&"*") -> 1 | H14: =COUNTIFS('03_BR'!$B:$B,"Business Constraint",'03_BR'!$G:$G,"*"&$A14&"*") -> 1 | I14: =COUNTIFS('03_BR'!$B:$B,"Business Goal",'03_BR'!$G:$G,"*"&$A14&"*") -> 1 | J14: =SUM(E14:I14) -> 5 | K14: BR-F-012, BR-F-013, BR-R-009, BR-C-022, BR-G-002 | L14: SCR-14 | M14: =COUNTIF('10_API'!$G:$G,A14) -> 1
A15: UC-11 | B15: Ước tính giá và phí | C15: ORD | D15: Must | E15: =COUNTIFS('03_BR'!$B:$B,"Functional BR",'03_BR'!$G:$G,"*"&$A15&"*") -> 5 | F15: =COUNTIFS('03_BR'!$B:$B,"Non-functional BR",'03_BR'!$G:$G,"*"&$A15&"*") -> 1 | G15: =COUNTIFS('03_BR'!$B:$B,"Business Rule",'03_BR'!$G:$G,"*"&$A15&"*") -> 5 | H15: =COUNTIFS('03_BR'!$B:$B,"Business Constraint",'03_BR'!$G:$G,"*"&$A15&"*") -> 1 | I15: =COUNTIFS('03_BR'!$B:$B,"Business Goal",'03_BR'!$G:$G,"*"&$A15&"*") -> 1 | J15: =SUM(E15:I15) -> 13 | K15: BR-F-014, BR-F-015, BR-F-018, BR-F-086, BR-F-122, BR-N-014, BR-R-017, BR-R-063, BR-R-065, BR-R-066, BR-R-068, BR-C-021, BR-G-001 | L15: SCR-01, SCR-02, SCR-17 | M15: =COUNTIF('10_API'!$G:$G,A15) -> 2
A16: UC-12 | B16: Tạo đơn giao hàng | C16: ORD | D16: Must | E16: =COUNTIFS('03_BR'!$B:$B,"Functional BR",'03_BR'!$G:$G,"*"&$A16&"*") -> 10 | F16: =COUNTIFS('03_BR'!$B:$B,"Non-functional BR",'03_BR'!$G:$G,"*"&$A16&"*") -> 4 | G16: =COUNTIFS('03_BR'!$B:$B,"Business Rule",'03_BR'!$G:$G,"*"&$A16&"*") -> 10 | H16: =COUNTIFS('03_BR'!$B:$B,"Business Constraint",'03_BR'!$G:$G,"*"&$A16&"*") -> 2 | I16: =COUNTIFS('03_BR'!$B:$B,"Business Goal",'03_BR'!$G:$G,"*"&$A16&"*") -> 1 | J16: =SUM(E16:I16) -> 27 | K16: BR-F-009, BR-F-015, BR-F-016, BR-F-017, BR-F-018, BR-F-019, BR-F-020, BR-F-025, BR-F-122, BR-F-123, BR-N-002, BR-N-023, BR-N-027, BR-N-030, BR-R-007, BR-R-015, BR-R-016, BR-R-017, BR-R-018, BR-R-019, BR-R-020, BR-R-023, BR-R-026, BR-R-080, BR-C-012, BR-C-020, BR-G-001 | L16: SCR-17 | M16: =COUNTIF('10_API'!$G:$G,A16) -> 6
... A18: UC-14 | B18: Sửa đơn | C18: ORD | D18: Must | E18: =COUNTIFS('03_BR'!$B:$B,"Functional BR",'03_BR'!$G:$G,"*"&$A18&"*") -> 1 | F18: =COUNTIFS('03_BR'!$B:$B,"Non-functional BR",'03_BR'!$G:$G,"*"&$A18&"*") -> 0 | G18: =COUNTIFS('03_BR'!$B:$B,"Business Rule",'03_BR'!$G:$G,"*"&$A18&"*") -> 2 | H18: =COUNTIFS('03_BR'!$B:$B,"Business Constraint",'03_BR'!$G:$G,"*"&$A18&"*") -> 0 | I18: =COUNTIFS('03_BR'!$B:$B,"Business Goal",'03_BR'!$G:$G,"*"&$A18&"*") -> 0 | J18: =SUM(E18:I18) -> 3 | K18: BR-F-023, BR-R-019, BR-R-021 | L18: SCR-20 | M18: =COUNTIF('10_API'!$G:$G,A18) -> 1
A19: UC-15 | B19: Hủy đơn | C19: ORD | D19: Must | E19: =COUNTIFS('03_BR'!$B:$B,"Functional BR",'03_BR'!$G:$G,"*"&$A19&"*") -> 1 | F19: =COUNTIFS('03_BR'!$B:$B,"Non-functional BR",'03_BR'!$G:$G,"*"&$A19&"*") -> 0 | G19: =COUNTIFS('03_BR'!$B:$B,"Business Rule",'03_BR'!$G:$G,"*"&$A19&"*") -> 2 | H19: =COUNTIFS('03_BR'!$B:$B,"Business Constraint",'03_BR'!$G:$G,"*"&$A19&"*") -> 0 | I19: =COUNTIFS('03_BR'!$B:$B,"Business Goal",'03_BR'!$G:$G,"*"&$A19&"*") -> 0 | J19: =SUM(E19:I19) -> 3 | K19: BR-F-024, BR-R-022, BR-R-075 | M19: =COUNTIF('10_API'!$G:$G,A19) -> 1
A20: UC-16 | B20: Duyệt và tìm kiếm sàn đơn | C20: MKT | D20: Must | E20: =COUNTIFS('03_BR'!$B:$B,"Functional BR",'03_BR'!$G:$G,"*"&$A20&"*") -> 4 | F20: =COUNTIFS('03_BR'!$B:$B,"Non-functional BR",'03_BR'!$G:$G,"*"&$A20&"*") -> 3 | G20: =COUNTIFS('03_BR'!$B:$B,"Business Rule",'03_BR'!$G:$G,"*"&$A20&"*") -> 2 | H20: =COUNTIFS('03_BR'!$B:$B,"Business Constraint",'03_BR'!$G:$G,"*"&$A20&"*") -> 0 | I20: =COUNTIFS('03_BR'!$B:$B,"Business Goal",'03_BR'!$G:$G,"*"&$A20&"*") -> 1 | J20: =SUM(E20:I20) -> 10 | K20: BR-F-026, BR-F-027, BR-F-028, BR-F-035, BR-N-001, BR-N-006, BR-N-031, BR-R-024, BR-R-027, BR-G-003 | L20: SCR-28, SCR-29 | M20: =COUNTIF('10_API'!$G:$G,A20) -> 4
A21: UC-17 | B21: Nhận đơn (giá niêm yết) | C21: MKT | D21: Must | E21: =COUNTIFS('03_BR'!$B:$B,"Functional BR",'03_BR'!$G:$G,"*"&$A21&"*") -> 1 | F21: =COUNTIFS('03_BR'!$B:$B,"Non-functional BR",'03_BR'!$G:$G,"*"&$A21&"*") -> 1 | G21: =COUNTIFS('03_BR'!$B:$B,"Business Rule",'03_BR'!$G:$G,"*"&$A21&"*") -> 5 | H21: =COUNTIFS('03_BR'!$B:$B,"Business Constraint",'03_BR'!$G:$G,"*"&$A21&"*") -> 0 | I21: =COUNTIFS('03_BR'!$B:$B,"Business Goal",'03_BR'!$G:$G,"*"&$A21&"*") -> 1 | J21: =SUM(E21:I21) -> 8 | K21: BR-F-029, BR-N-027, BR-R-008, BR-R-009, BR-R-024, BR-R-025, BR-R-028, BR-G-003 | L21: SCR-30 | M21: =COUNTIF('10_API'!$G:$G,A21) -> 1
A22: UC-18 | B22: Gửi chào giá | C22: MKT | D22: Must | E22: =COUNTIFS('03_BR'!$B:$B,"Functional BR",'03_BR'!$G:$G,"*"&$A22&"*") -> 1 | F22: =COUNTIFS('03_BR'!$B:$B,"Non-functional BR",'03_BR'!$G:$G,"*"&$A22&"*") -> 1 | G22: =COUNTIFS('03_BR'!$B:$B,"Business Rule",'03_BR'!$G:$G,"*"&$A22&"*") -> 5 | H22: =COUNTIFS('03_BR'!$B:$B,"Business Constraint",'03_BR'!$G:$G,"*"&$A22&"*") -> 0 | I22: =COUNTIFS('03_BR'!$B:$B,"Business Goal",'03_BR'!$G:$G,"*"&$A22&"*") -> 1 | J22: =SUM(E22:I22) -> 8 | K22: BR-F-030, BR-N-002, BR-R-008, BR-R-009, BR-R-028, BR-R-029, BR-R-030, BR-G-003 | L22: SCR-30 | M22: =COUNTIF('10_API'!$G:$G,A22) -> 3
A23: UC-19 | B23: Xử lý chào giá (chấp nhận, từ chối, phản giá) | C23: MKT | D23: Must | E23: =COUNTIFS('03_BR'!$B:$B,"Functional BR",'03_BR'!$G:$G,"*"&$A23&"*") -> 4 | F23: =COUNTIFS('03_BR'!$B:$B,"Non-functional BR",'03_BR'!$G:$G,"*"&$A23&"*") -> 0 | G23: =COUNTIFS('03_BR'!$B:$B,"Business Rule",'03_BR'!$G:$G,"*"&$A23&"*") -> 4 | H23: =COUNTIFS('03_BR'!$B:$B,"Business Constraint",'03_BR'!$G:$G,"*"&$A23&"*") -> 0 | I23: =COUNTIFS('03_BR'!$B:$B,"Business Goal",'03_BR'!$G:$G,"*"&$A23&"*") -> 0 | J23: =SUM(E23:I23) -> 8 | K23: BR-F-031, BR-F-032, BR-F-086, BR-F-094, BR-R-025, BR-R-029, BR-R-031, BR-R-032 | L23: SCR-21 | M23: =COUNTIF('10_API'!$G:$G,A23) -> 4
A24: UC-20 | B24: Mời trực tiếp người giao | C24: MKT | D24: Could | E24: =COUNTIFS('03_BR'!$B:$B,"Functional BR",'03_BR'!$G:$G,"*"&$A24&"*") -> 2 | F24: =COUNTIFS('03_BR'!$B:$B,"Non-functional BR",'03_BR'!$G:$G,"*"&$A24&"*") -> 0 | G24: =COUNTIFS('03_BR'!$B:$B,"Business Rule",'03_BR'!$G:$G,"*"&$A24&"*") -> 0 | H24: =COUNTIFS('03_BR'!$B:$B,"Business Constraint",'03_BR'!$G:$G,"*"&$A24&"*") -> 0 | I24: =COUNTIFS('03_BR'!$B:$B,"Business Goal",'03_BR'!$G:$G,"*"&$A24&"*") -> 0 | J24: =SUM(E24:I24) -> 2 | K24: BR-F-019, BR-F-033 | M24: =COUNTIF('10_API'!$G:$G,A24) -> 2
A25: UC-21 | B25: Gợi ý ghép đơn–chuyến | C25: MKT | D25: Should | E25: =COUNTIFS('03_BR'!$B:$B,"Functional BR",'03_BR'!$G:$G,"*"&$A25&"*") -> 2 | F25: =COUNTIFS('03_BR'!$B:$B,"Non-functional BR",'03_BR'!$G:$G,"*"&$A25&"*") -> 1 | G25: =COUNTIFS('03_BR'!$B:$B,"Business Rule",'03_BR'!$G:$G,"*"&$A25&"*") -> 1 | H25: =COUNTIFS('03_BR'!$B:$B,"Business Constraint",'03_BR'!$G:$G,"*"&$A25&"*") -> 0 | I25: =COUNTIFS('03_BR'!$B:$B,"Business Goal",'03_BR'!$G:$G,"*"&$A25&"*") -> 1 | J25: =SUM(E25:I25) -> 5 | K25: BR-F-034, BR-F-038, BR-N-008, BR-R-036, BR-G-008 | L25: SCR-34 | M25: =COUNTIF('10_API'!$G:$G,A25) -> 2
A26: UC-22 | B26: Đăng chuyến đi | C26: TRP | D26: Should | E26: =COUNTIFS('03_BR'!$B:$B,"Functional BR",'03_BR'!$G:$G,"*"&$A26&"*") -> 3 | F26: =COUNTIFS('03_BR'!$B:$B,"Non-functional BR",'03_BR'!$G:$G,"*"&$A26&"*") -> 0 | G26: =COUNTIFS('03_BR'!$B:$B,"Business Rule",'03_BR'!$G:$G,"*"&$A26&"*") -> 1 | H26: =COUNTIFS('03_BR'!$B:$B,"Business Constraint",'03_BR'!$G:$G,"*"&$A26&"*") -> 0 | I26: =COUNTIFS('03_BR'!$B:$B,"Business Goal",'03_BR'!$G:$G,"*"&$A26&"*") -> 1 | J26: =SUM(E26:I26) -> 5 | K26: BR-F-036, BR-F-037, BR-F-038, BR-R-035, BR-G-008 | L26: SCR-33 | M26: =COUNTIF('10_API'!$G:$G,A26) -> 2
A27: UC-23 | B27: Quản lý chuyến đi | C27: TRP | D27: Should | E27: =COUNTIFS('03_BR'!$B:$B,"Functional BR",'03_BR'!$G:$G,"*"&$A27&"*") -> 2 | F27: =COUNTIFS('03_BR'!$B:$B,"Non-functional BR",'03_BR'!$G:$G,"*"&$A27&"*") -> 0 | G27: =COUNTIFS('03_BR'!$B:$B,"Business Rule",'03_BR'!$G:$G,"*"&$A27&"*") -> 1 | H27: =COUNTIFS('03_BR'!$B:$B,"Business Constraint",'03_BR'!$G:$G,"*"&$A27&"*") -> 0 | I27: =COUNTIFS('03_BR'!$B:$B,"Business Goal",'03_BR'!$G:$G,"*"&$A27&"*") -> 0 | J27: =SUM(E27:I27) -> 3 | K27: BR-F-039, BR-F-040, BR-R-037 | L27: SCR-34 | M27: =COUNTIF('10_API'!$G:$G,A27) -> 5
A28: UC-24 | B28: Chat theo đơn | C28: NEG | D28: Must | E28: =COUNTIFS('03_BR'!$B:$B,"Functional BR",'03_BR'!$G:$G,"*"&$A28&"*") -> 5 | F28: =COUNTIFS('03_BR'!$B:$B,"Non-functional BR",'03_BR'!$G:$G,"*"&$A28&"*") -> 1 | G28: =COUNTIFS('03_BR'!$B:$B,"Business Rule",'03_BR'!$G:$G,"*"&$A28&"*") -> 2 | H28: =COUNTIFS('03_BR'!$B:$B,"Business Constraint",'03_BR'!$G:$G,"*"&$A28&"*") -> 1 | I28: =COUNTIFS('03_BR'!$B:$B,"Business Goal",'03_BR'!$G:$G,"*"&$A28&"*") -> 0 | J28: =SUM(E28:I28) -> 9 | K28: BR-F-041, BR-F-042, BR-F-043, BR-F-044, BR-F-045, BR-N-011, BR-R-033, BR-R-034, BR-C-004 | L28: SCR-38 | M28: =COUNTIF('10_API'!$G:$G,A28) -> 4
A29: UC-25 | B29: Xác nhận lấy hàng (QR + ảnh) | C29: TRK | D29: Must | E29: =COUNTIFS('03_BR'!$B:$B,"Functional BR",'03_BR'!$G:$G,"*"&$A29&"*") -> 3 | F29: =COUNTIFS('03_BR'!$B:$B,"Non-functional BR",'03_BR'!$G:$G,"*"&$A29&"*") -> 1 | G29: =COUNTIFS('03_BR'!$B:$B,"Business Rule",'03_BR'!$G:$G,"*"&$A29&"*") -> 1 | H29: =COUNTIFS('03_BR'!$B:$B,"Business Constraint",'03_BR'!$G:$G,"*"&$A29&"*") -> 0 | I29: =COUNTIFS('03_BR'!$B:$B,"Business Goal",'03_BR'!$G:$G,"*"&$A29&"*") -> 1 | J29: =SUM(E29:I29) -> 6 | K29: BR-F-046, BR-F-047, BR-F-123, BR-N-023, BR-R-038, BR-G-009 | L29: SCR-24, SCR-32 | M29: =COUNTIF('10_API'!$G:$G,A29) -> 2
A30: UC-26 | B30: Chia sẻ vị trí và cập nhật hành trình | C30: TRK | D30: Must | E30: =COUNTIFS('03_BR'!$B:$B,"Functional BR",'03_BR'!$G:$G,"*"&$A30&"*") -> 3 | F30: =COUNTIFS('03_BR'!$B:$B,"Non-functional BR",'03_BR'!$G:$G,"*"&$A30&"*") -> 1 | G30: =COUNTIFS('03_BR'!$B:$B,"Business Rule",'03_BR'!$G:$G,"*"&$A30&"*") -> 1 | H30: =COUNTIFS('03_BR'!$B:$B,"Business Constraint",'03_BR'!$G:$G,"*"&$A30&"*") -> 1 | I30: =COUNTIFS('03_BR'!$B:$B,"Business Goal",'03_BR'!$G:$G,"*"&$A30&"*") -> 0 | J30: =SUM(E30:I30) -> 6 | K30: BR-F-048, BR-F-049, BR-F-056, BR-N-007, BR-R-041, BR-C-017 | L30: SCR-32 | M30: =COUNTIF('10_API'!$G:$G,A30) -> 2
A31: UC-27 | B31: Theo dõi đơn thời gian thực | C31: TRK | D31: Must | E31: =COUNTIFS('03_BR'!$B:$B,"Functional BR",'03_BR'!$G:$G,"*"&$A31&"*") -> 5 | F31: =COUNTIFS('03_BR'!$B:$B,"Non-functional BR",'03_BR'!$G:$G,"*"&$A31&"*") -> 2 | G31: =COUNTIFS('03_BR'!$B:$B,"Business Rule",'03_BR'!$G:$G,"*"&$A31&"*") -> 1 | H31: =COUNTIFS('03_BR'!$B:$B,"Business Constraint",'03_BR'!$G:$G,"*"&$A31&"*") -> 1 | I31: =COUNTIFS('03_BR'!$B:$B,"Business Goal",'03_BR'!$G:$G,"*"&$A31&"*") -> 0 | J31: =SUM(E31:I31) -> 9 | K31: BR-F-022, BR-F-050, BR-F-051, BR-F-062, BR-F-122, BR-N-007, BR-N-011, BR-R-042, BR-C-004 | L31: SCR-09, SCR-23 | M31: =COUNTIF('10_API'!$G:$G,A31) -> 3
A32: UC-28 | B32: Xác nhận giao hàng (OTP/QR + ảnh) | C32: TRK | D32: Must | E32: =COUNTIFS('03_BR'!$B:$B,"Functional BR",'03_BR'!$G:$G,"*"&$A32&"*") -> 4 | F32: =COUNTIFS('03_BR'!$B:$B,"Non-functional BR",'03_BR'!$G:$G,"*"&$A32&"*") -> 1 | G32: =COUNTIFS('03_BR'!$B:$B,"Business Rule",'03_BR'!$G:$G,"*"&$A32&"*") -> 2 | H32: =COUNTIFS('03_BR'!$B:$B,"Business Constraint",'03_BR'!$G:$G,"*"&$A32&"*") -> 0 | I32: =COUNTIFS('03_BR'!$B:$B,"Business Goal",'03_BR'!$G:$G,"*"&$A32&"*") -> 2 | J32: =SUM(E32:I32) -> 9 | K32: BR-F-052, BR-F-053, BR-F-103, BR-F-123, BR-N-027, BR-R-039, BR-R-040, BR-G-004, BR-G-009 | L32: SCR-32 | M32: =COUNTIF('10_API'!$G:$G,A32) -> 3
A33: UC-29 | B33: Báo sự cố khi giao | C33: TRK | D33: Must | E33: =COUNTIFS('03_BR'!$B:$B,"Functional BR",'03_BR'!$G:$G,"*"&$A33&"*") -> 2 | F33: =COUNTIFS('03_BR'!$B:$B,"Non-functional BR",'03_BR'!$G:$G,"*"&$A33&"*") -> 0 | G33: =COUNTIFS('03_BR'!$B:$B,"Business Rule",'03_BR'!$G:$G,"*"&$A33&"*") -> 0 | H33: =COUNTIFS('03_BR'!$B:$B,"Business Constraint",'03_BR'!$G:$G,"*"&$A33&"*") -> 0 | I33: =COUNTIFS('03_BR'!$B:$B,"Business Goal",'03_BR'!$G:$G,"*"&$A33&"*") -> 0 | J33: =SUM(E33:I33) -> 2 | K33: BR-F-054, BR-F-110 | L33: SCR-32 | M33: =COUNTIF('10_API'!$G:$G,A33) -> 2
A34: UC-30 | B34: Giao thất bại và hoàn hàng | C34: TRK | D34: Must | E34: =COUNTIFS('03_BR'!$B:$B,"Functional BR",'03_BR'!$G:$G,"*"&$A34&"*") -> 1 | F34: =COUNTIFS('03_BR'!$B:$B,"Non-functional BR",'03_BR'!$G:$G,"*"&$A34&"*") -> 0 | G34: =COUNTIFS('03_BR'!$B:$B,"Business Rule",'03_BR'!$G:$G,"*"&$A34&"*") -> 1 | H34: =COUNTIFS('03_BR'!$B:$B,"Business Constraint",'03_BR'!$G:$G,"*"&$A34&"*") -> 0 | I34: =COUNTIFS('03_BR'!$B:$B,"Business Goal",'03_BR'!$G:$G,"*"&$A34&"*") -> 0 | J34: =SUM(E34:I34) -> 2 | K34: BR-F-055, BR-R-044 | L34: SCR-24, SCR-32 | M34: =COUNTIF('10_API'!$G:$G,A34) -> 2
A35: UC-31 | B35: Gộp đơn và gợi ý lộ trình | C35: REL | D35: Could | E35: =COUNTIFS('03_BR'!$B:$B,"Functional BR",'03_BR'!$G:$G,"*"&$A35&"*") -> 2 | F35: =COUNTIFS('03_BR'!$B:$B,"Non-functional BR",'03_BR'!$G:$G,"*"&$A35&"*") -> 0 | G35: =COUNTIFS('03_BR'!$B:$B,"Business Rule",'03_BR'!$G:$G,"*"&$A35&"*") -> 1 | H35: =COUNTIFS('03_BR'!$B:$B,"Business Constraint",'03_BR'!$G:$G,"*"&$A35&"*") -> 0 | I35: =COUNTIFS('03_BR'!$B:$B,"Business Goal",'03_BR'!$G:$G,"*"&$A35&"*") -> 0 | J35: =SUM(E35:I35) -> 3 | K35: BR-F-057, BR-F-058, BR-R-046 | L35: SCR-36 | M35: =COUNTIF('10_API'!$G:$G,A35) -> 2
A36: UC-32 | B36: Tạo đơn giao tiếp sức | C36: REL | D36: Could | E36: =COUNTIFS('03_BR'!$B:$B,"Functional BR",'03_BR'!$G:$G,"*"&$A36&"*") -> 2 | F36: =COUNTIFS('03_BR'!$B:$B,"Non-functional BR",'03_BR'!$G:$G,"*"&$A36&"*") -> 0 | G36: =COUNTIFS('03_BR'!$B:$B,"Business Rule",'03_BR'!$G:$G,"*"&$A36&"*") -> 1 | H36: =COUNTIFS('03_BR'!$B:$B,"Business Constraint",'03_BR'!$G:$G,"*"&$A36&"*") -> 0 | I36: =COUNTIFS('03_BR'!$B:$B,"Business Goal",'03_BR'!$G:$G,"*"&$A36&"*") -> 0 | J36: =SUM(E36:I36) -> 3 | K36: BR-F-059, BR-F-062, BR-R-047 | M36: =COUNTIF('10_API'!$G:$G,A36) -> 1
A37: UC-33 | B37: Bàn giao giữa các chặng | C37: REL | D37: Could | E37: =COUNTIFS('03_BR'!$B:$B,"Functional BR",'03_BR'!$G:$G,"*"&$A37&"*") -> 2 | F37: =COUNTIFS('03_BR'!$B:$B,"Non-functional BR",'03_BR'!$G:$G,"*"&$A37&"*") -> 0 | G37: =COUNTIFS('03_BR'!$B:$B,"Business Rule",'03_BR'!$G:$G,"*"&$A37&"*") -> 1 | H37: =COUNTIFS('03_BR'!$B:$B,"Business Constraint",'03_BR'!$G:$G,"*"&$A37&"*") -> 0 | I37: =COUNTIFS('03_BR'!$B:$B,"Business Goal",'03_BR'!$G:$G,"*"&$A37&"*") -> 0 | J37: =SUM(E37:I37) -> 3 | K37: BR-F-060, BR-F-061, BR-R-048 | M37: =COUNTIF('10_API'!$G:$G,A37) -> 1
A38: UC-34 | B38: Nạp tiền vào ví qua VNPay | C38: PAY | D38: Must | E38: =COUNTIFS('03_BR'!$B:$B,"Functional BR",'03_BR'!$G:$G,"*"&$A38&"*") -> 4 | F38: =COUNTIFS('03_BR'!$B:$B,"Non-functional BR",'03_BR'!$G:$G,"*"&$A38&"*") -> 2 | G38: =COUNTIFS('03_BR'!$B:$B,"Business Rule",'03_BR'!$G:$G,"*"&$A38&"*") -> 4 | H38: =COUNTIFS('03_BR'!$B:$B,"Business Constraint",'03_BR'!$G:$G,"*"&$A38&"*") -> 2 | I38: =COUNTIFS('03_BR'!$B:$B,"Business Goal",'03_BR'!$G:$G,"*"&$A38&"*") -> 0 | J38: =SUM(E38:I38) -> 12 | K38: BR-F-063, BR-F-064, BR-F-065, BR-F-071, BR-N-003, BR-N-014, BR-R-007, BR-R-050, BR-R-051, BR-R-052, BR-C-006, BR-C-019 | L38: SCR-42, SCR-43 | M38: =COUNTIF('10_API'!$G:$G,A38) -> 2
A39: UC-35 | B39: Thanh toán đơn và ký quỹ | C39: PAY | D39: Must | E39: =COUNTIFS('03_BR'!$B:$B,"Functional BR",'03_BR'!$G:$G,"*"&$A39&"*") -> 5 | F39: =COUNTIFS('03_BR'!$B:$B,"Non-functional BR",'03_BR'!$G:$G,"*"&$A39&"*") -> 3 | G39: =COUNTIFS('03_BR'!$B:$B,"Business Rule",'03_BR'!$G:$G,"*"&$A39&"*") -> 4 | H39: =COUNTIFS('03_BR'!$B:$B,"Business Constraint",'03_BR'!$G:$G,"*"&$A39&"*") -> 2 | I39: =COUNTIFS('03_BR'!$B:$B,"Business Goal",'03_BR'!$G:$G,"*"&$A39&"*") -> 1 | J39: =SUM(E39:I39) -> 15 | K39: BR-F-064, BR-F-070, BR-F-071, BR-F-072, BR-F-086, BR-N-003, BR-N-021, BR-N-039, BR-R-031, BR-R-052, BR-R-053, BR-R-068, BR-C-006, BR-C-009, BR-G-012 | L39: SCR-22, SCR-43 | M39: =COUNTIF('10_API'!$G:$G,A39) -> 1
A40: UC-36 | B40: Giải ngân cho người giao | C40: PAY | D40: Must | E40: =COUNTIFS('03_BR'!$B:$B,"Functional BR",'03_BR'!$G:$G,"*"&$A40&"*") -> 2 | F40: =COUNTIFS('03_BR'!$B:$B,"Non-functional BR",'03_BR'!$G:$G,"*"&$A40&"*") -> 2 | G40: =COUNTIFS('03_BR'!$B:$B,"Business Rule",'03_BR'!$G:$G,"*"&$A40&"*") -> 6 | H40: =COUNTIFS('03_BR'!$B:$B,"Business Constraint",'03_BR'!$G:$G,"*"&$A40&"*") -> 1 | I40: =COUNTIFS('03_BR'!$B:$B,"Business Goal",'03_BR'!$G:$G,"*"&$A40&"*") -> 2 | J40: =SUM(E40:I40) -> 13 | K40: BR-F-073, BR-F-074, BR-N-021, BR-N-039, BR-R-040, BR-R-054, BR-R-055, BR-R-063, BR-R-064, BR-R-067, BR-C-010, BR-G-006, BR-G-012 | M40: =COUNTIF('10_API'!$G:$G,A40) -> 2
A41: UC-37 | B41: Hoàn tiền | C41: PAY | D41: Must | E41: =COUNTIFS('03_BR'!$B:$B,"Functional BR",'03_BR'!$G:$G,"*"&$A41&"*") -> 2 | F41: =COUNTIFS('03_BR'!$B:$B,"Non-functional BR",'03_BR'!$G:$G,"*"&$A41&"*") -> 1 | G41: =COUNTIFS('03_BR'!$B:$B,"Business Rule",'03_BR'!$G:$G,"*"&$A41&"*") -> 4 | H41: =COUNTIFS('03_BR'!$B:$B,"Business Constraint",'03_BR'!$G:$G,"*"&$A41&"*") -> 1 | I41: =COUNTIFS('03_BR'!$B:$B,"Business Goal",'03_BR'!$G:$G,"*"&$A41&"*") -> 0 | J41: =SUM(E41:I41) -> 8 | K41: BR-F-075, BR-F-076, BR-N-021, BR-R-022, BR-R-043, BR-R-044, BR-R-056, BR-C-007 | M41: =COUNTIF('10_API'!$G:$G,A41) -> 1
A42: UC-38 | B42: Xem ví và lịch sử giao dịch | C42: PAY | D42: Must | E42: =COUNTIFS('03_BR'!$B:$B,"Functional BR",'03_BR'!$G:$G,"*"&$A42&"*") -> 2 | F42: =COUNTIFS('03_BR'!$B:$B,"Non-functional BR",'03_BR'!$G:$G,"*"&$A42&"*") -> 1 | G42: =COUNTIFS('03_BR'!$B:$B,"Business Rule",'03_BR'!$G:$G,"*"&$A42&"*") -> 1 | H42: =COUNTIFS('03_BR'!$B:$B,"Business Constraint",'03_BR'!$G:$G,"*"&$A42&"*") -> 1 | I42: =COUNTIFS('03_BR'!$B:$B,"Business Goal",'03_BR'!$G:$G,"*"&$A42&"*") -> 0 | J42: =SUM(E42:I42) -> 5 | K42: BR-F-068, BR-F-069, BR-N-020, BR-R-049, BR-C-009 | L42: SCR-41, SCR-44 | M42: =COUNTIF('10_API'!$G:$G,A42) -> 3
A43: UC-39 | B43: Quản lý tài khoản ngân hàng nhận tiền | C43: PAY | D43: Must | E43: =COUNTIFS('03_BR'!$B:$B,"Functional BR",'03_BR'!$G:$G,"*"&$A43&"*") -> 1 | F43: =COUNTIFS('03_BR'!$B:$B,"Non-functional BR",'03_BR'!$G:$G,"*"&$A43&"*") -> 1 | G43: =COUNTIFS('03_BR'!$B:$B,"Business Rule",'03_BR'!$G:$G,"*"&$A43&"*") -> 2 | H43: =COUNTIFS('03_BR'!$B:$B,"Business Constraint",'03_BR'!$G:$G,"*"&$A43&"*") -> 0 | I43: =COUNTIFS('03_BR'!$B:$B,"Business Goal",'03_BR'!$G:$G,"*"&$A43&"*") -> 0 | J43: =SUM(E43:I43) -> 4 | K43: BR-F-077, BR-N-018, BR-R-013, BR-R-058 | L43: SCR-45 | M43: =COUNTIF('10_API'!$G:$G,A43) -> 3
A44: UC-40 | B44: Yêu cầu rút tiền | C44: PAY | D44: Must | E44: =COUNTIFS('03_BR'!$B:$B,"Functional BR",'03_BR'!$G:$G,"*"&$A44&"*") -> 1 | F44: =COUNTIFS('03_BR'!$B:$B,"Non-functional BR",'03_BR'!$G:$G,"*"&$A44&"*") -> 1 | G44: =COUNTIFS('03_BR'!$B:$B,"Business Rule",'03_BR'!$G:$G,"*"&$A44&"*") -> 5 | H44: =COUNTIFS('03_BR'!$B:$B,"Business Constraint",'03_BR'!$G:$G,"*"&$A44&"*") -> 1 | I44: =COUNTIFS('03_BR'!$B:$B,"Business Goal",'03_BR'!$G:$G,"*"&$A44&"*") -> 1 | J44: =SUM(E44:I44) -> 9 | K44: BR-F-078, BR-N-021, BR-R-013, BR-R-057, BR-R-058, BR-R-059, BR-R-061, BR-C-008, BR-G-011 | L44: SCR-46 | M44: =COUNTIF('10_API'!$G:$G,A44) -> 3
A45: UC-41 | B45: Duyệt và chi trả rút tiền | C45: PAY | D45: Must | E45: =COUNTIFS('03_BR'!$B:$B,"Functional BR",'03_BR'!$G:$G,"*"&$A45&"*") -> 3 | F45: =COUNTIFS('03_BR'!$B:$B,"Non-functional BR",'03_BR'!$G:$G,"*"&$A45&"*") -> 0 | G45: =COUNTIFS('03_BR'!$B:$B,"Business Rule",'03_BR'!$G:$G,"*"&$A45&"*") -> 2 | H45: =COUNTIFS('03_BR'!$B:$B,"Business Constraint",'03_BR'!$G:$G,"*"&$A45&"*") -> 1 | I45: =COUNTIFS('03_BR'!$B:$B,"Business Goal",'03_BR'!$G:$G,"*"&$A45&"*") -> 1 | J45: =SUM(E45:I45) -> 7 | K45: BR-F-079, BR-F-080, BR-F-081, BR-R-060, BR-R-061, BR-C-008, BR-G-011 | L45: SCR-54 | M45: =COUNTIF('10_API'!$G:$G,A45) -> 6
A46: UC-42 | B46: Xử lý IPN và kết quả từ VNPay | C46: PAY | D46: Must | E46: =COUNTIFS('03_BR'!$B:$B,"Functional BR",'03_BR'!$G:$G,"*"&$A46&"*") -> 2 | F46: =COUNTIFS('03_BR'!$B:$B,"Non-functional BR",'03_BR'!$G:$G,"*"&$A46&"*") -> 3 | G46: =COUNTIFS('03_BR'!$B:$B,"Business Rule",'03_BR'!$G:$G,"*"&$A46&"*") -> 1 | H46: =COUNTIFS('03_BR'!$B:$B,"Business Constraint",'03_BR'!$G:$G,"*"&$A46&"*") -> 1 | I46: =COUNTIFS('03_BR'!$B:$B,"Business Goal",'03_BR'!$G:$G,"*"&$A46&"*") -> 0 | J46: =SUM(E46:I46) -> 7 | K46: BR-F-066, BR-F-067, BR-N-004, BR-N-021, BR-N-022, BR-R-051, BR-C-006 | M46: =COUNTIF('10_API'!$G:$G,A46) -> 1
A47: UC-43 | B47: Đối soát giao dịch hằng ngày | C47: PAY | D47: Should | E47: =COUNTIFS('03_BR'!$B:$B,"Functional BR",'03_BR'!$G:$G,"*"&$A47&"*") -> 3 | F47: =COUNTIFS('03_BR'!$B:$B,"Non-functional BR",'03_BR'!$G:$G,"*"&$A47&"*") -> 2 | G47: =COUNTIFS('03_BR'!$B:$B,"Business Rule",'03_BR'!$G:$G,"*"&$A47&"*") -> 1 | H47: =COUNTIFS('03_BR'!$B:$B,"Business Constraint",'03_BR'!$G:$G,"*"&$A47&"*") -> 0 | I47: =COUNTIFS('03_BR'!$B:$B,"Business Goal",'03_BR'!$G:$G,"*"&$A47&"*") -> 1 | J47: =SUM(E47:I47) -> 7 | K47: BR-F-082, BR-F-083, BR-F-084, BR-N-015, BR-N-039, BR-R-062, BR-G-012 | L47: SCR-55 | M47: =COUNTIF('10_API'!$G:$G,A47) -> 4
A48: UC-44 | B48: Áp dụng mã khuyến mãi | C48: FEE | D48: Could | E48: =COUNTIFS('03_BR'!$B:$B,"Functional BR",'03_BR'!$G:$G,"*"&$A48&"*") -> 1 | F48: =COUNTIFS('03_BR'!$B:$B,"Non-functional BR",'03_BR'!$G:$G,"*"&$A48&"*") -> 0 | G48: =COUNTIFS('03_BR'!$B:$B,"Business Rule",'03_BR'!$G:$G,"*"&$A48&"*") -> 1 | H48: =COUNTIFS('03_BR'!$B:$B,"Business Constraint",'03_BR'!$G:$G,"*"&$A48&"*") -> 0 | I48: =COUNTIFS('03_BR'!$B:$B,"Business Goal",'03_BR'!$G:$G,"*"&$A48&"*") -> 0 | J48: =SUM(E48:I48) -> 2 | K48: BR-F-087, BR-R-069 | L48: SCR-22 | M48: =COUNTIF('10_API'!$G:$G,A48) -> 1
A49: UC-45 | B49: Quản lý khuyến mãi | C49: FEE | D49: Could | E49: =COUNTIFS('03_BR'!$B:$B,"Functional BR",'03_BR'!$G:$G,"*"&$A49&"*") -> 1 | F49: =COUNTIFS('03_BR'!$B:$B,"Non-functional BR",'03_BR'!$G:$G,"*"&$A49&"*") -> 0 | G49: =COUNTIFS('03_BR'!$B:$B,"Business Rule",'03_BR'!$G:$G,"*"&$A49&"*") -> 1 | H49: =COUNTIFS('03_BR'!$B:$B,"Business Constraint",'03_BR'!$G:$G,"*"&$A49&"*") -> 0 | I49: =COUNTIFS('03_BR'!$B:$B,"Business Goal",'03_BR'!$G:$G,"*"&$A49&"*") -> 0 | J49: =SUM(E49:I49) -> 2 | K49: BR-F-088, BR-R-069 | L49: SCR-59 | M49: =COUNTIF('10_API'!$G:$G,A49) -> 3
A50: UC-46 | B50: Cấu hình tham số hệ thống và biểu phí | C50: ADM | D50: Must | E50: =COUNTIFS('03_BR'!$B:$B,"Functional BR",'03_BR'!$G:$G,"*"&$A50&"*") -> 2 | F50: =COUNTIFS('03_BR'!$B:$B,"Non-functional BR",'03_BR'!$G:$G,"*"&$A50&"*") -> 0 | G50: =COUNTIFS('03_BR'!$B:$B,"Business Rule",'03_BR'!$G:$G,"*"&$A50&"*") -> 3 | H50: =COUNTIFS('03_BR'!$B:$B,"Business Constraint",'03_BR'!$G:$G,"*"&$A50&"*") -> 0 | I50: =COUNTIFS('03_BR'!$B:$B,"Business Goal",'03_BR'!$G:$G,"*"&$A50&"*") -> 1 | J50: =SUM(E50:I50) -> 6 | K50: BR-F-085, BR-F-089, BR-R-055, BR-R-067, BR-R-083, BR-G-006 | L50: SCR-57 | M50: =COUNTIF('10_API'!$G:$G,A50) -> 3
A51: UC-47 | B51: Đánh giá hai chiều | C51: REP | D51: Must | E51: =COUNTIFS('03_BR'!$B:$B,"Functional BR",'03_BR'!$G:$G,"*"&$A51&"*") -> 1 | F51: =COUNTIFS('03_BR'!$B:$B,"Non-functional BR",'03_BR'!$G:$G,"*"&$A51&"*") -> 1 | G51: =COUNTIFS('03_BR'!$B:$B,"Business Rule",'03_BR'!$G:$G,"*"&$A51&"*") -> 3 | H51: =COUNTIFS('03_BR'!$B:$B,"Business Constraint",'03_BR'!$G:$G,"*"&$A51&"*") -> 0 | I51: =COUNTIFS('03_BR'!$B:$B,"Business Goal",'03_BR'!$G:$G,"*"&$A51&"*") -> 1 | J51: =SUM(E51:I51) -> 6 | K51: BR-F-090, BR-N-002, BR-R-008, BR-R-070, BR-R-071, BR-G-010 | L51: SCR-25 | M51: =COUNTIF('10_API'!$G:$G,A51) -> 1
A52: UC-48 | B52: Xem hồ sơ công khai và điểm uy tín | C52: REP | D52: Must | E52: =COUNTIFS('03_BR'!$B:$B,"Functional BR",'03_BR'!$G:$G,"*"&$A52&"*") -> 3 | F52: =COUNTIFS('03_BR'!$B:$B,"Non-functional BR",'03_BR'!$G:$G,"*"&$A52&"*") -> 0 | G52: =COUNTIFS('03_BR'!$B:$B,"Business Rule",'03_BR'!$G:$G,"*"&$A52&"*") -> 1 | H52: =COUNTIFS('03_BR'!$B:$B,"Business Constraint",'03_BR'!$G:$G,"*"&$A52&"*") -> 0 | I52: =COUNTIFS('03_BR'!$B:$B,"Business Goal",'03_BR'!$G:$G,"*"&$A52&"*") -> 0 | J52: =SUM(E52:I52) -> 4 | K52: BR-F-031, BR-F-091, BR-F-093, BR-R-071 | L52: SCR-15 | M52: =COUNTIF('10_API'!$G:$G,A52) -> 3
A53: UC-49 | B53: Tính điểm uy tín và xếp hạng | C53: REP | D53: Must | E53: =COUNTIFS('03_BR'!$B:$B,"Functional BR",'03_BR'!$G:$G,"*"&$A53&"*") -> 3 | F53: =COUNTIFS('03_BR'!$B:$B,"Non-functional BR",'03_BR'!$G:$G,"*"&$A53&"*") -> 0 | G53: =COUNTIFS('03_BR'!$B:$B,"Business Rule",'03_BR'!$G:$G,"*"&$A53&"*") -> 5 | H53: =COUNTIFS('03_BR'!$B:$B,"Business Constraint",'03_BR'!$G:$G,"*"&$A53&"*") -> 0 | I53: =COUNTIFS('03_BR'!$B:$B,"Business Goal",'03_BR'!$G:$G,"*"&$A53&"*") -> 1 | J53: =SUM(E53:I53) -> 9 | K53: BR-F-092, BR-F-094, BR-F-119, BR-R-028, BR-R-072, BR-R-073, BR-R-074, BR-R-075, BR-G-007 | M53: =COUNTIF('10_API'!$G:$G,A53) -> 1
A54: UC-50 | B54: Tạo khiếu nại | C54: DSP | D54: Must | E54: =COUNTIFS('03_BR'!$B:$B,"Functional BR",'03_BR'!$G:$G,"*"&$A54&"*") -> 1 | F54: =COUNTIFS('03_BR'!$B:$B,"Non-functional BR",'03_BR'!$G:$G,"*"&$A54&"*") -> 0 | G54: =COUNTIFS('03_BR'!$B:$B,"Business Rule",'03_BR'!$G:$G,"*"&$A54&"*") -> 3 | H54: =COUNTIFS('03_BR'!$B:$B,"Business Constraint",'03_BR'!$G:$G,"*"&$A54&"*") -> 0 | I54: =COUNTIFS('03_BR'!$B:$B,"Business Goal",'03_BR'!$G:$G,"*"&$A54&"*") -> 1 | J54: =SUM(E54:I54) -> 5 | K54: BR-F-095, BR-R-054, BR-R-076, BR-R-077, BR-G-005 | L54: SCR-26 | M54: =COUNTIF('10_API'!$G:$G,A54) -> 1
A55: UC-51 | B55: Xử lý khiếu nại và phán quyết | C55: DSP | D55: Must | E55: =COUNTIFS('03_BR'!$B:$B,"Functional BR",'03_BR'!$G:$G,"*"&$A55&"*") -> 5 | F55: =COUNTIFS('03_BR'!$B:$B,"Non-functional BR",'03_BR'!$G:$G,"*"&$A55&"*") -> 0 | G55: =COUNTIFS('03_BR'!$B:$B,"Business Rule",'03_BR'!$G:$G,"*"&$A55&"*") -> 2 | H55: =COUNTIFS('03_BR'!$B:$B,"Business Constraint",'03_BR'!$G:$G,"*"&$A55&"*") -> 0 | I55: =COUNTIFS('03_BR'!$B:$B,"Business Goal",'03_BR'!$G:$G,"*"&$A55&"*") -> 1 | J55: =SUM(E55:I55) -> 8 | K55: BR-F-045, BR-F-096, BR-F-097, BR-F-099, BR-F-100, BR-R-077, BR-R-078, BR-G-005 | L55: SCR-52, SCR-53 | M55: =COUNTIF('10_API'!$G:$G,A55) -> 5
A56: UC-52 | B56: Xét duyệt bồi thường từ Quỹ bảo đảm | C56: DSP | D56: Must | E56: =COUNTIFS('03_BR'!$B:$B,"Functional BR",'03_BR'!$G:$G,"*"&$A56&"*") -> 1 | F56: =COUNTIFS('03_BR'!$B:$B,"Non-functional BR",'03_BR'!$G:$G,"*"&$A56&"*") -> 0 | G56: =COUNTIFS('03_BR'!$B:$B,"Business Rule",'03_BR'!$G:$G,"*"&$A56&"*") -> 3 | H56: =COUNTIFS('03_BR'!$B:$B,"Business Constraint",'03_BR'!$G:$G,"*"&$A56&"*") -> 0 | I56: =COUNTIFS('03_BR'!$B:$B,"Business Goal",'03_BR'!$G:$G,"*"&$A56&"*") -> 0 | J56: =SUM(E56:I56) -> 4 | K56: BR-F-098, BR-R-064, BR-R-077, BR-R-079 | L56: SCR-56 | M56: =COUNTIF('10_API'!$G:$G,A56) -> 2
A57: UC-53 | B57: Nhận và cấu hình thông báo | C57: NTF | D57: Must | E57: =COUNTIFS('03_BR'!$B:$B,"Functional BR",'03_BR'!$G:$G,"*"&$A57&"*") -> 6 | F57: =COUNTIFS('03_BR'!$B:$B,"Non-functional BR",'03_BR'!$G:$G,"*"&$A57&"*") -> 2 | G57: =COUNTIFS('03_BR'!$B:$B,"Business Rule",'03_BR'!$G:$G,"*"&$A57&"*") -> 1 | H57: =COUNTIFS('03_BR'!$B:$B,"Business Constraint",'03_BR'!$G:$G,"*"&$A57&"*") -> 0 | I57: =COUNTIFS('03_BR'!$B:$B,"Business Goal",'03_BR'!$G:$G,"*"&$A57&"*") -> 0 | J57: =SUM(E57:I57) -> 9 | K57: BR-F-035, BR-F-101, BR-F-102, BR-F-103, BR-F-104, BR-F-105, BR-N-009, BR-N-014, BR-R-085 | L57: SCR-39, SCR-40 | M57: =COUNTIF('10_API'!$G:$G,A57) -> 6
A58: UC-54 | B58: Kiểm duyệt đơn hàng | C58: SAF | D58: Must | E58: =COUNTIFS('03_BR'!$B:$B,"Functional BR",'03_BR'!$G:$G,"*"&$A58&"*") -> 2 | F58: =COUNTIFS('03_BR'!$B:$B,"Non-functional BR",'03_BR'!$G:$G,"*"&$A58&"*") -> 0 | G58: =COUNTIFS('03_BR'!$B:$B,"Business Rule",'03_BR'!$G:$G,"*"&$A58&"*") -> 1 | H58: =COUNTIFS('03_BR'!$B:$B,"Business Constraint",'03_BR'!$G:$G,"*"&$A58&"*") -> 1 | I58: =COUNTIFS('03_BR'!$B:$B,"Business Goal",'03_BR'!$G:$G,"*"&$A58&"*") -> 0 | J58: =SUM(E58:I58) -> 4 | K58: BR-F-106, BR-F-107, BR-R-080, BR-C-012 | L58: SCR-51 | M58: =COUNTIF('10_API'!$G:$G,A58) -> 3
A59: UC-55 | B59: Báo cáo vi phạm | C59: SAF | D59: Must | E59: =COUNTIFS('03_BR'!$B:$B,"Functional BR",'03_BR'!$G:$G,"*"&$A59&"*") -> 4 | F59: =COUNTIFS('03_BR'!$B:$B,"Non-functional BR",'03_BR'!$G:$G,"*"&$A59&"*") -> 0 | G59: =COUNTIFS('03_BR'!$B:$B,"Business Rule",'03_BR'!$G:$G,"*"&$A59&"*") -> 1 | H59: =COUNTIFS('03_BR'!$B:$B,"Business Constraint",'03_BR'!$G:$G,"*"&$A59&"*") -> 0 | I59: =COUNTIFS('03_BR'!$B:$B,"Business Goal",'03_BR'!$G:$G,"*"&$A59&"*") -> 0 | J59: =SUM(E59:I59) -> 5 | K59: BR-F-044, BR-F-056, BR-F-108, BR-F-110, BR-R-034 | L59: SCR-64 | M59: =COUNTIF('10_API'!$G:$G,A59) -> 2
A60: UC-56 | B60: Khóa và mở khóa tài khoản | C60: SAF | D60: Must | E60: =COUNTIFS('03_BR'!$B:$B,"Functional BR",'03_BR'!$G:$G,"*"&$A60&"*") -> 1 | F60: =COUNTIFS('03_BR'!$B:$B,"Non-functional BR",'03_BR'!$G:$G,"*"&$A60&"*") -> 0 | G60: =COUNTIFS('03_BR'!$B:$B,"Business Rule",'03_BR'!$G:$G,"*"&$A60&"*") -> 3 | H60: =COUNTIFS('03_BR'!$B:$B,"Business Constraint",'03_BR'!$G:$G,"*"&$A60&"*") -> 0 | I60: =COUNTIFS('03_BR'!$B:$B,"Business Goal",'03_BR'!$G:$G,"*"&$A60&"*") -> 0 | J60: =SUM(E60:I60) -> 4 | K60: BR-F-109, BR-R-074, BR-R-081, BR-R-082 | L60: SCR-49 | M60: =COUNTIF('10_API'!$G:$G,A60) -> 3
A61: UC-57 | B61: Quản lý người dùng và nhân sự | C61: ADM | D61: Must | E61: =COUNTIFS('03_BR'!$B:$B,"Functional BR",'03_BR'!$G:$G,"*"&$A61&"*") -> 3 | F61: =COUNTIFS('03_BR'!$B:$B,"Non-functional BR",'03_BR'!$G:$G,"*"&$A61&"*") -> 1 | G61: =COUNTIFS('03_BR'!$B:$B,"Business Rule",'03_BR'!$G:$G,"*"&$A61&"*") -> 0 | H61: =COUNTIFS('03_BR'!$B:$B,"Business Constraint",'03_BR'!$G:$G,"*"&$A61&"*") -> 0 | I61: =COUNTIFS('03_BR'!$B:$B,"Business Goal",'03_BR'!$G:$G,"*"&$A61&"*") -> 0 | J61: =SUM(E61:I61) -> 4 | K61: BR-F-111, BR-F-112, BR-F-124, BR-N-040 | L61: SCR-48, SCR-49, SCR-63 | M61: =COUNTIF('10_API'!$G:$G,A61) -> 4
A62: UC-58 | B62: Quản lý danh mục | C62: ADM | D62: Must | E62: =COUNTIFS('03_BR'!$B:$B,"Functional BR",'03_BR'!$G:$G,"*"&$A62&"*") -> 2 | F62: =COUNTIFS('03_BR'!$B:$B,"Non-functional BR",'03_BR'!$G:$G,"*"&$A62&"*") -> 0 | G62: =COUNTIFS('03_BR'!$B:$B,"Business Rule",'03_BR'!$G:$G,"*"&$A62&"*") -> 0 | H62: =COUNTIFS('03_BR'!$B:$B,"Business Constraint",'03_BR'!$G:$G,"*"&$A62&"*") -> 1 | I62: =COUNTIFS('03_BR'!$B:$B,"Business Goal",'03_BR'!$G:$G,"*"&$A62&"*") -> 0 | J62: =SUM(E62:I62) -> 3 | K62: BR-F-061, BR-F-113, BR-C-012 | L62: SCR-58 | M62: =COUNTIF('10_API'!$G:$G,A62) -> 6
A63: UC-59 | B63: Dashboard và báo cáo | C63: ADM | D63: Must | E63: =COUNTIFS('03_BR'!$B:$B,"Functional BR",'03_BR'!$G:$G,"*"&$A63&"*") -> 4 | F63: =COUNTIFS('03_BR'!$B:$B,"Non-functional BR",'03_BR'!$G:$G,"*"&$A63&"*") -> 0 | G63: =COUNTIFS('03_BR'!$B:$B,"Business Rule",'03_BR'!$G:$G,"*"&$A63&"*") -> 0 | H63: =COUNTIFS('03_BR'!$B:$B,"Business Constraint",'03_BR'!$G:$G,"*"&$A63&"*") -> 1 | I63: =COUNTIFS('03_BR'!$B:$B,"Business Goal",'03_BR'!$G:$G,"*"&$A63&"*") -> 0 | J63: =SUM(E63:I63) -> 5 | K63: BR-F-084, BR-F-100, BR-F-114, BR-F-115, BR-C-010 | L63: SCR-47, SCR-62 | M63: =COUNTIF('10_API'!$G:$G,A63) -> 3
A64: UC-60 | B64: Xem nhật ký kiểm toán | C64: ADM | D64: Should | E64: =COUNTIFS('03_BR'!$B:$B,"Functional BR",'03_BR'!$G:$G,"*"&$A64&"*") -> 2 | F64: =COUNTIFS('03_BR'!$B:$B,"Non-functional BR",'03_BR'!$G:$G,"*"&$A64&"*") -> 2 | G64: =COUNTIFS('03_BR'!$B:$B,"Business Rule",'03_BR'!$G:$G,"*"&$A64&"*") -> 2 | H64: =COUNTIFS('03_BR'!$B:$B,"Business Constraint",'03_BR'!$G:$G,"*"&$A64&"*") -> 0 | I64: =COUNTIFS('03_BR'!$B:$B,"Business Goal",'03_BR'!$G:$G,"*"&$A64&"*") -> 0 | J64: =SUM(E64:I64) -> 6 | K64: BR-F-083, BR-F-116, BR-N-026, BR-N-038, BR-R-045, BR-R-084 | L64: SCR-60 | M64: =COUNTIF('10_API'!$G:$G,A64) -> 1
A65: UC-61 | B65: Xem thu nhập và thống kê | C65: GAM | D65: Should | E65: =COUNTIFS('03_BR'!$B:$B,"Functional BR",'03_BR'!$G:$G,"*"&$A65&"*") -> 3 | F65: =COUNTIFS('03_BR'!$B:$B,"Non-functional BR",'03_BR'!$G:$G,"*"&$A65&"*") -> 0 | G65: =COUNTIFS('03_BR'!$B:$B,"Business Rule",'03_BR'!$G:$G,"*"&$A65&"*") -> 0 | H65: =COUNTIFS('03_BR'!$B:$B,"Business Constraint",'03_BR'!$G:$G,"*"&$A65&"*") -> 0 | I65: =COUNTIFS('03_BR'!$B:$B,"Business Goal",'03_BR'!$G:$G,"*"&$A65&"*") -> 1 | J65: =SUM(E65:I65) -> 4 | K65: BR-F-074, BR-F-118, BR-F-119, BR-G-014 | L65: SCR-27, SCR-35 | M65: =COUNTIF('10_API'!$G:$G,A65) -> 2
... A67: UC-63 | B67: Xử lý tác vụ định kỳ | C67: ADM | D67: Must | E67: =COUNTIFS('03_BR'!$B:$B,"Functional BR",'03_BR'!$G:$G,"*"&$A67&"*") -> 3 | F67: =COUNTIFS('03_BR'!$B:$B,"Non-functional BR",'03_BR'!$G:$G,"*"&$A67&"*") -> 2 | G67: =COUNTIFS('03_BR'!$B:$B,"Business Rule",'03_BR'!$G:$G,"*"&$A67&"*") -> 3 | H67: =COUNTIFS('03_BR'!$B:$B,"Business Constraint",'03_BR'!$G:$G,"*"&$A67&"*") -> 0 | I67: =COUNTIFS('03_BR'!$B:$B,"Business Goal",'03_BR'!$G:$G,"*"&$A67&"*") -> 0 | J67: =SUM(E67:I67) -> 8 | K67: BR-F-067, BR-F-073, BR-F-117, BR-N-015, BR-N-041, BR-R-020, BR-R-031, BR-R-043 | L67: SCR-61 | M67: =COUNTIF('10_API'!$G:$G,A67) -> 3
A70: Ma trận số lượng BR theo phân hệ và loại
A71: Mã | B71: Phân hệ | E71: Functional | F71: Non-functional | G71: Business Rule | H71: Constraint | I71: Goal | J71: Tổng
A72: AUTH | B72: Tài khoản & Xác thực | E72: =COUNTIFS('03_BR'!$C:$C,$A72,'03_BR'!$B:$B,"Functional BR") -> 7 | F72: =COUNTIFS('03_BR'!$C:$C,$A72,'03_BR'!$B:$B,"Non-functional BR") -> 2 | G72: =COUNTIFS('03_BR'!$C:$C,$A72,'03_BR'!$B:$B,"Business Rule") -> 8 | H72: =COUNTIFS('03_BR'!$C:$C,$A72,'03_BR'!$B:$B,"Business Constraint") -> 1 | I72: =COUNTIFS('03_BR'!$C:$C,$A72,'03_BR'!$B:$B,"Business Goal") -> 0 | J72: =SUM(E72:I72) -> 18
A73: KYC | B73: Xác minh & Hồ sơ | E73: =COUNTIFS('03_BR'!$C:$C,$A73,'03_BR'!$B:$B,"Functional BR") -> 6 | F73: =COUNTIFS('03_BR'!$C:$C,$A73,'03_BR'!$B:$B,"Non-functional BR") -> 2 | G73: =COUNTIFS('03_BR'!$C:$C,$A73,'03_BR'!$B:$B,"Business Rule") -> 6 | H73: =COUNTIFS('03_BR'!$C:$C,$A73,'03_BR'!$B:$B,"Business Constraint") -> 2 | I73: =COUNTIFS('03_BR'!$C:$C,$A73,'03_BR'!$B:$B,"Business Goal") -> 0 | J73: =SUM(E73:I73) -> 16
A74: ORD | B74: Đơn hàng | E74: =COUNTIFS('03_BR'!$C:$C,$A74,'03_BR'!$B:$B,"Functional BR") -> 12 | F74: =COUNTIFS('03_BR'!$C:$C,$A74,'03_BR'!$B:$B,"Non-functional BR") -> 0 | G74: =COUNTIFS('03_BR'!$C:$C,$A74,'03_BR'!$B:$B,"Business Rule") -> 12 | H74: =COUNTIFS('03_BR'!$C:$C,$A74,'03_BR'!$B:$B,"Business Constraint") -> 1 | I74: =COUNTIFS('03_BR'!$C:$C,$A74,'03_BR'!$B:$B,"Business Goal") -> 0 | J74: =SUM(E74:I74) -> 25
A75: MKT | B75: Sàn đơn & Ghép đơn | E75: =COUNTIFS('03_BR'!$C:$C,$A75,'03_BR'!$B:$B,"Functional BR") -> 10 | F75: =COUNTIFS('03_BR'!$C:$C,$A75,'03_BR'!$B:$B,"Non-functional BR") -> 2 | G75: =COUNTIFS('03_BR'!$C:$C,$A75,'03_BR'!$B:$B,"Business Rule") -> 5 | H75: =COUNTIFS('03_BR'!$C:$C,$A75,'03_BR'!$B:$B,"Business Constraint") -> 1 | I75: =COUNTIFS('03_BR'!$C:$C,$A75,'03_BR'!$B:$B,"Business Goal") -> 2 | J75: =SUM(E75:I75) -> 20
A76: TRP | B76: Chuyến đi | E76: =COUNTIFS('03_BR'!$C:$C,$A76,'03_BR'!$B:$B,"Functional BR") -> 5 | F76: =COUNTIFS('03_BR'!$C:$C,$A76,'03_BR'!$B:$B,"Non-functional BR") -> 0 | G76: =COUNTIFS('03_BR'!$C:$C,$A76,'03_BR'!$B:$B,"Business Rule") -> 3 | H76: =COUNTIFS('03_BR'!$C:$C,$A76,'03_BR'!$B:$B,"Business Constraint") -> 0 | I76: =COUNTIFS('03_BR'!$C:$C,$A76,'03_BR'!$B:$B,"Business Goal") -> 0 | J76: =SUM(E76:I76) -> 8
A77: NEG | B77: Thương lượng & Chat | E77: =COUNTIFS('03_BR'!$C:$C,$A77,'03_BR'!$B:$B,"Functional BR") -> 5 | F77: =COUNTIFS('03_BR'!$C:$C,$A77,'03_BR'!$B:$B,"Non-functional BR") -> 0 | G77: =COUNTIFS('03_BR'!$C:$C,$A77,'03_BR'!$B:$B,"Business Rule") -> 3 | H77: =COUNTIFS('03_BR'!$C:$C,$A77,'03_BR'!$B:$B,"Business Constraint") -> 0 | I77: =COUNTIFS('03_BR'!$C:$C,$A77,'03_BR'!$B:$B,"Business Goal") -> 0 | J77: =SUM(E77:I77) -> 8
A78: TRK | B78: Theo dõi & Giao nhận | E78: =COUNTIFS('03_BR'!$C:$C,$A78,'03_BR'!$B:$B,"Functional BR") -> 11 | F78: =COUNTIFS('03_BR'!$C:$C,$A78,'03_BR'!$B:$B,"Non-functional BR") -> 2 | G78: =COUNTIFS('03_BR'!$C:$C,$A78,'03_BR'!$B:$B,"Business Rule") -> 8 | H78: =COUNTIFS('03_BR'!$C:$C,$A78,'03_BR'!$B:$B,"Business Constraint") -> 0 | I78: =COUNTIFS('03_BR'!$C:$C,$A78,'03_BR'!$B:$B,"Business Goal") -> 2 | J78: =SUM(E78:I78) -> 23
A79: REL | B79: Giao tiếp sức & Gộp đơn | E79: =COUNTIFS('03_BR'!$C:$C,$A79,'03_BR'!$B:$B,"Functional BR") -> 6 | F79: =COUNTIFS('03_BR'!$C:$C,$A79,'03_BR'!$B:$B,"Non-functional BR") -> 0 | G79: =COUNTIFS('03_BR'!$C:$C,$A79,'03_BR'!$B:$B,"Business Rule") -> 3 | H79: =COUNTIFS('03_BR'!$C:$C,$A79,'03_BR'!$B:$B,"Business Constraint") -> 0 | I79: =COUNTIFS('03_BR'!$C:$C,$A79,'03_BR'!$B:$B,"Business Goal") -> 0 | J79: =SUM(E79:I79) -> 9
A80: PAY | B80: Ví & Thanh toán | E80: =COUNTIFS('03_BR'!$C:$C,$A80,'03_BR'!$B:$B,"Functional BR") -> 22 | F80: =COUNTIFS('03_BR'!$C:$C,$A80,'03_BR'!$B:$B,"Non-functional BR") -> 5 | G80: =COUNTIFS('03_BR'!$C:$C,$A80,'03_BR'!$B:$B,"Business Rule") -> 16 | H80: =COUNTIFS('03_BR'!$C:$C,$A80,'03_BR'!$B:$B,"Business Constraint") -> 6 | I80: =COUNTIFS('03_BR'!$C:$C,$A80,'03_BR'!$B:$B,"Business Goal") -> 2 | J80: =SUM(E80:I80) -> 51
A81: FEE | B81: Giá, Phí & Khuyến mãi | E81: =COUNTIFS('03_BR'!$C:$C,$A81,'03_BR'!$B:$B,"Functional BR") -> 5 | F81: =COUNTIFS('03_BR'!$C:$C,$A81,'03_BR'!$B:$B,"Non-functional BR") -> 0 | G81: =COUNTIFS('03_BR'!$C:$C,$A81,'03_BR'!$B:$B,"Business Rule") -> 5 | H81: =COUNTIFS('03_BR'!$C:$C,$A81,'03_BR'!$B:$B,"Business Constraint") -> 0 | I81: =COUNTIFS('03_BR'!$C:$C,$A81,'03_BR'!$B:$B,"Business Goal") -> 1 | J81: =SUM(E81:I81) -> 11
A82: REP | B82: Uy tín & Đánh giá | E82: =COUNTIFS('03_BR'!$C:$C,$A82,'03_BR'!$B:$B,"Functional BR") -> 5 | F82: =COUNTIFS('03_BR'!$C:$C,$A82,'03_BR'!$B:$B,"Non-functional BR") -> 0 | G82: =COUNTIFS('03_BR'!$C:$C,$A82,'03_BR'!$B:$B,"Business Rule") -> 6 | H82: =COUNTIFS('03_BR'!$C:$C,$A82,'03_BR'!$B:$B,"Business Constraint") -> 0 | I82: =COUNTIFS('03_BR'!$C:$C,$A82,'03_BR'!$B:$B,"Business Goal") -> 1 | J82: =SUM(E82:I82) -> 12
A83: DSP | B83: Khiếu nại & Bảo đảm | E83: =COUNTIFS('03_BR'!$C:$C,$A83,'03_BR'!$B:$B,"Functional BR") -> 6 | F83: =COUNTIFS('03_BR'!$C:$C,$A83,'03_BR'!$B:$B,"Non-functional BR") -> 0 | G83: =COUNTIFS('03_BR'!$C:$C,$A83,'03_BR'!$B:$B,"Business Rule") -> 4 | H83: =COUNTIFS('03_BR'!$C:$C,$A83,'03_BR'!$B:$B,"Business Constraint") -> 0 | I83: =COUNTIFS('03_BR'!$C:$C,$A83,'03_BR'!$B:$B,"Business Goal") -> 1 | J83: =SUM(E83:I83) -> 11
... A88: SYS | B88: Hệ thống chung | E88: =COUNTIFS('03_BR'!$C:$C,$A88,'03_BR'!$B:$B,"Functional BR") -> 3 | F88: =COUNTIFS('03_BR'!$C:$C,$A88,'03_BR'!$B:$B,"Non-functional BR") -> 26 | G88: =COUNTIFS('03_BR'!$C:$C,$A88,'03_BR'!$B:$B,"Business Rule") -> 0 | H88: =COUNTIFS('03_BR'!$C:$C,$A88,'03_BR'!$B:$B,"Business Constraint") -> 10 | I88: =COUNTIFS('03_BR'!$C:$C,$A88,'03_BR'!$B:$B,"Business Goal") -> 4 | J88: =SUM(E88:I88) -> 43
A89: Tổng | E89: =SUM(E72:E88) -> 124 | F89: =SUM(F72:F88) -> 41 | G89: =SUM(G72:G88) -> 85 | H89: =SUM(H72:H88) -> 22 | I89: =SUM(I72:I88) -> 14 | J89: =SUM(J72:J88) -> 286

Sheet 06_Tham_số
A1: Tham số nghiệp vụ (có thể cấu hình)
A2: Mọi con số trong BR được lấy từ đây; Admin chỉnh qua UC-46. Ô giá trị (chữ xanh) là nguồn duy nhất của sự thật.
A4: Mã | B4: Nhóm | C4: Khóa cấu hình | D4: Tên tham số | E4: Giá trị mặc định | F4: Đơn vị | G4: Mô tả | H4: Số BR tham chiếu | I4: BR liên quan | J4: Người chỉnh
A5: PRM-001 | B5: Tài khoản & Bảo mật | C5: OTP_TTL | D5: Thời hạn hiệu lực OTP | E5: 5 | F5: phút | G5: Thời gian OTP đăng ký/đặt lại mật khẩu còn hiệu lực. | H5: =COUNTIF('03_BR'!$K:$K,"*"&A5&"*") -> 1 | I5: BR-R-003 | J5: Admin (UC-46)
A6: PRM-002 | B6: Tài khoản & Bảo mật | C6: OTP_MAX_TRIES | D6: Số lần nhập sai OTP tối đa | E6: 5 | F6: lần | G6: Vượt quá thì OTP bị vô hiệu, phải yêu cầu gửi lại. | H6: =COUNTIF('03_BR'!$K:$K,"*"&A6&"*") -> 1 | I6: BR-R-003 | J6: Admin (UC-46)
A7: PRM-003 | B7: Tài khoản & Bảo mật | C7: OTP_RESEND | D7: Khoảng cách tối thiểu giữa 2 lần gửi OTP | E7: 60 | F7: giây | G7: Chống spam SMS/email. | H7: =COUNTIF('03_BR'!$K:$K,"*"&A7&"*") -> 1 | I7: BR-R-003 | J7: Admin (UC-46)
A8: PRM-004 | B8: Tài khoản & Bảo mật | C8: LOGIN_MAX_FAIL | D8: Số lần đăng nhập sai liên tiếp tối đa | E8: 5 | F8: lần | G8: Vượt quá thì khóa đăng nhập tạm thời. | H8: =COUNTIF('03_BR'!$K:$K,"*"&A8&"*") -> 1 | I8: BR-R-004 | J8: Admin (UC-46)
A9: PRM-005 | B9: Tài khoản & Bảo mật | C9: LOGIN_LOCK | D9: Thời gian khóa đăng nhập tạm thời | E9: 15 | F9: phút | G9: Áp dụng khi vượt LOGIN_MAX_FAIL. | H9: =COUNTIF('03_BR'!$K:$K,"*"&A9&"*") -> 1 | I9: BR-R-004 | J9: Admin (UC-46)
A10: PRM-006 | B10: Tài khoản & Bảo mật | C10: JWT_ACCESS | D10: Thời hạn Access Token | E10: 15 | F10: phút | G10: JWT truy cập ngắn hạn. | H10: =COUNTIF('03_BR'!$K:$K,"*"&A10&"*") -> 1 | I10: BR-R-005 | J10: Admin (UC-46)
A11: PRM-007 | B11: Tài khoản & Bảo mật | C11: JWT_REFRESH | D11: Thời hạn Refresh Token | E11: 7 | F11: ngày | G11: Refresh token xoay vòng (rotation). | H11: =COUNTIF('03_BR'!$K:$K,"*"&A11&"*") -> 1 | I11: BR-R-005 | J11: Admin (UC-46)
A12: PRM-008 | B12: Tài khoản & Bảo mật | C12: PWD_MIN | D12: Độ dài mật khẩu tối thiểu | E12: 8 | F12: ký tự | G12: Kèm ít nhất 1 chữ hoa, 1 chữ thường, 1 chữ số. | H12: =COUNTIF('03_BR'!$K:$K,"*"&A12&"*") -> 1 | I12: BR-R-002 | J12: Admin (UC-46)
A13: PRM-009 | B13: Tài khoản & Bảo mật | C13: MAX_DEVICES | D13: Số thiết bị đăng nhập đồng thời tối đa | E13: 5 | F13: thiết bị | G13: Thiết bị cũ nhất bị đăng xuất khi vượt. | H13: =COUNTIF('03_BR'!$K:$K,"*"&A13&"*") -> 1 | I13: BR-R-006 | J13: Admin (UC-46)
A14: PRM-010 | B14: Tài khoản & Bảo mật | C14: RATE_API | D14: Giới hạn gọi API | E14: 100 | F14: request/phút/người dùng | G14: Vượt quá trả HTTP 429. | H14: =COUNTIF('03_BR'!$K:$K,"*"&A14&"*") -> 1 | I14: BR-N-024 | J14: Admin (UC-46)
A15: PRM-011 | B15: Tài khoản & Bảo mật | C15: RATE_AUTH | D15: Giới hạn gọi API xác thực | E15: 10 | F15: request/phút/IP | G15: Áp dụng cho đăng nhập, đăng ký, OTP, quên mật khẩu. | H15: =COUNTIF('03_BR'!$K:$K,"*"&A15&"*") -> 1 | I15: BR-N-024 | J15: Admin (UC-46)
A16: PRM-012 | B16: Đơn hàng | C16: MAX_WEIGHT | D16: Khối lượng tối đa mỗi đơn | E16: 20 | F16: kg | G16: Phù hợp xe máy/xe khách; hàng nặng hơn không nhận. | H16: =COUNTIF('03_BR'!$K:$K,"*"&A16&"*") -> 2 | I16: BR-R-016, BR-C-020 | J16: Admin (UC-46)
... A28: PRM-024 | B28: Đơn hàng | C28: MAX_OPEN | D28: Số đơn đang mở tối đa của một người gửi | E28: 10 | F28: đơn | G28: Chống spam sàn đơn. | H28: =COUNTIF('03_BR'!$K:$K,"*"&A28&"*") -> 1 | I28: BR-R-015 | J28: Admin (UC-46)
A29: PRM-025 | B29: Đơn hàng | C29: CONTACT_TRIES | D29: Số lần liên hệ người nhận trước khi coi là giao thất bại | E29: 3 lần gọi trong 30 phút | G29: Người giao phải có bằng chứng cuộc gọi/tin nhắn trong ứng dụng. | H29: =COUNTIF('03_BR'!$K:$K,"*"&A29&"*") -> 1 | I29: BR-R-044 | J29: Admin (UC-46)
A30: PRM-026 | B30: Giá & Phí | C30: BASE_FARE | D30: Phí giao cơ bản | E30: 10000 | F30: VND | G30: Áp dụng cho BASE_KM km đầu tiên. | H30: =COUNTIF('03_BR'!$K:$K,"*"&A30&"*") -> 1 | I30: BR-R-065 | J30: Admin (UC-46)
A31: PRM-027 | B31: Giá & Phí | C31: BASE_KM | D31: Quãng đường tính phí cơ bản | E31: 2 | F31: km | G31: Km đầu tiên nằm trong phí cơ bản. | H31: =COUNTIF('03_BR'!$K:$K,"*"&A31&"*") -> 1 | I31: BR-R-065 | J31: Admin (UC-46)
A32: PRM-028 | B32: Giá & Phí | C32: PER_KM | D32: Đơn giá mỗi km tiếp theo | E32: 3500 | F32: VND/km | G32: Từ sau BASE_KM đến LONG_KM. | H32: =COUNTIF('03_BR'!$K:$K,"*"&A32&"*") -> 1 | I32: BR-R-065 | J32: Admin (UC-46)
A33: PRM-029 | B33: Giá & Phí | C33: LONG_KM | D33: Ngưỡng quãng đường dài | E33: 50 | F33: km | G33: Vượt ngưỡng áp dụng đơn giá PER_KM_LONG cho phần vượt. | H33: =COUNTIF('03_BR'!$K:$K,"*"&A33&"*") -> 1 | I33: BR-R-065 | J33: Admin (UC-46)
A34: PRM-030 | B34: Giá & Phí | C34: PER_KM_LONG | D34: Đơn giá mỗi km phần quãng đường dài | E34: 2000 | F34: VND/km | G34: Áp dụng cho phần vượt LONG_KM. | H34: =COUNTIF('03_BR'!$K:$K,"*"&A34&"*") -> 1 | I34: BR-R-065 | J34: Admin (UC-46)
A35: PRM-031 | B35: Giá & Phí | C35: W_FEE_2 | D35: Phụ phí khối lượng >2–5 kg | E35: 5000 | F35: VND | G35: Dưới hoặc bằng 2 kg: 0đ. | H35: =COUNTIF('03_BR'!$K:$K,"*"&A35&"*") -> 1 | I35: BR-R-066 | J35: Admin (UC-46)
A36: PRM-032 | B36: Giá & Phí | C36: W_FEE_3 | D36: Phụ phí khối lượng >5–10 kg | E36: 12000 | F36: VND | H36: =COUNTIF('03_BR'!$K:$K,"*"&A36&"*") -> 1 | I36: BR-R-066 | J36: Admin (UC-46)
A37: PRM-033 | B37: Giá & Phí | C37: W_FEE_4 | D37: Phụ phí khối lượng >10–20 kg | E37: 25000 | F37: VND | H37: =COUNTIF('03_BR'!$K:$K,"*"&A37&"*") -> 1 | I37: BR-R-066 | J37: Admin (UC-46)
A38: PRM-034 | B38: Giá & Phí | C38: SIZE_FEE_M | D38: Phụ phí cỡ Vừa | E38: 5000 | F38: VND | G38: Cỡ Nhỏ: 0đ. | H38: =COUNTIF('03_BR'!$K:$K,"*"&A38&"*") -> 0 | J38: Admin (UC-46)
A39: PRM-035 | B39: Giá & Phí | C39: SIZE_FEE_L | D39: Phụ phí cỡ Lớn | E39: 10000 | F39: VND | H39: =COUNTIF('03_BR'!$K:$K,"*"&A39&"*") -> 0 | J39: Admin (UC-46)
A40: PRM-036 | B40: Giá & Phí | C40: URGENT_MULT | D40: Hệ số giao gấp (trong 2 giờ) | E40: 1.5 | F40: lần | G40: Nhân vào phí giao. | H40: =COUNTIF('03_BR'!$K:$K,"*"&A40&"*") -> 1 | I40: BR-R-066 | J40: Admin (UC-46)
A41: PRM-037 | B41: Giá & Phí | C41: SAMEDAY_MULT | D41: Hệ số giao trong ngày | E41: 1.2 | F41: lần | G41: Nhân vào phí giao. | H41: =COUNTIF('03_BR'!$K:$K,"*"&A41&"*") -> 1 | I41: BR-R-066 | J41: Admin (UC-46)
A42: PRM-038 | B42: Giá & Phí | C42: MIN_FARE | D42: Phí giao tối thiểu | E42: 10000 | F42: VND | G42: Sàn giá của mọi đơn. | H42: =COUNTIF('03_BR'!$K:$K,"*"&A42&"*") -> 1 | I42: BR-R-065 | J42: Admin (UC-46)
A43: PRM-039 | B43: Giá & Phí | C43: BID_MIN | D43: Biên dưới giá chào | E43: 0.7 | F43: % giá gợi ý | G43: Chào giá/phản giá phải ≥ biên này. | H43: =COUNTIF('03_BR'!$K:$K,"*"&A43&"*") -> 1 | I43: BR-R-029 | J43: Admin (UC-46)
A44: PRM-040 | B44: Giá & Phí | C44: BID_MAX | D44: Biên trên giá chào | E44: 1.5 | F44: % giá gợi ý | G44: Chào giá/phản giá phải ≤ biên này. | H44: =COUNTIF('03_BR'!$K:$K,"*"&A44&"*") -> 1 | I44: BR-R-029 | J44: Admin (UC-46)
A45: PRM-041 | B45: Giá & Phí | C45: BID_TTL | D45: Thời hạn hiệu lực chào giá | E45: 120 | F45: phút | G45: Chào giá tự hết hạn. | H45: =COUNTIF('03_BR'!$K:$K,"*"&A45&"*") -> 1 | I45: BR-R-029 | J45: Admin (UC-46)
A46: PRM-042 | B46: Giá & Phí | C46: FEE_NEW | D46: Hoa hồng hạng Tân binh | E46: 0.08 | F46: % phí giao | G46: Thu từ người giao, tính trên phí giao. | H46: =COUNTIF('03_BR'!$K:$K,"*"&A46&"*") -> 2 | I46: BR-R-067, BR-G-006 | J46: Admin (UC-46)
A47: PRM-043 | B47: Giá & Phí | C47: FEE_BRONZE | D47: Hoa hồng hạng Đồng | E47: 0.07 | F47: % phí giao | H47: =COUNTIF('03_BR'!$K:$K,"*"&A47&"*") -> 1 | I47: BR-R-067 | J47: Admin (UC-46)
A48: PRM-044 | B48: Giá & Phí | C48: FEE_SILVER | D48: Hoa hồng hạng Bạc | E48: 0.06 | F48: % phí giao | H48: =COUNTIF('03_BR'!$K:$K,"*"&A48&"*") -> 1 | I48: BR-R-067 | J48: Admin (UC-46)
A49: PRM-045 | B49: Giá & Phí | C49: FEE_GOLD | D49: Hoa hồng hạng Vàng | E49: 0.05 | F49: % phí giao | H49: =COUNTIF('03_BR'!$K:$K,"*"&A49&"*") -> 1 | I49: BR-R-067 | J49: Admin (UC-46)
A50: PRM-046 | B50: Giá & Phí | C50: FEE_DIAMOND | D50: Hoa hồng hạng Kim cương | E50: 0.04 | F50: % phí giao | H50: =COUNTIF('03_BR'!$K:$K,"*"&A50&"*") -> 2 | I50: BR-R-067, BR-G-006 | J50: Admin (UC-46)
A51: PRM-047 | B51: Giá & Phí | C51: INS_RATE | D51: Phí bảo hiểm tùy chọn | E51: 0.01 | F51: % giá trị khai báo | G51: Người gửi trả nếu chọn bảo hiểm. | H51: =COUNTIF('03_BR'!$K:$K,"*"&A51&"*") -> 1 | I51: BR-R-068 | J51: Admin (UC-46)
A52: PRM-048 | B52: Giá & Phí | C52: INS_MIN | D52: Phí bảo hiểm tối thiểu | E52: 2000 | F52: VND | H52: =COUNTIF('03_BR'!$K:$K,"*"&A52&"*") -> 1 | I52: BR-R-068 | J52: Admin (UC-46)
A53: PRM-049 | B53: Giá & Phí | C53: FUND_SHARE | D53: Tỷ lệ trích hoa hồng vào Quỹ bảo đảm | E53: 0.1 | F53: % hoa hồng | G53: Cộng thêm toàn bộ phí bảo hiểm. | H53: =COUNTIF('03_BR'!$K:$K,"*"&A53&"*") -> 1 | I53: BR-R-055 | J53: Admin (UC-46)
A54: PRM-050 | B54: Giá & Phí | C54: CANCEL_RATE | D54: Phí hủy đơn sau khi có người giao | E54: 0.1 | F54: % phí giao | G54: Người gửi hủy sau khi ký quỹ và trước khi lấy hàng. | H54: =COUNTIF('03_BR'!$K:$K,"*"&A54&"*") -> 1 | I54: BR-R-022 | J54: Admin (UC-46)
A55: PRM-051 | B55: Giá & Phí | C55: CANCEL_MIN | D55: Phí hủy tối thiểu | E55: 5000 | F55: VND | H55: =COUNTIF('03_BR'!$K:$K,"*"&A55&"*") -> 1 | I55: BR-R-022 | J55: Admin (UC-46)
A56: PRM-052 | B56: Giá & Phí | C56: RETURN_FEE | D56: Phí hoàn hàng khi giao thất bại do người gửi/người nhận | E56: 0.5 | F56: % phí giao | G56: Thu thêm từ người gửi, trả cho người giao. | H56: =COUNTIF('03_BR'!$K:$K,"*"&A56&"*") -> 1 | I56: BR-R-044 | J56: Admin (UC-46)
A57: PRM-053 | B57: Giá & Phí | C57: ROUND_FEE | D57: Bước làm tròn lên của phí giao | E57: 500 | F57: VND | G57: Phí giao làm tròn lên bội số của giá trị này. | H57: =COUNTIF('03_BR'!$K:$K,"*"&A57&"*") -> 1 | I57: BR-R-063 | J57: Admin (UC-46)
A58: PRM-054 | B58: Giá & Phí | C58: NEGO_ROUNDS | D58: Số vòng phản giá tối đa cho một chào giá | E58: 3 | F58: vòng | H58: =COUNTIF('03_BR'!$K:$K,"*"&A58&"*") -> 1 | I58: BR-R-032 | J58: Admin (UC-46)
A59: PRM-055 | B59: Giá & Phí | C59: WITHHOLD | D59: Tỷ lệ khấu trừ thuế trên doanh thu người giao | E59: 0 | F59: % doanh thu | G59: Mặc định 0% trong đồ án; cấu hình theo quy định thuế hiện hành khi thương mại hóa. | H59: =COUNTIF('03_BR'!$K:$K,"*"&A59&"*") -> 1 | I59: BR-C-010 | J59: Admin (UC-46)
A60: PRM-056 | B60: Ví & Thanh toán | C60: MIN_TOPUP | D60: Số tiền nạp tối thiểu | E60: 20000 | F60: VND | G60: Mỗi giao dịch nạp. | H60: =COUNTIF('03_BR'!$K:$K,"*"&A60&"*") -> 1 | I60: BR-R-050 | J60: Admin (UC-46)
A61: PRM-057 | B61: Ví & Thanh toán | C61: MAX_TOPUP | D61: Số tiền nạp tối đa mỗi giao dịch | E61: 10000000 | F61: VND | G61: Còn phụ thuộc hạn mức của ngân hàng/VNPay. | H61: =COUNTIF('03_BR'!$K:$K,"*"&A61&"*") -> 1 | I61: BR-R-050 | J61: Admin (UC-46)
A62: PRM-058 | B62: Ví & Thanh toán | C62: MAX_BALANCE | D62: Số dư ví tối đa | E62: 20000000 | F62: VND | G62: Kiểm soát rủi ro pháp lý và gian lận. | H62: =COUNTIF('03_BR'!$K:$K,"*"&A62&"*") -> 1 | I62: BR-R-050 | J62: Admin (UC-46)
A63: PRM-059 | B63: Ví & Thanh toán | C63: MIN_WITHDRAW | D63: Số tiền rút tối thiểu | E63: 100000 | F63: VND | G63: Số dư khả dụng phải ≥ ngưỡng này mới được rút. | H63: =COUNTIF('03_BR'!$K:$K,"*"&A63&"*") -> 1 | I63: BR-R-057 | J63: Admin (UC-46)
A64: PRM-060 | B64: Ví & Thanh toán | C64: MAX_WITHDRAW | D64: Số tiền rút tối đa mỗi lần | E64: 10000000 | F64: VND | H64: =COUNTIF('03_BR'!$K:$K,"*"&A64&"*") -> 1 | I64: BR-R-057 | J64: Admin (UC-46)
A65: PRM-061 | B65: Ví & Thanh toán | C65: MAX_WD_DAY | D65: Tổng số tiền rút tối đa mỗi ngày | E65: 20000000 | F65: VND | G65: Mỗi người dùng. | H65: =COUNTIF('03_BR'!$K:$K,"*"&A65&"*") -> 1 | I65: BR-R-057 | J65: Admin (UC-46)
A66: PRM-062 | B66: Ví & Thanh toán | C66: FREE_WD | D66: Số lần rút miễn phí mỗi tháng | E66: 4 | F66: lần | G66: Từ lần thứ 5 tính phí. | H66: =COUNTIF('03_BR'!$K:$K,"*"&A66&"*") -> 1 | I66: BR-R-059 | J66: Admin (UC-46)
A67: PRM-063 | B67: Ví & Thanh toán | C67: WD_FEE | D67: Phí rút tiền từ lần thứ 5 trong tháng | E67: 5000 | F67: VND | H67: =COUNTIF('03_BR'!$K:$K,"*"&A67&"*") -> 1 | I67: BR-R-059 | J67: Admin (UC-46)
A68: PRM-064 | B68: Ví & Thanh toán | C68: WD_SLA | D68: Thời hạn xử lý yêu cầu rút tiền | E68: 1 | F68: ngày làm việc | G68: Tính từ khi yêu cầu hợp lệ. | H68: =COUNTIF('03_BR'!$K:$K,"*"&A68&"*") -> 1 | I68: BR-G-011 | J68: Admin (UC-46)
A69: PRM-065 | B69: Ví & Thanh toán | C69: DUAL_APPROVE | D69: Ngưỡng bắt buộc hai cấp duyệt | E69: 5000000 | F69: VND | G69: Yêu cầu rút ≥ ngưỡng cần 2 Admin khác nhau duyệt (maker–checker). | H69: =COUNTIF('03_BR'!$K:$K,"*"&A69&"*") -> 1 | I69: BR-R-060 | J69: Admin (UC-46)
A70: PRM-066 | B70: Ví & Thanh toán | C70: BANK_COOLDOWN | D70: Thời gian chờ sau khi thêm/đổi tài khoản ngân hàng | E70: 24 | F70: giờ | G70: Chưa được rút về tài khoản mới trong thời gian này. | H70: =COUNTIF('03_BR'!$K:$K,"*"&A70&"*") -> 1 | I70: BR-R-058 | J70: Admin (UC-46)
A71: PRM-067 | B71: Ví & Thanh toán | C71: VNPAY_EXPIRE | D71: Thời hạn liên kết thanh toán VNPay | E71: 15 | F71: phút | G71: Đặt vào tham số hết hạn của giao dịch VNPay. | H71: =COUNTIF('03_BR'!$K:$K,"*"&A71&"*") -> 1 | I71: BR-R-052 | J71: Admin (UC-46)
A72: PRM-068 | B72: Ví & Thanh toán | C72: VNPAY_TIMEOUT | D72: Timeout gọi API VNPay | E72: 10 | F72: giây | G72: Thử lại tối đa 2 lần với truy vấn/hoàn tiền. | H72: =COUNTIF('03_BR'!$K:$K,"*"&A72&"*") -> 0 | J72: Admin (UC-46)
A73: PRM-069 | B73: Ví & Thanh toán | C73: RELEASE_DELAY | D73: Độ trễ giải ngân sau khi người nhận xác nhận | E73: 2 | F73: giờ | G73: Cửa sổ để phát hiện sự cố nhanh trước khi tiền chuyển cho người giao. | H73: =COUNTIF('03_BR'!$K:$K,"*"&A73&"*") -> 1 | I73: BR-R-054 | J73: Admin (UC-46)
A74: PRM-070 | B74: Ví & Thanh toán | C74: AUTO_RELEASE | D74: Thời gian tự giải ngân khi không có xác nhận của người nhận | E74: 24 | F74: giờ | G74: Áp dụng khi giao không có OTP/QR và không có khiếu nại. | H74: =COUNTIF('03_BR'!$K:$K,"*"&A74&"*") -> 2 | I74: BR-R-040, BR-R-054 | J74: Admin (UC-46)
A75: PRM-071 | B75: Ví & Thanh toán | C75: DISPUTE_WINDOW | D75: Thời hạn khiếu nại sau khi giao | E75: 48 | F75: giờ | G75: Quá hạn không tiếp nhận khiếu nại (trừ trường hợp Admin cho phép). | H75: =COUNTIF('03_BR'!$K:$K,"*"&A75&"*") -> 3 | I75: BR-R-033, BR-R-042, BR-R-076 | J75: Admin (UC-46)
A76: PRM-072 | B76: Ví & Thanh toán | C76: RECONCILE_AT | D76: Giờ chạy đối soát hằng ngày | E76: 2 | F76: giờ (02:00) | G76: Đối soát giao dịch ngày hôm trước. | H76: =COUNTIF('03_BR'!$K:$K,"*"&A76&"*") -> 1 | I76: BR-R-062 | J76: Admin (UC-46)
A77: PRM-073 | B77: Ví & Thanh toán | C77: IDEM_TTL | D77: Thời hạn lưu khóa idempotency | E77: 24 | F77: giờ | G77: Chống xử lý lặp giao dịch tiền. | H77: =COUNTIF('03_BR'!$K:$K,"*"&A77&"*") -> 1 | I77: BR-N-021 | J77: Admin (UC-46)
A78: PRM-074 | B78: Uy tín & Hạng | C78: TRUST_INIT | D78: Điểm uy tín khởi tạo | E78: 50 | F78: điểm | G78: Thang 0–100. | H78: =COUNTIF('03_BR'!$K:$K,"*"&A78&"*") -> 1 | I78: BR-R-072 | J78: Admin (UC-46)
A79: PRM-075 | B79: Uy tín & Hạng | C79: W_ONTIME | D79: Trọng số tỷ lệ giao đúng hạn | E79: 0.35 | F79: % | H79: =COUNTIF('03_BR'!$K:$K,"*"&A79&"*") -> 1 | I79: BR-R-072 | J79: Admin (UC-46)
A80: PRM-076 | B80: Uy tín & Hạng | C80: W_RATING | D80: Trọng số điểm đánh giá trung bình | E80: 0.3 | F80: % | H80: =COUNTIF('03_BR'!$K:$K,"*"&A80&"*") -> 1 | I80: BR-R-072 | J80: Admin (UC-46)
A81: PRM-077 | B81: Uy tín & Hạng | C81: W_COMPLETE | D81: Trọng số tỷ lệ hoàn thành đơn đã nhận | E81: 0.2 | F81: % | H81: =COUNTIF('03_BR'!$K:$K,"*"&A81&"*") -> 1 | I81: BR-R-072 | J81: Admin (UC-46)
A82: PRM-078 | B82: Uy tín & Hạng | C82: W_COMPLAINT | D82: Trọng số khiếu nại (điểm trừ) | E82: 0.15 | F82: % | G82: Tỷ lệ khiếu nại bị xử thua càng cao, điểm càng thấp. | H82: =COUNTIF('03_BR'!$K:$K,"*"&A82&"*") -> 1 | I82: BR-R-072 | J82: Admin (UC-46)
A83: PRM-079 | B83: Uy tín & Hạng | C83: TIER_BRONZE | D83: Điều kiện lên hạng Đồng | E83: ≥ 55 điểm & ≥ 5 đơn | H83: =COUNTIF('03_BR'!$K:$K,"*"&A83&"*") -> 1 | I83: BR-R-073 | J83: Admin (UC-46)
A84: PRM-080 | B84: Uy tín & Hạng | C84: TIER_SILVER | D84: Điều kiện lên hạng Bạc | E84: ≥ 70 điểm & ≥ 20 đơn | H84: =COUNTIF('03_BR'!$K:$K,"*"&A84&"*") -> 1 | I84: BR-R-073 | J84: Admin (UC-46)
A85: PRM-081 | B85: Uy tín & Hạng | C85: TIER_GOLD | D85: Điều kiện lên hạng Vàng | E85: ≥ 85 điểm & ≥ 60 đơn | H85: =COUNTIF('03_BR'!$K:$K,"*"&A85&"*") -> 1 | I85: BR-R-073 | J85: Admin (UC-46)
A86: PRM-082 | B86: Uy tín & Hạng | C86: TIER_DIAMOND | D86: Điều kiện lên hạng Kim cương | E86: ≥ 95 điểm & ≥ 150 đơn | H86: =COUNTIF('03_BR'!$K:$K,"*"&A86&"*") -> 1 | I86: BR-R-073 | J86: Admin (UC-46)
A87: PRM-083 | B87: Uy tín & Hạng | C87: CONC_TIER | D87: Số đơn đang giao đồng thời tối đa theo hạng | E87: Tân binh 3 / Đồng 5 / Bạc 8 / Vàng 12 / Kim cương 15 | H87: =COUNTIF('03_BR'!$K:$K,"*"&A87&"*") -> 1 | I87: BR-R-028 | J87: Admin (UC-46)
A88: PRM-084 | B88: Uy tín & Hạng | C88: VALUE_TIER | D88: Tổng giá trị khai báo đang giữ tối đa theo hạng | E88: Tân binh 3 / Đồng 6 / Bạc 10 / Vàng 15 / Kim cương 20 (triệu đồng) | H88: =COUNTIF('03_BR'!$K:$K,"*"&A88&"*") -> 1 | I88: BR-R-028 | J88: Admin (UC-46)
A89: PRM-085 | B89: Uy tín & Hạng | C89: TRUST_RESTRICT | D89: Ngưỡng hạn chế nhận đơn | E89: 30 | F89: điểm | G89: Điểm dưới ngưỡng: chỉ nhận đơn giá trị thấp. | H89: =COUNTIF('03_BR'!$K:$K,"*"&A89&"*") -> 1 | I89: BR-R-074 | J89: Admin (UC-46)
A90: PRM-086 | B90: Uy tín & Hạng | C90: TRUST_REVIEW | D90: Ngưỡng chuyển Admin xem xét khóa | E90: 20 | F90: điểm | H90: =COUNTIF('03_BR'!$K:$K,"*"&A90&"*") -> 1 | I90: BR-R-074 | J90: Admin (UC-46)
A91: PRM-087 | B91: Uy tín & Hạng | C91: REVIEW_WINDOW | D91: Thời hạn gửi đánh giá sau khi hoàn tất | E91: 7 | F91: ngày | H91: =COUNTIF('03_BR'!$K:$K,"*"&A91&"*") -> 1 | I91: BR-R-070 | J91: Admin (UC-46)
A92: PRM-088 | B92: Uy tín & Hạng | C92: CANCEL_LIMIT | D92: Số lần người giao hủy tối đa trong 30 ngày | E92: 3 | F92: lần | G92: Vượt quá bị tạm khóa nhận đơn. | H92: =COUNTIF('03_BR'!$K:$K,"*"&A92&"*") -> 1 | I92: BR-R-075 | J92: Admin (UC-46)
A93: PRM-089 | B93: Uy tín & Hạng | C93: CANCEL_BAN | D93: Thời gian tạm khóa nhận đơn do hủy quá nhiều | E93: 3 | F93: ngày | H93: =COUNTIF('03_BR'!$K:$K,"*"&A93&"*") -> 1 | I93: BR-R-075 | J93: Admin (UC-46)
A94: PRM-090 | B94: Uy tín & Hạng | C94: CANCEL_PENALTY | D94: Điểm trừ mỗi lần người giao hủy sau khi nhận | E94: 5 | F94: điểm | H94: =COUNTIF('03_BR'!$K:$K,"*"&A94&"*") -> 2 | I94: BR-R-043, BR-R-075 | J94: Admin (UC-46)
A95: PRM-091 | B95: Theo dõi & Vận hành | C95: GPS_INTERVAL | D95: Chu kỳ gửi vị trí GPS | E95: 15 | F95: giây | G95: Khi người giao đang ở trạng thái Đã lấy hàng/Đang giao và ứng dụng ở foreground. | H95: =COUNTIF('03_BR'!$K:$K,"*"&A95&"*") -> 1 | I95: BR-R-041 | J95: Admin (UC-46)
A96: PRM-092 | B96: Theo dõi & Vận hành | C96: TRACK_TTL | D96: Thời gian lưu điểm vị trí chi tiết | E96: 12 | F96: tháng | G96: MongoDB TTL index. | H96: =COUNTIF('03_BR'!$K:$K,"*"&A96&"*") -> 1 | I96: BR-N-038 | J96: Admin (UC-46)
A97: PRM-093 | B97: Theo dõi & Vận hành | C97: CHAT_TTL | D97: Thời gian lưu tin nhắn chat | E97: 12 | F97: tháng | H97: =COUNTIF('03_BR'!$K:$K,"*"&A97&"*") -> 1 | I97: BR-N-038 | J97: Admin (UC-46)
A98: PRM-094 | B98: Theo dõi & Vận hành | C98: DELIVERY_OTP_LEN | D98: Độ dài OTP giao hàng | E98: 6 | F98: chữ số | G98: Gửi cho người nhận. | H98: =COUNTIF('03_BR'!$K:$K,"*"&A98&"*") -> 1 | I98: BR-R-039 | J98: Admin (UC-46)
A99: PRM-095 | B99: Theo dõi & Vận hành | C99: DELIVERY_OTP_FAIL | D99: Số lần nhập sai OTP giao hàng tối đa | E99: 5 | F99: lần | G99: Quá số lần: khóa nhập OTP 30 phút, hướng dẫn liên hệ Hỗ trợ. | H99: =COUNTIF('03_BR'!$K:$K,"*"&A99&"*") -> 1 | I99: BR-R-039 | J99: Admin (UC-46)
A100: PRM-096 | B100: Theo dõi & Vận hành | C100: DELIVERY_OTP_LOCK | D100: Thời gian khóa nhập OTP giao hàng khi nhập sai quá số lần | E100: 30 | F100: phút | H100: =COUNTIF('03_BR'!$K:$K,"*"&A100&"*") -> 1 | I100: BR-R-039 | J100: Admin (UC-46)
A101: PRM-097 | B101: Theo dõi & Vận hành | C101: QR_TTL | D101: Thời hạn mã QR bàn giao | E101: 10 | F101: phút | G101: Mã QR có chữ ký, tự làm mới. | H101: =COUNTIF('03_BR'!$K:$K,"*"&A101&"*") -> 1 | I101: BR-R-048 | J101: Admin (UC-46)
A102: PRM-098 | B102: Theo dõi & Vận hành | C102: NOTIF_RETRY | D102: Số lần thử lại gửi thông báo | E102: 3 | F102: lần | G102: Email/SMS gửi lỗi. | H102: =COUNTIF('03_BR'!$K:$K,"*"&A102&"*") -> 0 | J102: Admin (UC-46)
A103: PRM-099 | B103: Theo dõi & Vận hành | C103: MATCH_DETOUR | D103: Độ lệch tuyến tối đa khi ghép đơn–chuyến | E103: 3 | F103: km | G103: Khoảng cách từ điểm lấy/giao đến đường đi của chuyến. | H103: =COUNTIF('03_BR'!$K:$K,"*"&A103&"*") -> 1 | I103: BR-R-036 | J103: Admin (UC-46)
A104: PRM-100 | B104: Theo dõi & Vận hành | C104: MATCH_TOPN | D104: Số gợi ý ghép tối đa | E104: 10 | F104: gợi ý | H104: =COUNTIF('03_BR'!$K:$K,"*"&A104&"*") -> 1 | I104: BR-R-036 | J104: Admin (UC-46)
A105: PRM-101 | B105: Theo dõi & Vận hành | C105: BATCH_MAX | D105: Số đơn gộp tối đa cho một lượt giao | E105: 5 | F105: đơn | H105: =COUNTIF('03_BR'!$K:$K,"*"&A105&"*") -> 1 | I105: BR-R-046 | J105: Admin (UC-46)
A106: PRM-102 | B106: Theo dõi & Vận hành | C106: RELAY_MAX | D106: Số chặng tối đa của đơn giao tiếp sức | E106: 3 | F106: chặng | H106: =COUNTIF('03_BR'!$K:$K,"*"&A106&"*") -> 1 | I106: BR-R-047 | J106: Admin (UC-46)
A107: PRM-103 | B107: Theo dõi & Vận hành | C107: KYC_SLA | D107: Thời hạn duyệt hồ sơ xác minh | E107: 24 | F107: giờ làm việc | H107: =COUNTIF('03_BR'!$K:$K,"*"&A107&"*") -> 0 | J107: Admin (UC-46)
A108: PRM-104 | B108: Theo dõi & Vận hành | C108: DISPUTE_RESP | D108: Thời hạn phản hồi đầu tiên cho khiếu nại | E108: 24 | F108: giờ | H108: =COUNTIF('03_BR'!$K:$K,"*"&A108&"*") -> 1 | I108: BR-R-078 | J108: Admin (UC-46)
A109: PRM-105 | B109: Theo dõi & Vận hành | C109: DISPUTE_RESOLVE | D109: Thời hạn xử lý xong khiếu nại | E109: 5 | F109: ngày làm việc | H109: =COUNTIF('03_BR'!$K:$K,"*"&A109&"*") -> 1 | I109: BR-R-078 | J109: Admin (UC-46)
A110: PRM-106 | B110: Theo dõi & Vận hành | C110: APPEAL_WINDOW | D110: Thời hạn kháng nghị phán quyết khiếu nại | E110: 48 | F110: giờ | G110: Mỗi bên được kháng nghị 1 lần. | H110: =COUNTIF('03_BR'!$K:$K,"*"&A110&"*") -> 1 | I110: BR-R-078 | J110: Admin (UC-46)
A111: PRM-107 | B111: Theo dõi & Vận hành | C111: AUDIT_KEEP | D111: Thời gian lưu nhật ký kiểm toán | E111: 5 | F111: năm | H111: =COUNTIF('03_BR'!$K:$K,"*"&A111&"*") -> 1 | I111: BR-N-038 | J111: Admin (UC-46)
A112: PRM-108 | B112: Theo dõi & Vận hành | C112: LEDGER_KEEP | D112: Thời gian lưu sổ cái giao dịch | E112: 10 | F112: năm | G112: Dự kiến theo quy định lưu trữ chứng từ kế toán; cần xác nhận với kế toán/pháp chế. | H112: =COUNTIF('03_BR'!$K:$K,"*"&A112&"*") -> 1 | I112: BR-N-038 | J112: Admin (UC-46)
...

Sheet 07_Biểu_phí_Mô_phỏng
A1: Biểu phí và công cụ mô phỏng
A2: Nhập thông số ở khung A (ô vàng) để xem giá gợi ý, hoa hồng, dòng tiền; khung D kiểm thử công thức giá bằng 20 ca mẫu
A4: A. Đầu vào mô phỏng
A5: Khoảng cách (km) | B5: 8 | C5: Quãng đường đường bộ
A6: Khối lượng (kg) | B6: 3 | C6: Tối đa theo tham số MAX_WEIGHT
A7: Cạnh dài nhất (cm) | B7: 40 | C7: Dùng xác định cỡ hàng
A8: Mức khẩn cấp | B8: Trong ngày | C8: Thường / Trong ngày / Gấp
A9: Giá trị khai báo (VND) | B9: 500000 | C9: Tối đa theo MAX_DECLARED
A10: Mua bảo hiểm | B10: Có | C10: Có / Không
A11: Hạng người giao | B11: Đồng | C11: Tân binh / Đồng / Bạc / Vàng / Kim cương
A12: Giá thống nhất so với giá gợi ý | B12: 1 | C12: 100% = đúng giá gợi ý; nằm trong biên chào giá
A13: Giảm giá khuyến mãi (VND) | B13: 0 | C13: Nền tảng chịu chi phí
A15: B. Kết quả tính toán (công thức, không nhập)
A16: Kiểm tra giới hạn hàng hóa | B16: {=IF(OR($B$6>INDEX('06_Tham_số'!$E:$E,MATCH("PRM-012",'06_Tham_số'!$A:$A,0)),$B$7>INDEX('06_Tham_số'!$E:$E,MATCH("PRM-013",'06_Tham_số'!$A:$A,0)),$B$9>INDEX('06_Tham_số'!$E:$E,MATCH("PRM-016",'06_Tham_số'!$A:$A,0))),"VƯỢT GIỚI HẠN","Hợp lệ")} -> Hợp lệ | C16: Khối lượng, cạnh dài, giá trị khai báo
A17: Phí cơ bản + quãng đường | B17: {=INDEX('06_Tham_số'!$E:$E,MATCH("PRM-026",'06_Tham_số'!$A:$A,0))+MAX(0,MIN($B$5,INDEX('06_Tham_số'!$E:$E,MATCH("PRM-029",'06_Tham_số'!$A:$A,0)))-INDEX('06_Tham_số'!$E:$E,MATCH("PRM-027",'06_Tham_số'!$A:$A,0)))*INDEX('06_Tham_số'!$E:$E,MATCH("PRM-028",'06_Tham_số'!$A:$A,0))+MAX(0,$B$5-INDEX('06_Tham_số'!$E:$E,MATCH("PRM-029",'06_Tham_số'!$A:$A,0)))*INDEX('06_Tham_số'!$E:$E,MATCH("PRM-030",'06_Tham_số'!$A:$A,0))} -> 31000 | C17: BASE_FARE + phần vượt BASE_KM × PER_KM + phần vượt LONG_KM × PER_KM_LONG
A18: Phụ phí khối lượng | B18: {=IF($B$6<=2,0,IF($B$6<=5,INDEX('06_Tham_số'!$E:$E,MATCH("PRM-031",'06_Tham_số'!$A:$A,0)),IF($B$6<=10,INDEX('06_Tham_số'!$E:$E,MATCH("PRM-032",'06_Tham_số'!$A:$A,0)),INDEX('06_Tham_số'!$E:$E,MATCH("PRM-033",'06_Tham_số'!$A:$A,0)))))} -> 5000 | C18: ≤2 kg: 0; >2–5; >5–10; >10–20 kg
A19: Cỡ hàng | B19: {=IF($B$7<=INDEX('06_Tham_số'!$E:$E,MATCH("PRM-014",'06_Tham_số'!$A:$A,0)),"Nhỏ",IF($B$7<=INDEX('06_Tham_số'!$E:$E,MATCH("PRM-015",'06_Tham_số'!$A:$A,0)),"Vừa","Lớn"))} -> Vừa | C19: Theo cạnh dài nhất
A20: Phụ phí cỡ | B20: {=IF($B$7<=INDEX('06_Tham_số'!$E:$E,MATCH("PRM-014",'06_Tham_số'!$A:$A,0)),0,IF($B$7<=INDEX('06_Tham_số'!$E:$E,MATCH("PRM-015",'06_Tham_số'!$A:$A,0)),INDEX('06_Tham_số'!$E:$E,MATCH("PRM-034",'06_Tham_số'!$A:$A,0)),INDEX('06_Tham_số'!$E:$E,MATCH("PRM-035",'06_Tham_số'!$A:$A,0))))} -> 5000
A21: Tổng trước hệ số khẩn cấp | B21: =$B$17+$B$18+$B$20 -> 41000
A22: Hệ số khẩn cấp | B22: {=IF($B$8="Gấp",INDEX('06_Tham_số'!$E:$E,MATCH("PRM-036",'06_Tham_số'!$A:$A,0)),IF($B$8="Trong ngày",INDEX('06_Tham_số'!$E:$E,MATCH("PRM-037",'06_Tham_số'!$A:$A,0)),1))} -> 1.2
A23: Giá gợi ý (phí giao) | B23: {=MAX(INDEX('06_Tham_số'!$E:$E,MATCH("PRM-038",'06_Tham_số'!$A:$A,0)),CEILING(ROUND($B$21*$B$22,2),INDEX('06_Tham_số'!$E:$E,MATCH("PRM-053",'06_Tham_số'!$A:$A,0))))} -> 49500 | C23: Làm tròn lên bội số ROUND_FEE, không thấp hơn MIN_FARE
A24: Biên dưới giá chào | B24: {=CEILING($B$23*INDEX('06_Tham_số'!$E:$E,MATCH("PRM-039",'06_Tham_số'!$A:$A,0)),INDEX('06_Tham_số'!$E:$E,MATCH("PRM-053",'06_Tham_số'!$A:$A,0)))} -> 35000 | C24: BID_MIN × giá gợi ý
A25: Biên trên giá chào | B25: {=CEILING($B$23*INDEX('06_Tham_số'!$E:$E,MATCH("PRM-040",'06_Tham_số'!$A:$A,0)),INDEX('06_Tham_số'!$E:$E,MATCH("PRM-053",'06_Tham_số'!$A:$A,0)))} -> 74500 | C25: BID_MAX × giá gợi ý
A26: Giá thống nhất (phí giao) | B26: {=CEILING(ROUND($B$23*$B$12,2),INDEX('06_Tham_số'!$E:$E,MATCH("PRM-053",'06_Tham_số'!$A:$A,0)))} -> 49500 | C26: Giá được ký quỹ và là cơ sở tính hoa hồng
A27: Kiểm tra biên giá chào | B27: =IF(AND($B$26>=$B$24,$B$26<=$B$25),"Hợp lệ","Ngoài biên") -> Hợp lệ
A28: Phí bảo hiểm | B28: {=IF($B$10="Có",MAX(INDEX('06_Tham_số'!$E:$E,MATCH("PRM-048",'06_Tham_số'!$A:$A,0)),ROUND($B$9*INDEX('06_Tham_số'!$E:$E,MATCH("PRM-047",'06_Tham_số'!$A:$A,0)),0)),0)} -> 5000 | C28: INS_RATE × giá trị khai báo, tối thiểu INS_MIN
A29: Khuyến mãi áp dụng | B29: =MIN($B$13,$B$26) -> 0 | C29: Không vượt phí giao
A30: Người gửi thanh toán (ký quỹ) | B30: =$B$26+$B$28-$B$29 -> 54500 | C30: Phí giao + bảo hiểm − khuyến mãi
A31: Tỷ lệ hoa hồng theo hạng | B31: {=INDEX($B$52:$B$56,MATCH($B$11,$A$52:$A$56,0))} -> 0.07 | C31: Tra bảng khung C
A32: Hoa hồng nền tảng | B32: =ROUNDDOWN($B$26*$B$31,0) -> 3465 | C32: Làm tròn xuống đến đồng
A33: Khấu trừ thuế (nếu cấu hình) | B33: {=ROUNDDOWN($B$26*INDEX('06_Tham_số'!$E:$E,MATCH("PRM-055",'06_Tham_số'!$A:$A,0)),0)} -> 0 | C33: Mặc định 0%
A34: Thu nhập ròng của người giao | B34: =$B$26-$B$32-$B$33 -> 46035 | C34: Phần lẻ do làm tròn thuộc người giao
A35: Trích Quỹ bảo đảm từ hoa hồng | B35: {=ROUNDDOWN($B$32*INDEX('06_Tham_số'!$E:$E,MATCH("PRM-049",'06_Tham_số'!$A:$A,0)),0)} -> 346 | C35: FUND_SHARE × hoa hồng
A36: Quỹ bảo đảm nhận (gồm bảo hiểm) | B36: =$B$35+$B$28 -> 5346
A37: Doanh thu nền tảng (trước khuyến mãi) | B37: =$B$32-$B$35 -> 3119
A38: Doanh thu nền tảng sau khuyến mãi | B38: =$B$37-$B$29 -> 3119
A39: Chênh lệch cân đối | B39: =($B$30+$B$29)-($B$34+$B$33+$B$37+$B$36) -> 0 | C39: Người gửi trả + chi phí khuyến mãi = thu nhập ròng + thuế + doanh thu + quỹ; phải bằng 0
A40: Trạng thái cân đối | B40: =IF($B$39=0,"Cân bằng","LỆCH") -> Cân bằng
A50: C. Bảng hoa hồng theo hạng (lấy từ sheet 06)
A51: Hạng | B51: Tỷ lệ hoa hồng
A52: Tân binh | B52: {=INDEX('06_Tham_số'!$E:$E,MATCH("PRM-042",'06_Tham_số'!$A:$A,0))} -> 0.08
A53: Đồng | B53: {=INDEX('06_Tham_số'!$E:$E,MATCH("PRM-043",'06_Tham_số'!$A:$A,0))} -> 0.07
A54: Bạc | B54: {=INDEX('06_Tham_số'!$E:$E,MATCH("PRM-044",'06_Tham_số'!$A:$A,0))} -> 0.06
A55: Vàng | B55: {=INDEX('06_Tham_số'!$E:$E,MATCH("PRM-045",'06_Tham_số'!$A:$A,0))} -> 0.05
A56: Kim cương | B56: {=INDEX('06_Tham_số'!$E:$E,MATCH("PRM-046",'06_Tham_số'!$A:$A,0))} -> 0.04
A58: D. Kiểm thử công thức giá: 20 ca mẫu (kỳ vọng tính độc lập, so với công thức trong sheet)
A59: Ca kiểm thử | B59: Mã ca | C59: Mô tả đầu vào | D59: Giá kỳ vọng | E59: Giá trong công thức | F59: Kết quả | G59: Khoảng cách (km) | H59: Khối lượng (kg) | I59: Cạnh dài (cm) | J59: Khẩn cấp
A60: Ca 01 | B60: T01 | C60: 1 km, 1 kg, cạnh 20 cm, Thường | D60: 10000 | E60: {=MAX(INDEX('06_Tham_số'!$E:$E,MATCH("PRM-038",'06_Tham_số'!$A:$A,0)),CEILING(ROUND(((INDEX('06_Tham_số'!$E:$E,MATCH("PRM-026",'06_Tham_số'!$A:$A,0))+MAX(0,MIN($G60,INDEX('06_Tham_số'!$E:$E,MATCH("PRM-029",'06_Tham_số'!$A:$A,0)))-INDEX('06_Tham_số'!$E:$E,MATCH("PRM-027",'06_Tham_số'!$A:$A,0)))*INDEX('06_Tham_số'!$E:$E,MATCH("PRM-028",'06_Tham_số'!$A:$A,0))+MAX(0,$G60-INDEX('06_Tham_số'!$E:$E,MATCH("PRM-029",'06_Tham_số'!$A:$A,0)))*INDEX('06_Tham_số'!$E:$E,MATCH("PRM-030",'06_Tham_số'!$A:$A,0)))+IF($H60<=2,0,IF($H60<=5,INDEX('06_Tham_số'!$E:$E,MATCH("PRM-031",'06_Tham_số'!$A:$A,0)),IF($H60<=10,INDEX('06_Tham_số'!$E:$E,MATCH("PRM-032",'06_Tham_số'!$A:$A,0)),INDEX('06_Tham_số'!$E:$E,MATCH("PRM-033",'06_Tham_số'!$A:$A,0)))))+IF($I60<=INDEX('06_Tham_số'!$E:$E,MATCH("PRM-014",'06_Tham_số'!$A:$A,0)),0,IF($I60<=INDEX('06_Tham_số'!$E:$E,MATCH("PRM-015",'06_Tham_số'!$A:$A,0)),INDEX('06_Tham_số'!$E:$E,MATCH("PRM-034",'06_Tham_số'!$A:$A,0)),INDEX('06_Tham_số'!$E:$E,MATCH("PRM-035",'06_Tham_số'!$A:$A,0)))))*IF($J60="Gấp",INDEX('06_Tham_số'!$E:$E,MATCH("PRM-036",'06_Tham_số'!$A:$A,0)),IF($J60="Trong ngày",INDEX('06_Tham_số'!$E:$E,MATCH("PRM-037",'06_Tham_số'!$A:$A,0)),1)),2),INDEX('06_Tham_số'!$E:$E,MATCH("PRM-053",'06_Tham_số'!$A:$A,0))))} -> 10000 | F60: =IF(D60=E60,"ĐẠT","LỖI") -> ĐẠT | G60: 1 | H60: 1 | I60: 20 | J60: Thường
A61: Ca 02 | B61: T02 | C61: 2 km, 2 kg, cạnh 30 cm, Thường | D61: 10000 | E61: {=MAX(INDEX('06_Tham_số'!$E:$E,MATCH("PRM-038",'06_Tham_số'!$A:$A,0)),CEILING(ROUND(((INDEX('06_Tham_số'!$E:$E,MATCH("PRM-026",'06_Tham_số'!$A:$A,0))+MAX(0,MIN($G61,INDEX('06_Tham_số'!$E:$E,MATCH("PRM-029",'06_Tham_số'!$A:$A,0)))-INDEX('06_Tham_số'!$E:$E,MATCH("PRM-027",'06_Tham_số'!$A:$A,0)))*INDEX('06_Tham_số'!$E:$E,MATCH("PRM-028",'06_Tham_số'!$A:$A,0))+MAX(0,$G61-INDEX('06_Tham_số'!$E:$E,MATCH("PRM-029",'06_Tham_số'!$A:$A,0)))*INDEX('06_Tham_số'!$E:$E,MATCH("PRM-030",'06_Tham_số'!$A:$A,0)))+IF($H61<=2,0,IF($H61<=5,INDEX('06_Tham_số'!$E:$E,MATCH("PRM-031",'06_Tham_số'!$A:$A,0)),IF($H61<=10,INDEX('06_Tham_số'!$E:$E,MATCH("PRM-032",'06_Tham_số'!$A:$A,0)),INDEX('06_Tham_số'!$E:$E,MATCH("PRM-033",'06_Tham_số'!$A:$A,0)))))+IF($I61<=INDEX('06_Tham_số'!$E:$E,MATCH("PRM-014",'06_Tham_số'!$A:$A,0)),0,IF($I61<=INDEX('06_Tham_số'!$E:$E,MATCH("PRM-015",'06_Tham_số'!$A:$A,0)),INDEX('06_Tham_số'!$E:$E,MATCH("PRM-034",'06_Tham_số'!$A:$A,0)),INDEX('06_Tham_số'!$E:$E,MATCH("PRM-035",'06_Tham_số'!$A:$A,0)))))*IF($J61="Gấp",INDEX('06_Tham_số'!$E:$E,MATCH("PRM-036",'06_Tham_số'!$A:$A,0)),IF($J61="Trong ngày",INDEX('06_Tham_số'!$E:$E,MATCH("PRM-037",'06_Tham_số'!$A:$A,0)),1)),2),INDEX('06_Tham_số'!$E:$E,MATCH("PRM-053",'06_Tham_số'!$A:$A,0))))} -> 10000 | F61: =IF(D61=E61,"ĐẠT","LỖI") -> ĐẠT | G61: 2 | H61: 2 | I61: 30 | J61: Thường
A62: Ca 03 | B62: T03 | C62: 3 km, 2.5 kg, cạnh 30 cm, Thường | D62: 18500 | E62: {=MAX(INDEX('06_Tham_số'!$E:$E,MATCH("PRM-038",'06_Tham_số'!$A:$A,0)),CEILING(ROUND(((INDEX('06_Tham_số'!$E:$E,MATCH("PRM-026",'06_Tham_số'!$A:$A,0))+MAX(0,MIN($G62,INDEX('06_Tham_số'!$E:$E,MATCH("PRM-029",'06_Tham_số'!$A:$A,0)))-INDEX('06_Tham_số'!$E:$E,MATCH("PRM-027",'06_Tham_số'!$A:$A,0)))*INDEX('06_Tham_số'!$E:$E,MATCH("PRM-028",'06_Tham_số'!$A:$A,0))+MAX(0,$G62-INDEX('06_Tham_số'!$E:$E,MATCH("PRM-029",'06_Tham_số'!$A:$A,0)))*INDEX('06_Tham_số'!$E:$E,MATCH("PRM-030",'06_Tham_số'!$A:$A,0)))+IF($H62<=2,0,IF($H62<=5,INDEX('06_Tham_số'!$E:$E,MATCH("PRM-031",'06_Tham_số'!$A:$A,0)),IF($H62<=10,INDEX('06_Tham_số'!$E:$E,MATCH("PRM-032",'06_Tham_số'!$A:$A,0)),INDEX('06_Tham_số'!$E:$E,MATCH("PRM-033",'06_Tham_số'!$A:$A,0)))))+IF($I62<=INDEX('06_Tham_số'!$E:$E,MATCH("PRM-014",'06_Tham_số'!$A:$A,0)),0,IF($I62<=INDEX('06_Tham_số'!$E:$E,MATCH("PRM-015",'06_Tham_số'!$A:$A,0)),INDEX('06_Tham_số'!$E:$E,MATCH("PRM-034",'06_Tham_số'!$A:$A,0)),INDEX('06_Tham_số'!$E:$E,MATCH("PRM-035",'06_Tham_số'!$A:$A,0)))))*IF($J62="Gấp",INDEX('06_Tham_số'!$E:$E,MATCH("PRM-036",'06_Tham_số'!$A:$A,0)),IF($J62="Trong ngày",INDEX('06_Tham_số'!$E:$E,MATCH("PRM-037",'06_Tham_số'!$A:$A,0)),1)),2),INDEX('06_Tham_số'!$E:$E,MATCH("PRM-053",'06_Tham_số'!$A:$A,0))))} -> 18500 | F62: =IF(D62=E62,"ĐẠT","LỖI") -> ĐẠT | G62: 3 | H62: 2.5 | I62: 30 | J62: Thường
A63: Ca 04 | B63: T04 | C63: 5 km, 5 kg, cạnh 50 cm, Thường | D63: 30500 | E63: {=MAX(INDEX('06_Tham_số'!$E:$E,MATCH("PRM-038",'06_Tham_số'!$A:$A,0)),CEILING(ROUND(((INDEX('06_Tham_số'!$E:$E,MATCH("PRM-026",'06_Tham_số'!$A:$A,0))+MAX(0,MIN($G63,INDEX('06_Tham_số'!$E:$E,MATCH("PRM-029",'06_Tham_số'!$A:$A,0)))-INDEX('06_Tham_số'!$E:$E,MATCH("PRM-027",'06_Tham_số'!$A:$A,0)))*INDEX('06_Tham_số'!$E:$E,MATCH("PRM-028",'06_Tham_số'!$A:$A,0))+MAX(0,$G63-INDEX('06_Tham_số'!$E:$E,MATCH("PRM-029",'06_Tham_số'!$A:$A,0)))*INDEX('06_Tham_số'!$E:$E,MATCH("PRM-030",'06_Tham_số'!$A:$A,0)))+IF($H63<=2,0,IF($H63<=5,INDEX('06_Tham_số'!$E:$E,MATCH("PRM-031",'06_Tham_số'!$A:$A,0)),IF($H63<=10,INDEX('06_Tham_số'!$E:$E,MATCH("PRM-032",'06_Tham_số'!$A:$A,0)),INDEX('06_Tham_số'!$E:$E,MATCH("PRM-033",'06_Tham_số'!$A:$A,0)))))+IF($I63<=INDEX('06_Tham_số'!$E:$E,MATCH("PRM-014",'06_Tham_số'!$A:$A,0)),0,IF($I63<=INDEX('06_Tham_số'!$E:$E,MATCH("PRM-015",'06_Tham_số'!$A:$A,0)),INDEX('06_Tham_số'!$E:$E,MATCH("PRM-034",'06_Tham_số'!$A:$A,0)),INDEX('06_Tham_số'!$E:$E,MATCH("PRM-035",'06_Tham_số'!$A:$A,0)))))*IF($J63="Gấp",INDEX('06_Tham_số'!$E:$E,MATCH("PRM-036",'06_Tham_số'!$A:$A,0)),IF($J63="Trong ngày",INDEX('06_Tham_số'!$E:$E,MATCH("PRM-037",'06_Tham_số'!$A:$A,0)),1)),2),INDEX('06_Tham_số'!$E:$E,MATCH("PRM-053",'06_Tham_số'!$A:$A,0))))} -> 30500 | F63: =IF(D63=E63,"ĐẠT","LỖI") -> ĐẠT | G63: 5 | H63: 5 | I63: 50 | J63: Thường
A64: Ca 05 | B64: T05 | C64: 5 km, 5.1 kg, cạnh 51 cm, Thường | D64: 42500 | E64: {=MAX(INDEX('06_Tham_số'!$E:$E,MATCH("PRM-038",'06_Tham_số'!$A:$A,0)),CEILING(ROUND(((INDEX('06_Tham_số'!$E:$E,MATCH("PRM-026",'06_Tham_số'!$A:$A,0))+MAX(0,MIN($G64,INDEX('06_Tham_số'!$E:$E,MATCH("PRM-029",'06_Tham_số'!$A:$A,0)))-INDEX('06_Tham_số'!$E:$E,MATCH("PRM-027",'06_Tham_số'!$A:$A,0)))*INDEX('06_Tham_số'!$E:$E,MATCH("PRM-028",'06_Tham_số'!$A:$A,0))+MAX(0,$G64-INDEX('06_Tham_số'!$E:$E,MATCH("PRM-029",'06_Tham_số'!$A:$A,0)))*INDEX('06_Tham_số'!$E:$E,MATCH("PRM-030",'06_Tham_số'!$A:$A,0)))+IF($H64<=2,0,IF($H64<=5,INDEX('06_Tham_số'!$E:$E,MATCH("PRM-031",'06_Tham_số'!$A:$A,0)),IF($H64<=10,INDEX('06_Tham_số'!$E:$E,MATCH("PRM-032",'06_Tham_số'!$A:$A,0)),INDEX('06_Tham_số'!$E:$E,MATCH("PRM-033",'06_Tham_số'!$A:$A,0)))))+IF($I64<=INDEX('06_Tham_số'!$E:$E,MATCH("PRM-014",'06_Tham_số'!$A:$A,0)),0,IF($I64<=INDEX('06_Tham_số'!$E:$E,MATCH("PRM-015",'06_Tham_số'!$A:$A,0)),INDEX('06_Tham_số'!$E:$E,MATCH("PRM-034",'06_Tham_số'!$A:$A,0)),INDEX('06_Tham_số'!$E:$E,MATCH("PRM-035",'06_Tham_số'!$A:$A,0)))))*IF($J64="Gấp",INDEX('06_Tham_số'!$E:$E,MATCH("PRM-036",'06_Tham_số'!$A:$A,0)),IF($J64="Trong ngày",INDEX('06_Tham_số'!$E:$E,MATCH("PRM-037",'06_Tham_số'!$A:$A,0)),1)),2),INDEX('06_Tham_số'!$E:$E,MATCH("PRM-053",'06_Tham_số'!$A:$A,0))))} -> 42500 | F64: =IF(D64=E64,"ĐẠT","LỖI") -> ĐẠT | G64: 5 | H64: 5.1 | I64: 51 | J64: Thường
A65: Ca 06 | B65: T06 | C65: 8 km, 10 kg, cạnh 50 cm, Trong ngày | D65: 58000 | E65: {=MAX(INDEX('06_Tham_số'!$E:$E,MATCH("PRM-038",'06_Tham_số'!$A:$A,0)),CEILING(ROUND(((INDEX('06_Tham_số'!$E:$E,MATCH("PRM-026",'06_Tham_số'!$A:$A,0))+MAX(0,MIN($G65,INDEX('06_Tham_số'!$E:$E,MATCH("PRM-029",'06_Tham_số'!$A:$A,0)))-INDEX('06_Tham_số'!$E:$E,MATCH("PRM-027",'06_Tham_số'!$A:$A,0)))*INDEX('06_Tham_số'!$E:$E,MATCH("PRM-028",'06_Tham_số'!$A:$A,0))+MAX(0,$G65-INDEX('06_Tham_số'!$E:$E,MATCH("PRM-029",'06_Tham_số'!$A:$A,0)))*INDEX('06_Tham_số'!$E:$E,MATCH("PRM-030",'06_Tham_số'!$A:$A,0)))+IF($H65<=2,0,IF($H65<=5,INDEX('06_Tham_số'!$E:$E,MATCH("PRM-031",'06_Tham_số'!$A:$A,0)),IF($H65<=10,INDEX('06_Tham_số'!$E:$E,MATCH("PRM-032",'06_Tham_số'!$A:$A,0)),INDEX('06_Tham_số'!$E:$E,MATCH("PRM-033",'06_Tham_số'!$A:$A,0)))))+IF($I65<=INDEX('06_Tham_số'!$E:$E,MATCH("PRM-014",'06_Tham_số'!$A:$A,0)),0,IF($I65<=INDEX('06_Tham_số'!$E:$E,MATCH("PRM-015",'06_Tham_số'!$A:$A,0)),INDEX('06_Tham_số'!$E:$E,MATCH("PRM-034",'06_Tham_số'!$A:$A,0)),INDEX('06_Tham_số'!$E:$E,MATCH("PRM-035",'06_Tham_số'!$A:$A,0)))))*IF($J65="Gấp",INDEX('06_Tham_số'!$E:$E,MATCH("PRM-036",'06_Tham_số'!$A:$A,0)),IF($J65="Trong ngày",INDEX('06_Tham_số'!$E:$E,MATCH("PRM-037",'06_Tham_số'!$A:$A,0)),1)),2),INDEX('06_Tham_số'!$E:$E,MATCH("PRM-053",'06_Tham_số'!$A:$A,0))))} -> 58000 | F65: =IF(D65=E65,"ĐẠT","LỖI") -> ĐẠT | G65: 8 | H65: 10 | I65: 50 | J65: Trong ngày
